Workbook

Sheet Scenario_Output
A1: Transactions | H1: Balances | M1: Monthly NR | N1: =P1/1200 -> 0.0083333333 | P1: 10 | Q1: =P1/100 -> 0.1 | R1: =Q1/360 -> 0.00027777778
A2: PD | B2: ED | C2: Transaction | D2: Component | E2: Amount | F2: Entry | H2: UPB | I2: AIR | M2: Daily NR | N2: =R1 -> 0.00027777778
A3: 44592 | B3: =A3 -> 44592 | C3: Purchase | D3: UPB | E3: 100000 | F3: New | H3: =E3 -> 100000 | I3: 0
A4: 44592 | B4: =A4 -> 44592 | C4: Purchase | D4: Interest | E4: 100 | F4: New | H4: =E3 -> 100000 | I4: =E4 -> 100 | M4: Monthly NR | N4: =P4/1200 -> 0.0125 | P4: 15 | Q4: =P4/100 -> 0.15 | R4: =Q4/360 -> 0.00041666667
A5: 44593 | B5: 44593 | C5: accrual | D5: Interest | E5: =H5*$N$2 -> 27.777778 | F5: New | H5: =H4 -> 100000 | I5: =I4+E5 -> 127.77778 | M5: Daily NR | N5: =R4 -> 0.00041666667
A6: 44594 | B6: 44594 | C6: accrual | D6: Interest | E6: =H6*$N$2 -> 27.777778 | F6: New | H6: =H5 -> 100000 | I6: =I5+E6 -> 155.55556
A7: 44595 | B7: 44595 | C7: Remit | E7: 210 | F7: New | H7: =H6 -> 100000 | I7: =I6 -> 155.55556
A8: 44595 | B8: 44595 | C8: Payment | D8: UPB | E8: =-(E7-I7) -> -54.444444 | F8: New | H8: =H7+E8 -> 99945.556 | I8: =I7 -> 155.55556
A9: 44595 | B9: 44595 | C9: Payment | D9: Interest | E9: =-(I8) -> -155.55556 | F9: New | H9: =H7+E8 -> 99945.556 | I9: =I8+E9 -> 0
A10: 44595 | B10: 44595 | C10: accrual | D10: Interest | E10: =H10*$N$2 -> 27.762654 | F10: New | H10: =H9 -> 99945.556 | I10: =E10+I9 -> 27.762654
A11: 44596 | B11: 44596 | C11: accrual | D11: Interest | E11: =ROUND(H10*N2,4) -> 27.7627 | F11: New | H11: =H10 -> 99945.556 | I11: =I10+E11 -> 55.525354
A12: 44597 | B12: 44597 | C12: accrual | D12: Interest | E12: =H10*$N$5 -> 41.643981 | F12: New | H12: =H11 -> 99945.556 | I12: =I11+E12 -> 97.169336
A21: ORIG | B21: ATTRIBUTE_LOAN_AMOUNT_CURRENT | C21: ATTRIBUTE_INTEREST_RECEIVABLE_CONSUMER_CURRENT | D21: 1 | E21: LOAN_AMOUNT = ATTRIBUTE_LOAN_AMOUNT_CURRENT INTEREST_RECEIVABLE = ATTRIBUTE_INTEREST_RECEIVABLE_CONSUMER_CURRENT
A22: Payment | B22: TRANSACTIONS_AMOUNT_REMIT | C22: BALANCES_ENDINGBALANCE_Accrued_Interest_Receivable | D22: 2 | E22: PAYMENT_INTEREST = MIN(REMIT_AMOUNT, AIR_BALANCE), PAYMENT_PRINCIPAL = MAX(REMIT_AMOUNT - PAYMENT_INTEREST, 0)
A23: RC | B23: ATTRIBUTE_INTEREST_RATE_CURRENT | D23: 3 | E23: Do nothing/ Not needed
A24: Accrual | B24: ATTRIBUTE_INTEREST_RATE_CURRENT | C24: BALANCES_ENDINGBALANCE_Unpaid_Principal_Balance | D24: 4 | E24: simple_interest(BALANCES_ENDINGBALANCE_Unpaid_Principal_Balance,ATTRIBUTE_INTEREST_RATE_CURRENT,ATTRIBUTE_ACCRUAL_CONVENTION_CURRENT) | F24: simple_interest(100000,0.10,30/360) → 833.33
B25: ATTRIBUTE_ACCRUAL_CONVENTION_CURRENT

Sheet ORIG
A1: PostingDate | B1: EffectiveDate | C1: InstrumentId | D1: AttributeId | E1: ATTRIBUTE_LOAN_AMOUNT_CURRENT | F1: ATTRIBUTE_INTEREST_RECEIVABLE_CONSUMER_CURRENT

Sheet PMT
A1: PostingDate | B1: EffectiveDate | C1: InstrumentId | D1: AttributeId | E1: TRANSACTIONS_AMOUNT_REMIT

Sheet INT_ACC
A1: PostingDate | B1: EffectiveDate | C1: InstrumentId | D1: AttributeId | E1: ATTRIBUTE_INTEREST_RATE_CURRENT | F1: BALANCES_ENDINGBALANCE_Unpaid_Principal_Balance | G1: BALANCES_ENDINGBALANCE_Accrued_Interest_Receivable | H1: BALANCES_ENDINGBALANCE_Servicing_Interest_Accrual

Sheet RC
A1: PostingDate | B1: EffectiveDate | C1: InstrumentId | D1: AttributeId | E1: ATTRIBUTE_INTEREST_RATE_CURRENT | F1: ATTRIBUTE_INTEREST_RATE_PRIOR

Sheet CALCULATION
A1: ExecutionDate | B1: =IF(INT_ACC!A2="","",INT_ACC!A2)
A2: LoanId | B2: =IF(INT_ACC!C2="","",INT_ACC!C2)
A3: AttributeId | B3: =IF(INT_ACC!D2="","",INT_ACC!D2)
A5: ORIGINATION EVENT
A7: TRANSACTION | B7: AMOUNT | C7: FORMULA
A8: PURCHASE_UPB | B8: =IF(ORIG!E2="",0,ORIG!E2) -> 0 | C8: DIRECT PULL FROM ORIG
A9: PURCHASE_INTEREST | B9: =IF(ORIG!F2="",0,ORIG!F2) -> 0 | C9: DIRECT PULL FROM ORIG
A11: PAYMENT EVENT
A13: TRANSACTION | B13: AMOUNT | C13: FORMULA
A14: REMIT_AMOUNT | B14: =IF(PMT!E2="",0,PMT!E2) -> 0 | C14: DIRECT PULL FROM INT_ACC
A15: AIR_BALANCE | B15: =IF(INT_ACC!G2="",0,INT_ACC!G2) -> 0 | C15: DIRECT PULL FROM PMT
A16: PAYMENT_INTEREST | B16: =MIN(B14,B15) -> 0 | C16: PAYMENT_INTEREST = MIN(REMIT_AMOUNT, AIR_BALANCE)
A17: PAYMENT_PRINCIPAL | B17: =MAX(B14-B16,0) -> 0 | C17: PAYMENT_PRINCIPAL = MAX(REMIT_AMOUNT - PAYMENT_INTEREST, 0)
A19: INTEREST ACCRUAL EVENT / RATE CHANGE
A21: TRANSACTION | B21: AMOUNT | C21: FORMULA
A22: UPB_BALANCE | B22: =IF(INT_ACC!F2="",0,INT_ACC!F2) -> 0 | C22: DIRECT PULL FROM INT_ACC
A23: INTEREST_RATE | B23: =IF('RC'!E2="",INT_ACC!E2,'RC'!E2) -> 0 | C23: IF (RC_IINTEREST_RATE = "", INT_ACC_INTEREST_RATE, RC_IINTEREST_RATE)
A24: INTEREST_ACCRUAL | B24: =(B22*B23)/36000 -> 0 | C24: (UPB_BALANCE x INTEREST_RATE )/36000
A27: TRANSACTIONS
A28: PostingDate | B28: TransactionDate | C28: InstrumentId | D28: Transactiontype | E28: Amount | F28: AttributeId
A29: =IF(E29="","",$B$1) | B29: =IF(E29="","",$B$1) | C29: =IF($E29="","",$B$2) | D29: =IF($E29="","","Servicing_Interest_Accrual") -> Servicing_Interest_Accrual | E29: =ROUND(B24,4) -> 0 | F29: =IF($E29="","",$B$3)
A30: =IF(E30="","",$B$1) | B30: =IF(E30="","",$B$1) | C30: =IF($E30="","",$B$2) | D30: =IF($E30="","","Payment_Interest") -> Payment_Interest | E30: =ROUND(B16,4) -> 0 | F30: =IF($E30="","",$B$3)
A31: =IF(E31="","",$B$1) | B31: =IF(E31="","",$B$1) | C31: =IF($E31="","",$B$2) | D31: =IF($E31="","","Payment_UPB") -> Payment_UPB | E31: =ROUND(B17,4) -> 0 | F31: =IF($E31="","",$B$3)
A32: =IF(E32="","",$B$1) | B32: =IF(E32="","",$B$1) | C32: =IF($E32="","",$B$2) | D32: =IF($E32="","","Purchase_UPB") -> Purchase_UPB | E32: =ROUND(B8,4) -> 0 | F32: =IF($E32="","",$B$3)
A33: =IF(E33="","",$B$1) | B33: =IF(E33="","",$B$1) | C33: =IF($E33="","",$B$2) | D33: =IF($E33="","","Purchase_Interest") -> Purchase_Interest | E33: =ROUND(B9,4) -> 0 | F33: =IF($E33="","",$B$3)

Sheet EXPECTED_INP
A1: 44592
A2: ORIG
A3: PostingDate | B3: EffectiveDate | C3: InstrumentId | D3: AttributeId | E3: ATTRIBUTES_LOAN_AMOUNT_CURRENT | F3: ATTRIBUTES_INTEREST_RECEIVABLE_CONSUMER_CURRENT
A4: 44592 | B4: 44592 | C4: IDHJ-EGNY | D4: 1 | E4: 100000 | F4: 100
A6: INT_ACC
A7: PostingDate | B7: EffectiveDate | C7: InstrumentId | D7: AttributeId | E7: ATTRIBUTES_INTEREST_RATE_CURRENT | F7: BALANCES_BEGINNINGBALANCE_Unpaid_Principal_Balance | G7: BALANCES_BEGINNINGBALANCE_Accrued_Interest_Receivable | H7: BALANCES_BEGINNINGBALANCE_Servicing_Interest_Accrual
A8: 44592 | B8: 44592 | C8: IDHJ-EGNY | D8: 1 | E8: 10 | F8: 0 | G8: 0 | H8: 0
A11: 44593
B12: =TEXT(B15,"mm/dd/yyyy") -> 02/01/2022
A13: INT_ACC
A14: PostingDate | B14: EffectiveDate | C14: InstrumentId | D14: AttributeId | E14: ATTRIBUTES_INTEREST_RATE_CURRENT | F14: BALANCES_BEGINNINGBALANCE_Unpaid_Principal_Balance | G14: BALANCES_BEGINNINGBALANCE_Accrued_Interest_Receivable | H14: BALANCES_BEGINNINGBALANCE_Servicing_Interest_Accrual
A15: 02/01/2022 | B15: 02/01/2022 | C15: IDHJ-EGNY | D15: 1 | E15: 10 | F15: 100000 | G15: 100 | H15: 0
A18: 44594
A20: INT_ACC
A21: PostingDate | B21: EffectiveDate | C21: InstrumentId | D21: AttributeId | E21: ATTRIBUTES_INTEREST_RATE_CURRENT | F21: BALANCES_BEGINNINGBALANCE_Unpaid_Principal_Balance | G21: BALANCES_BEGINNINGBALANCE_Accrued_Interest_Receivable | H21: BALANCES_BEGINNINGBALANCE_Servicing_Interest_Accrual
A22: 44594 | B22: 44594 | C22: IDHJ-EGNY | D22: 1 | E22: 10 | F22: 100000 | G22: 127.7778 | H22: 27.7778
A25: 44595
A27: INT_ACC
A28: PostingDate | B28: EffectiveDate | C28: InstrumentId | D28: AttributeId | E28: ATTRIBUTES_INTEREST_RATE_CURRENT | F28: BALANCES_BEGINNINGBALANCE_Unpaid_Principal_Balance | G28: BALANCES_BEGINNINGBALANCE_Accrued_Interest_Receivable | H28: BALANCES_BEGINNINGBALANCE_Servicing_Interest_Accrual
A29: 44595 | B29: 44595 | C29: IDHJ-EGNY | D29: 1 | E29: 10 | F29: 100000 | G29: 155.5556 | H29: 55.5556
A31: PMT
A32: PostingDate | B32: EffectiveDate | C32: InstrumentId | D32: AttributeId | E32: TRANSACTIONS.AMOUNT.REMIT
A33: 44595 | B33: 44595 | C33: IDHJ-EGNY | D33: 1 | E33: 210
A36: 44596
A38: INT_ACC
A39: PostingDate | B39: EffectiveDate | C39: InstrumentId | D39: AttributeId | E39: ATTRIBUTES_INTEREST_RATE_CURRENT | F39: BALANCES_BEGINNINGBALANCE_Unpaid_Principal_Balance | G39: BALANCES_BEGINNINGBALANCE_Accrued_Interest_Receivable | H39: BALANCES_BEGINNINGBALANCE_Servicing_Interest_Accrual
A40: 44596 | B40: 44596 | C40: IDHJ-EGNY | D40: 1 | E40: 10 | F40: 99945.556 | G40: 27.7627 | H40: =H29+G40 -> 83.3183
A43: 44597
A45: INT_ACC
A46: PostingDate | B46: EffectiveDate | C46: InstrumentId | D46: AttributeId | E46: ATTRIBUTES_INTEREST_RATE_CURRENT | F46: BALANCES_BEGINNINGBALANCE_Unpaid_Principal_Balance | G46: BALANCES_BEGINNINGBALANCE_Accrued_Interest_Receivable | H46: BALANCES_BEGINNINGBALANCE_Servicing_Interest_Accrual
A47: 44597 | B47: 44597 | C47: IDHJ-EGNY | D47: 1 | E47: 10 | F47: 99945.556 | G47: 55.5254 | H47: 111.081
A49: RC
A50: PostingDate | B50: EffectiveDate | C50: InstrumentId | D50: AttributeId | E50: ATTRIBUTES_INTEREST_RATE_CURRENT | F50: ATTRIBUTES_INTEREST_RATE_PRIOR
A51: 44596 | B51: 44596 | C51: IDHJ-EGNY | D51: 1 | E51: 15 | F51: 10

Sheet Events
A1: INT_ACC
A3: Trigger Type
A4: ON MODEL EXECUTION
A6: Source Mapping
A7: Balances | B7: ENDINGBALANCE | C7: UPB,AIR,ACCRUAL
A8: Attribute | B8: NoteRate | C8: Current
A11: PMT
A13: Trigger Type | B13: Trigger Source
A14: ON TRANSACTION POST | B14: Remit
A17: Source Mapping
A18: Transactions | B18: Amount | C18: Remit
A20: ORIG
A21: Trigger Type
A22: ON ATTRIBUTE ADD
A24: Source Mapping
A25: Attribute | B25: Loan_amount | C25: Current
A26: Attribute | B26: INTEREST_RECEIVABLE_CONSUMER | C26: Current
A28: RC
A29: Trigger Type
A30: ON ATTRIBUTE CHANGE
A32: Source Mapping
A33: Attribute | B33: Interest Rate | C33: Current, Prior

Sheet o_Transaction
A1: PostingDate | B1: TransactionDate | C1: InstrumentId | D1: TransactionName | E1: Amount | F1: AttributeId
A2: =CALCULATION!A29 | B2: =CALCULATION!B29 | C2: =CALCULATION!C29 | D2: =IF(A2="","",CALCULATION!D29) | E2: =IF(A2="","",CALCULATION!E29) | F2: =CALCULATION!F29
A3: =CALCULATION!A30 | B3: =CALCULATION!B30 | C3: =CALCULATION!C30 | D3: =IF(A3="","",CALCULATION!D30) | E3: =IF(A3="","",CALCULATION!E30) | F3: =CALCULATION!F30
A4: =CALCULATION!A31 | B4: =CALCULATION!B31 | C4: =CALCULATION!C31 | D4: =IF(A4="","",CALCULATION!D31) | E4: =IF(A4="","",CALCULATION!E31) | F4: =CALCULATION!F31
A5: =CALCULATION!A32 | B5: =CALCULATION!B32 | C5: =CALCULATION!C32 | D5: =IF(A5="","",CALCULATION!D32) | E5: =IF(A5="","",CALCULATION!E32) | F5: =CALCULATION!F32
A6: =CALCULATION!A33 | B6: =CALCULATION!B33 | C6: =CALCULATION!C33 | D6: =IF(A6="","",CALCULATION!D33) | E6: =IF(A6="","",CALCULATION!E33) | F6: =CALCULATION!F33
