Workbook

Sheet Test
A1: Steps | B1: Type | C1: Input
A2: LOAD_REF_DATA | B2: FILE_UPLOAD | C2: TestSBO/ReferenceData/RefData_SBO_EVENTS.xlsx
A3: EVENT_CONFIGURATION | B3: CONFIGURATION | C3: TestSBO/EventConfigurations.json
A4: MODEL_UPLOAD | B4: FILE_UPLOAD | C4: TestSBO/Model/SBO_MODEL_EVENTS_All_Trigger.xlsx
A5: MODEL_CONFIGURATION | B5: CONFIGURATION | C5: ATTRIBUTE
A6: ACTIVITY_UPLOAD | B6: FILE_UPLOAD | C6: TestSBO/ActivityData/ActivityData_JAN1.xlsx
A7: MODEL_EXECUTION | B7: EXECUTION | C7: 44592
A8: MODEL_EXECUTION | B8: EXECUTION | C8: 44593
A9: MODEL_EXECUTION | B9: EXECUTION | C9: 44594
A10: ACTIVITY_UPLOAD | B10: FILE_UPLOAD | C10: TestSBO/ActivityData/ActivityData_FEB3.xlsx
A11: MODEL_EXECUTION | B11: EXECUTION | C11: 44595
A12: MODEL_EXECUTION | B12: EXECUTION | C12: 44596
A13: ACTIVITY_UPLOAD | B13: FILE_UPLOAD | C13: TestSBO/ActivityData/ActivityData_FEB5.xlsx
A14: MODEL_EXECUTION | B14: EXECUTION | C14: 44597

Sheet O_TransactionActivity
A1: TransactionActivity | B1: {"instrumentId": "LOAN1"}
A2: postingDate ASC | B2: attributeId ASC | C2: transactionName ASC | D2: source ASC | E2: effectiveDate ASC | F2: instrumentId | G2: amount | H2: originalPeriodId | I2: accountingPeriod.periodId | J2: isReplayable
A3: 20220131 | B3: 1 | C3: PURCHASE_INTEREST | D3: MODEL | E3: 20220131 | F3: LOAN1 | G3: 100 | H3: 202201 | I3: 202201 | J3: 0
A4: 20220131 | B4: 1 | C4: PURCHASE_UPB | D4: MODEL | E4: 20220131 | F4: LOAN1 | G4: 100000 | H4: 202201 | I4: 202201 | J4: 0
A5: 20220201 | B5: 1 | C5: SERVICING_INTEREST_ACCRUAL | D5: MODEL | E5: 20220201 | F5: LOAN1 | G5: 27.7778 | H5: 202202 | I5: 202202 | J5: 0
A6: 20220202 | B6: 1 | C6: SERVICING_INTEREST_ACCRUAL | D6: MODEL | E6: 20220202 | F6: LOAN1 | G6: 27.7778 | H6: 202202 | I6: 202202 | J6: 0
A7: 20220203 | B7: 1 | C7: PAYMENT_INTEREST | D7: MODEL | E7: 20220203 | F7: LOAN1 | G7: -155.5556 | H7: 202202 | I7: 202202 | J7: 0
A8: 20220203 | B8: 1 | C8: PAYMENT_UPB | D8: MODEL | E8: 20220203 | F8: LOAN1 | G8: -54.4444 | H8: 202202 | I8: 202202 | J8: 0
A9: 20220203 | B9: 1 | C9: REMIT | D9: ETL | E9: 20220203 | F9: LOAN1 | G9: 210 | H9: 202202 | I9: 202202 | J9: 0
A10: 20220203 | B10: 1 | C10: SERVICING_INTEREST_ACCRUAL | D10: MODEL | E10: 20220203 | F10: LOAN1 | G10: 27.7627 | H10: 202202 | I10: 202202 | J10: 0
A11: 20220204 | B11: 1 | C11: SERVICING_INTEREST_ACCRUAL | D11: MODEL | E11: 20220204 | F11: LOAN1 | G11: 27.7627 | H11: 202202 | I11: 202202 | J11: 0
A12: 20220205 | B12: 1 | C12: SERVICING_INTEREST_ACCRUAL | D12: MODEL | E12: 20220205 | F12: LOAN1 | G12: 41.644 | H12: 202202 | I12: 202202 | J12: 0

Sheet O_TransactionActivity2
A1: TransactionActivity | B1: {"instrumentId": "LOAN2"}
A2: postingDate ASC | B2: attributeId ASC | C2: transactionName ASC | D2: source ASC | E2: effectiveDate ASC | F2: instrumentId | G2: amount | H2: originalPeriodId | I2: accountingPeriod.periodId | J2: isReplayable
A3: 20220131 | B3: 1 | C3: PURCHASE_INTEREST | D3: MODEL | E3: 20220131 | F3: LOAN2 | G3: 200 | H3: 202201 | I3: 202201 | J3: 0
A4: 20220131 | B4: 1 | C4: PURCHASE_UPB | D4: MODEL | E4: 20220131 | F4: LOAN2 | G4: 150000 | H4: 202201 | I4: 202201 | J4: 0
A5: 20220201 | B5: 1 | C5: SERVICING_INTEREST_ACCRUAL | D5: MODEL | E5: 20220201 | F5: LOAN2 | G5: 33.3333 | H5: 202202 | I5: 202202 | J5: 0
A6: 20220202 | B6: 1 | C6: SERVICING_INTEREST_ACCRUAL | D6: MODEL | E6: 20220202 | F6: LOAN2 | G6: 33.3333 | H6: 202202 | I6: 202202 | J6: 0
A7: 20220203 | B7: 1 | C7: PAYMENT_INTEREST | D7: MODEL | E7: 20220203 | F7: LOAN2 | G7: -266.6666 | H7: 202202 | I7: 202202 | J7: 0
A8: 20220203 | B8: 1 | C8: PAYMENT_UPB | D8: MODEL | E8: 20220203 | F8: LOAN2 | G8: -43.3334 | H8: 202202 | I8: 202202 | J8: 0
A9: 20220203 | B9: 1 | C9: REMIT | D9: ETL | E9: 20220203 | F9: LOAN2 | G9: 310 | H9: 202202 | I9: 202202 | J9: 0
A10: 20220203 | B10: 1 | C10: SERVICING_INTEREST_ACCRUAL | D10: MODEL | E10: 20220203 | F10: LOAN2 | G10: 33.3237 | H10: 202202 | I10: 202202 | J10: 0
A11: 20220204 | B11: 1 | C11: SERVICING_INTEREST_ACCRUAL | D11: MODEL | E11: 20220204 | F11: LOAN2 | G11: 33.3237 | H11: 202202 | I11: 202202 | J11: 0
A12: 20220205 | B12: 1 | C12: SERVICING_INTEREST_ACCRUAL | D12: MODEL | E12: 20220205 | F12: LOAN2 | G12: 49.9856 | H12: 202202 | I12: 202202 | J12: 0

Sheet O_TransactionActivity3
A1: TransactionActivity | B1: {"instrumentId": "LOAN3"}
A2: postingDate ASC | B2: attributeId ASC | C2: transactionName ASC | D2: source ASC | E2: effectiveDate ASC | F2: instrumentId | G2: amount | H2: originalPeriodId | I2: accountingPeriod.periodId | J2: isReplayable
A3: 20220131 | B3: 1 | C3: PURCHASE_INTEREST | D3: MODEL | E3: 20220131 | F3: LOAN3 | G3: 300 | H3: 202201 | I3: 202201 | J3: 0
A4: 20220131 | B4: 1 | C4: PURCHASE_UPB | D4: MODEL | E4: 20220131 | F4: LOAN3 | G4: 200000 | H4: 202201 | I4: 202201 | J4: 0
A5: 20220201 | B5: 1 | C5: SERVICING_INTEREST_ACCRUAL | D5: MODEL | E5: 20220201 | F5: LOAN3 | G5: 11.1111 | H5: 202202 | I5: 202202 | J5: 0
A6: 20220202 | B6: 1 | C6: SERVICING_INTEREST_ACCRUAL | D6: MODEL | E6: 20220202 | F6: LOAN3 | G6: 11.1111 | H6: 202202 | I6: 202202 | J6: 0
A7: 20220203 | B7: 1 | C7: PAYMENT_INTEREST | D7: MODEL | E7: 20220203 | F7: LOAN3 | G7: -322.2222 | H7: 202202 | I7: 202202 | J7: 0
A8: 20220203 | B8: 1 | C8: PAYMENT_UPB | D8: MODEL | E8: 20220203 | F8: LOAN3 | G8: -87.7778 | H8: 202202 | I8: 202202 | J8: 0
A9: 20220203 | B9: 1 | C9: REMIT | D9: ETL | E9: 20220203 | F9: LOAN3 | G9: 410 | H9: 202202 | I9: 202202 | J9: 0
A10: 20220203 | B10: 1 | C10: SERVICING_INTEREST_ACCRUAL | D10: MODEL | E10: 20220203 | F10: LOAN3 | G10: 11.1062 | H10: 202202 | I10: 202202 | J10: 0
A11: 20220204 | B11: 1 | C11: SERVICING_INTEREST_ACCRUAL | D11: MODEL | E11: 20220204 | F11: LOAN3 | G11: 11.1062 | H11: 202202 | I11: 202202 | J11: 0
A12: 20220205 | B12: 1 | C12: SERVICING_INTEREST_ACCRUAL | D12: MODEL | E12: 20220205 | F12: LOAN3 | G12: 44.4249 | H12: 202202 | I12: 202202 | J12: 0

Sheet O_Attribute
A1: AttributeLevelLtd | B1: {"instrumentId": "LOAN1"}
A2: postingDate ASC | B2: attributeId ASC | C2: metricName ASC | D2: instrumentId | E2: balance.beginningBalance | F2: balance.activity | G2: balance.endingBalance
A3: 20220131 | B3: 1 | C3: ACCRUED_INTEREST_RECEIVABLE | D3: LOAN1 | E3: 0 | F3: 100 | G3: 100
A4: 20220131 | B4: 1 | C4: UNPAID_PRINCIPAL_BALANCE | D4: LOAN1 | E4: 0 | F4: 100000 | G4: 100000
A5: 20220201 | B5: 1 | C5: ACCRUED_INTEREST_RECEIVABLE | D5: LOAN1 | E5: =G3 -> 100 | F5: =F6 -> 27.7778 | G5: =E5+F5 -> 127.7778
A6: 20220201 | B6: 1 | C6: SERVICING_INTEREST_ACCRUAL | D6: LOAN1 | E6: 0 | F6: =O_TransactionActivity!G5 -> 27.7778 | G6: =E6+F6 -> 27.7778
A7: 20220201 | B7: 1 | C7: UNPAID_PRINCIPAL_BALANCE | D7: LOAN1 | E7: =F4 -> 100000 | F7: 0 | G7: =E7+F7 -> 100000
A8: 20220202 | B8: 1 | C8: ACCRUED_INTEREST_RECEIVABLE | D8: LOAN1 | E8: =G5 -> 127.7778 | F8: =F9 -> 27.7778 | G8: =E8+F8 -> 155.5556
A9: 20220202 | B9: 1 | C9: SERVICING_INTEREST_ACCRUAL | D9: LOAN1 | E9: =G6 -> 27.7778 | F9: =E9 -> 27.7778 | G9: =E9+F9 -> 55.5556
A10: 20220202 | B10: 1 | C10: UNPAID_PRINCIPAL_BALANCE | D10: LOAN1 | E10: =G7 -> 100000 | F10: 0 | G10: =E10+F10 -> 100000
A11: 20220203 | B11: 1 | C11: ACCRUED_INTEREST_RECEIVABLE | D11: LOAN1 | E11: =G8 -> 155.5556 | F11: =O_TransactionActivity!G7+O_TransactionActivity!G10 -> -127.7929 | G11: =E11+F11 -> 27.7627
A12: 20220203 | B12: 1 | C12: SERVICING_INTEREST_ACCRUAL | D12: LOAN1 | E12: =G9 -> 55.5556 | F12: =O_TransactionActivity!G10 -> 27.7627 | G12: =E12+F12 -> 83.3183
A13: 20220203 | B13: 1 | C13: UNPAID_PRINCIPAL_BALANCE | D13: LOAN1 | E13: =G10 -> 100000 | F13: =O_TransactionActivity!G8 -> -54.4444 | G13: =E13+F13 -> 99945.556
A14: 20220204 | B14: 1 | C14: ACCRUED_INTEREST_RECEIVABLE | D14: LOAN1 | E14: =G11 -> 27.7627 | F14: =O_TransactionActivity!G11 -> 27.7627 | G14: =E14+F14 -> 55.5254
A15: 20220204 | B15: 1 | C15: SERVICING_INTEREST_ACCRUAL | D15: LOAN1 | E15: =G12 -> 83.3183 | F15: =F14 -> 27.7627 | G15: =E15+F15 -> 111.081
A16: 20220204 | B16: 1 | C16: UNPAID_PRINCIPAL_BALANCE | D16: LOAN1 | E16: =G13 -> 99945.556 | F16: 0 | G16: =E16+F16 -> 99945.556
A17: 20220205 | B17: 1 | C17: ACCRUED_INTEREST_RECEIVABLE | D17: LOAN1 | E17: =G14 -> 55.5254 | F17: =O_TransactionActivity!G12 -> 41.644 | G17: =E17+F17 -> 97.1694
A18: 20220205 | B18: 1 | C18: SERVICING_INTEREST_ACCRUAL | D18: LOAN1 | E18: =G15 -> 111.081 | F18: =F17 -> 41.644 | G18: =E18+F18 -> 152.725
A19: 20220205 | B19: 1 | C19: UNPAID_PRINCIPAL_BALANCE | D19: LOAN1 | E19: =G16 -> 99945.556 | F19: 0 | G19: =E19+F19 -> 99945.556

Sheet O_Instrument
A1: InstrumentLevelLtd | B1: {"instrumentId": "LOAN1"}
A2: postingDate ASC | B2: metricName ASC | C2: instrumentId | D2: balance.beginningBalance | E2: balance.activity | F2: balance.endingBalance
A3: 20220131 | B3: ACCRUED_INTEREST_RECEIVABLE | C3: LOAN1 | D3: 0 | E3: =O_TransactionActivity!G3 -> 100 | F3: =D3+E3 -> 100
A4: 20220131 | B4: UNPAID_PRINCIPAL_BALANCE | C4: LOAN1 | D4: 0 | E4: =O_TransactionActivity!G4 -> 100000 | F4: =D4+E4 -> 100000
A5: 20220201 | B5: ACCRUED_INTEREST_RECEIVABLE | C5: LOAN1 | D5: =F3 -> 100 | E5: =O_TransactionActivity!G5 -> 27.7778 | F5: =D5+E5 -> 127.7778
A6: 20220201 | B6: SERVICING_INTEREST_ACCRUAL | C6: LOAN1 | D6: 0 | E6: =O_TransactionActivity!G6 -> 27.7778 | F6: =D6+E6 -> 27.7778
A7: 20220201 | B7: UNPAID_PRINCIPAL_BALANCE | C7: LOAN1 | D7: =F4 -> 100000 | E7: 0 | F7: =D7+E7 -> 100000
A8: 20220202 | B8: ACCRUED_INTEREST_RECEIVABLE | C8: LOAN1 | D8: =F5 -> 127.7778 | E8: =O_TransactionActivity!G5 -> 27.7778 | F8: =D8+E8 -> 155.5556
A9: 20220202 | B9: SERVICING_INTEREST_ACCRUAL | C9: LOAN1 | D9: =F6 -> 27.7778 | E9: =O_TransactionActivity!G6 -> 27.7778 | F9: =D9+E9 -> 55.5556
A10: 20220202 | B10: UNPAID_PRINCIPAL_BALANCE | C10: LOAN1 | D10: =F7 -> 100000 | E10: 0 | F10: =D10+E10 -> 100000
A11: 20220203 | B11: ACCRUED_INTEREST_RECEIVABLE | C11: LOAN1 | D11: =F8 -> 155.5556 | E11: =O_TransactionActivity!G7+O_TransactionActivity!G10 -> -127.7929 | F11: =D11+E11 -> 27.7627
A12: 20220203 | B12: SERVICING_INTEREST_ACCRUAL | C12: LOAN1 | D12: =F9 -> 55.5556 | E12: =O_TransactionActivity!G10 -> 27.7627 | F12: =D12+E12 -> 83.3183
A13: 20220203 | B13: UNPAID_PRINCIPAL_BALANCE | C13: LOAN1 | D13: =F10 -> 100000 | E13: =O_TransactionActivity!G8 -> -54.4444 | F13: =D13+E13 -> 99945.556
A14: 20220204 | B14: ACCRUED_INTEREST_RECEIVABLE | C14: LOAN1 | D14: =F11 -> 27.7627 | E14: =O_TransactionActivity!G11 -> 27.7627 | F14: =D14+E14 -> 55.5254
A15: 20220204 | B15: SERVICING_INTEREST_ACCRUAL | C15: LOAN1 | D15: =F12 -> 83.3183 | E15: =O_TransactionActivity!G11 -> 27.7627 | F15: =D15+E15 -> 111.081
A16: 20220204 | B16: UNPAID_PRINCIPAL_BALANCE | C16: LOAN1 | D16: =F13 -> 99945.556 | E16: 0 | F16: =D16+E16 -> 99945.556
A17: 20220205 | B17: ACCRUED_INTEREST_RECEIVABLE | C17: LOAN1 | D17: =F14 -> 55.5254 | E17: =O_TransactionActivity!G12 -> 41.644 | F17: =D17+E17 -> 97.1694
A18: 20220205 | B18: SERVICING_INTEREST_ACCRUAL | C18: LOAN1 | D18: =F15 -> 111.081 | E18: =O_TransactionActivity!G12 -> 41.644 | F18: =D18+E18 -> 152.725
A19: 20220205 | B19: UNPAID_PRINCIPAL_BALANCE | C19: LOAN1 | D19: =F16 -> 99945.556 | E19: 0 | F19: =D19+E19 -> 99945.556

Sheet O_Instrument2
A1: InstrumentLevelLtd | B1: {"instrumentId": "LOAN2"}
A2: postingDate ASC | B2: metricName ASC | C2: instrumentId | D2: balance.beginningBalance | E2: balance.activity | F2: balance.endingBalance
A3: 20220131 | B3: ACCRUED_INTEREST_RECEIVABLE | C3: LOAN2 | D3: 0 | E3: =O_TransactionActivity2!G3 -> 200 | F3: =D3+E3 -> 200
A4: 20220131 | B4: UNPAID_PRINCIPAL_BALANCE | C4: LOAN2 | D4: 0 | E4: =O_TransactionActivity2!G4 -> 150000 | F4: =D4+E4 -> 150000
A5: 20220201 | B5: ACCRUED_INTEREST_RECEIVABLE | C5: LOAN2 | D5: =F3 -> 200 | E5: =O_TransactionActivity2!G5 -> 33.3333 | F5: =D5+E5 -> 233.3333
A6: 20220201 | B6: SERVICING_INTEREST_ACCRUAL | C6: LOAN2 | D6: 0 | E6: =O_TransactionActivity2!G6 -> 33.3333 | F6: =D6+E6 -> 33.3333
A7: 20220201 | B7: UNPAID_PRINCIPAL_BALANCE | C7: LOAN2 | D7: =F4 -> 150000 | E7: 0 | F7: =D7+E7 -> 150000
A8: 20220202 | B8: ACCRUED_INTEREST_RECEIVABLE | C8: LOAN2 | D8: =F5 -> 233.3333 | E8: =O_TransactionActivity2!G5 -> 33.3333 | F8: =D8+E8 -> 266.6666
A9: 20220202 | B9: SERVICING_INTEREST_ACCRUAL | C9: LOAN2 | D9: =F6 -> 33.3333 | E9: =O_TransactionActivity2!G6 -> 33.3333 | F9: =D9+E9 -> 66.6666
A10: 20220202 | B10: UNPAID_PRINCIPAL_BALANCE | C10: LOAN2 | D10: =F7 -> 150000 | E10: 0 | F10: =D10+E10 -> 150000
A11: 20220203 | B11: ACCRUED_INTEREST_RECEIVABLE | C11: LOAN2 | D11: =F8 -> 266.6666 | E11: =O_TransactionActivity2!G7+O_TransactionActivity2!G10 -> -233.3429 | F11: =D11+E11 -> 33.3237
A12: 20220203 | B12: SERVICING_INTEREST_ACCRUAL | C12: LOAN2 | D12: =F9 -> 66.6666 | E12: =O_TransactionActivity2!G10 -> 33.3237 | F12: =D12+E12 -> 99.9903
A13: 20220203 | B13: UNPAID_PRINCIPAL_BALANCE | C13: LOAN2 | D13: =F10 -> 150000 | E13: =O_TransactionActivity2!G8 -> -43.3334 | F13: =D13+E13 -> 149956.67
A14: 20220204 | B14: ACCRUED_INTEREST_RECEIVABLE | C14: LOAN2 | D14: =F11 -> 33.3237 | E14: =O_TransactionActivity2!G11 -> 33.3237 | F14: =D14+E14 -> 66.6474
A15: 20220204 | B15: SERVICING_INTEREST_ACCRUAL | C15: LOAN2 | D15: =F12 -> 99.9903 | E15: =O_TransactionActivity2!G11 -> 33.3237 | F15: =D15+E15 -> 133.314
A16: 20220204 | B16: UNPAID_PRINCIPAL_BALANCE | C16: LOAN2 | D16: =F13 -> 149956.67 | E16: 0 | F16: =D16+E16 -> 149956.67
A17: 20220205 | B17: ACCRUED_INTEREST_RECEIVABLE | C17: LOAN2 | D17: =F14 -> 66.6474 | E17: =O_TransactionActivity2!G12 -> 49.9856 | F17: =D17+E17 -> 116.633
A18: 20220205 | B18: SERVICING_INTEREST_ACCRUAL | C18: LOAN2 | D18: =F15 -> 133.314 | E18: =O_TransactionActivity2!G12 -> 49.9856 | F18: =D18+E18 -> 183.2996
A19: 20220205 | B19: UNPAID_PRINCIPAL_BALANCE | C19: LOAN2 | D19: =F16 -> 149956.67 | E19: 0 | F19: =D19+E19 -> 149956.67

Sheet O_Instrument3
A1: InstrumentLevelLtd | B1: {"instrumentId": "LOAN3"}
A2: postingDate ASC | B2: metricName ASC | C2: instrumentId | D2: balance.beginningBalance | E2: balance.activity | F2: balance.endingBalance
A3: 20220131 | B3: ACCRUED_INTEREST_RECEIVABLE | C3: LOAN3 | D3: 0 | E3: =O_TransactionActivity3!G3 -> 300 | F3: =D3+E3 -> 300
A4: 20220131 | B4: UNPAID_PRINCIPAL_BALANCE | C4: LOAN3 | D4: 0 | E4: =O_TransactionActivity3!G4 -> 200000 | F4: =D4+E4 -> 200000
A5: 20220201 | B5: ACCRUED_INTEREST_RECEIVABLE | C5: LOAN3 | D5: =F3 -> 300 | E5: =O_TransactionActivity3!G5 -> 11.1111 | F5: =D5+E5 -> 311.1111
A6: 20220201 | B6: SERVICING_INTEREST_ACCRUAL | C6: LOAN3 | D6: 0 | E6: =O_TransactionActivity3!G6 -> 11.1111 | F6: =D6+E6 -> 11.1111
A7: 20220201 | B7: UNPAID_PRINCIPAL_BALANCE | C7: LOAN3 | D7: =F4 -> 200000 | E7: 0 | F7: =D7+E7 -> 200000
A8: 20220202 | B8: ACCRUED_INTEREST_RECEIVABLE | C8: LOAN3 | D8: =F5 -> 311.1111 | E8: =O_TransactionActivity3!G5 -> 11.1111 | F8: =D8+E8 -> 322.2222
A9: 20220202 | B9: SERVICING_INTEREST_ACCRUAL | C9: LOAN3 | D9: =F6 -> 11.1111 | E9: =O_TransactionActivity3!G6 -> 11.1111 | F9: =D9+E9 -> 22.2222
A10: 20220202 | B10: UNPAID_PRINCIPAL_BALANCE | C10: LOAN3 | D10: =F7 -> 200000 | E10: 0 | F10: =D10+E10 -> 200000
A11: 20220203 | B11: ACCRUED_INTEREST_RECEIVABLE | C11: LOAN3 | D11: =F8 -> 322.2222 | E11: =O_TransactionActivity3!G7+O_TransactionActivity3!G10 -> -311.116 | F11: =D11+E11 -> 11.1062
A12: 20220203 | B12: SERVICING_INTEREST_ACCRUAL | C12: LOAN3 | D12: =F9 -> 22.2222 | E12: =O_TransactionActivity3!G10 -> 11.1062 | F12: =D12+E12 -> 33.3284
A13: 20220203 | B13: UNPAID_PRINCIPAL_BALANCE | C13: LOAN3 | D13: =F10 -> 200000 | E13: =O_TransactionActivity3!G8 -> -87.7778 | F13: =D13+E13 -> 199912.22
A14: 20220204 | B14: ACCRUED_INTEREST_RECEIVABLE | C14: LOAN3 | D14: =F11 -> 11.1062 | E14: =O_TransactionActivity3!G11 -> 11.1062 | F14: =D14+E14 -> 22.2124
A15: 20220204 | B15: SERVICING_INTEREST_ACCRUAL | C15: LOAN3 | D15: =F12 -> 33.3284 | E15: =O_TransactionActivity3!G11 -> 11.1062 | F15: =D15+E15 -> 44.4346
A16: 20220204 | B16: UNPAID_PRINCIPAL_BALANCE | C16: LOAN3 | D16: =F13 -> 199912.22 | E16: 0 | F16: =D16+E16 -> 199912.22
A17: 20220205 | B17: ACCRUED_INTEREST_RECEIVABLE | C17: LOAN3 | D17: =F14 -> 22.2124 | E17: =O_TransactionActivity3!G12 -> 44.4249 | F17: =D17+E17 -> 66.6373
A18: 20220205 | B18: SERVICING_INTEREST_ACCRUAL | C18: LOAN3 | D18: =F15 -> 44.4346 | E18: =O_TransactionActivity3!G12 -> 44.4249 | F18: =D18+E18 -> 88.8595
A19: 20220205 | B19: UNPAID_PRINCIPAL_BALANCE | C19: LOAN3 | D19: =F16 -> 199912.22 | E19: 0 | F19: =D19+E19 -> 199912.22

Sheet O_Metric
A1: MetricLevelLtd | B1: {}
A2: postingDate ASC | B2: metricName ASC | C2: balance.beginningBalance | D2: balance.activity | E2: balance.endingBalance
A3: 20220131 | B3: ACCRUED_INTEREST_RECEIVABLE | C3: =O_Instrument!D3+O_Instrument2!D3+O_Instrument3!D3 -> 0 | D3: =O_Instrument!E3+O_Instrument2!E3+O_Instrument3!E3 -> 600 | E3: =O_Instrument!F3+O_Instrument2!F3+O_Instrument3!F3 -> 600
A4: 20220131 | B4: UNPAID_PRINCIPAL_BALANCE | C4: =O_Instrument!D4+O_Instrument2!D4+O_Instrument3!D4 -> 0 | D4: =O_Instrument!E4+O_Instrument2!E4+O_Instrument3!E4 -> 450000 | E4: =O_Instrument!F4+O_Instrument2!F4+O_Instrument3!F4 -> 450000
A5: 20220201 | B5: ACCRUED_INTEREST_RECEIVABLE | C5: =O_Instrument!D5+O_Instrument2!D5+O_Instrument3!D5 -> 600 | D5: =O_Instrument!E5+O_Instrument2!E5+O_Instrument3!E5 -> 72.2222 | E5: =O_Instrument!F5+O_Instrument2!F5+O_Instrument3!F5 -> 672.2222
A6: 20220201 | B6: SERVICING_INTEREST_ACCRUAL | C6: =O_Instrument!D6+O_Instrument2!D6+O_Instrument3!D6 -> 0 | D6: =O_Instrument!E6+O_Instrument2!E6+O_Instrument3!E6 -> 72.2222 | E6: =O_Instrument!F6+O_Instrument2!F6+O_Instrument3!F6 -> 72.2222
A7: 20220201 | B7: UNPAID_PRINCIPAL_BALANCE | C7: =O_Instrument!D7+O_Instrument2!D7+O_Instrument3!D7 -> 450000 | D7: =O_Instrument!E7+O_Instrument2!E7+O_Instrument3!E7 -> 0 | E7: =O_Instrument!F7+O_Instrument2!F7+O_Instrument3!F7 -> 450000
A8: 20220202 | B8: ACCRUED_INTEREST_RECEIVABLE | C8: =O_Instrument!D8+O_Instrument2!D8+O_Instrument3!D8 -> 672.2222 | D8: =O_Instrument!E8+O_Instrument2!E8+O_Instrument3!E8 -> 72.2222 | E8: =O_Instrument!F8+O_Instrument2!F8+O_Instrument3!F8 -> 744.4444
A9: 20220202 | B9: SERVICING_INTEREST_ACCRUAL | C9: =O_Instrument!D9+O_Instrument2!D9+O_Instrument3!D9 -> 72.2222 | D9: =O_Instrument!E9+O_Instrument2!E9+O_Instrument3!E9 -> 72.2222 | E9: =O_Instrument!F9+O_Instrument2!F9+O_Instrument3!F9 -> 144.4444
A10: 20220202 | B10: UNPAID_PRINCIPAL_BALANCE | C10: =O_Instrument!D10+O_Instrument2!D10+O_Instrument3!D10 -> 450000 | D10: =O_Instrument!E10+O_Instrument2!E10+O_Instrument3!E10 -> 0 | E10: =O_Instrument!F10+O_Instrument2!F10+O_Instrument3!F10 -> 450000
A11: 20220203 | B11: ACCRUED_INTEREST_RECEIVABLE | C11: =O_Instrument!D11+O_Instrument2!D11+O_Instrument3!D11 -> 744.4444 | D11: =O_Instrument!E11+O_Instrument2!E11+O_Instrument3!E11 -> -672.2518 | E11: =O_Instrument!F11+O_Instrument2!F11+O_Instrument3!F11 -> 72.1926
A12: 20220203 | B12: SERVICING_INTEREST_ACCRUAL | C12: =O_Instrument!D12+O_Instrument2!D12+O_Instrument3!D12 -> 144.4444 | D12: =O_Instrument!E12+O_Instrument2!E12+O_Instrument3!E12 -> 72.1926 | E12: =O_Instrument!F12+O_Instrument2!F12+O_Instrument3!F12 -> 216.637
A13: 20220203 | B13: UNPAID_PRINCIPAL_BALANCE | C13: =O_Instrument!D13+O_Instrument2!D13+O_Instrument3!D13 -> 450000 | D13: =O_Instrument!E13+O_Instrument2!E13+O_Instrument3!E13 -> -185.5556 | E13: =O_Instrument!F13+O_Instrument2!F13+O_Instrument3!F13 -> 449814.44
A14: 20220204 | B14: ACCRUED_INTEREST_RECEIVABLE | C14: =O_Instrument!D14+O_Instrument2!D14+O_Instrument3!D14 -> 72.1926 | D14: =O_Instrument!E14+O_Instrument2!E14+O_Instrument3!E14 -> 72.1926 | E14: =O_Instrument!F14+O_Instrument2!F14+O_Instrument3!F14 -> 144.3852
... A19: 20220205 | B19: UNPAID_PRINCIPAL_BALANCE | C19: =O_Instrument!D19+O_Instrument2!D19+O_Instrument3!D19 -> 449814.44 | D19: =O_Instrument!E19+O_Instrument2!E19+O_Instrument3!E19 -> 0 | E19: =O_Instrument!F19+O_Instrument2!F19+O_Instrument3!F19 -> 449814.44

Sheet xxInstrumentAttribute
A1: InstrumentAttribute | B1: {"instrumentId": "SO1"}
A2: postingDate ASC | B2: attributeId ASC | C2: effectiveDate | D2: instrumentId | E2: batchId | F2: endDate | G2: periodId | H2: source | I2: attributes.LOAN_AMOUNT | J2: attributes.ACCRUAL_METHOD | K2: attributes.INTEREST_RATE | L2: attributes.LOAN_TERM | M2: attributes.CAPTURE_DATE | N2: attributes.MATURITY_DATE | O2: attributes.PRINCIPAL_BALANCE_CONSUMER | P2: attributes.LOAN_STATUS | Q2: attributes.MERCHANT_INDUSTRY | R2: attributes.STATUS_AS_OF | S2: attributes.INTEREST_RECEIVABLE_CONSUMER | T2: attributes.NEXT_PAYMENT_DUE_DATE | U2: attributes.LAST_PAYMENT_MADE_DATE
A3: 20220131 | B3: 1 | C3: 2022-01-31T00:00:00.000Z | D3: LOAN1 | E3: 1 | F3: 2022-02-05T00:00:00.000Z | G3: 202201 | H3: ETL | I3: USD | K3: 2022-01-15T18:30:00.000Z | O3: INVOICE | Q3: 0 | R3: INVOICE
