Workbook

Sheet Instructions
A5: Fixed Asset and Depreciation Schedule: Instructions
A6: This worksheet is intended to assist in tracking an organization's fixed assets and annual depreciation estimates. Note: the template assumes that all assets are depreciated on a straight-line basis. For simplicity, an asset's depreciation estimate for its first and last years in service will be calculated at a half-year's rate regardless of how many months the asset was actually in service.
A8: Category | B8: Instructions | C8: Cell / Column / Row
A9: INPUTS
A10: Current Fiscal Year | B10: Enter the current fiscal year in YYYY format (e.g. 2022). | C10: Cell E4
A11: Asset | B11: Enter the name of the individual asset or group of assets being depreciated (e.g. van, copier, computers). Note: use the "+" buttons in the left-hand margin of the template to open additional rows as needed. | C11: Column A
A12: Cost | B12: Enter the acquisition cost of the asset or group of assets. | C12: Column B
A13: Fiscal Year Put Into Service (YYYY) | B13: Enter the fiscal year in which the asset or group of assets was put into service, in YYYY format (e.g. 2017). | C13: Column C
A14: Useful Life (in years) | B14: Enter the estimated useful life of the asset or group of assets in years (between 2 and 50). (For "Land," leave blank.) | C14: Column D
A15: Salvage Value (if other than $0) | B15: Enter the salvage value of the asset or group of assets (in other words, the estimated amount that can be obtained for the asset after its useful life has ended). In most cases, salvage value is assumed to be $0, in which case this cell may be left blank. | C15: Column E
A17: OUTPUTS
A18: Fixed Assets, at Cost | B18: Calculates the total value (cost basis) of all fixed assets on the schedule. | C18: Cell E5
A19: Accumulated Depreciation, as of Fiscal Year End (FYE) | B19: Calculates the total accumulated depreciation of all fixed assets on the schedule as of the end of the current fiscal year (entered in cell E4). | C19: Cell E6
A20: Fixed Assets, net of depreciation, as of FYE | B20: Calculates the current book value of the organization's fixed assets (original cost minus accumulated depreciation) as of the end of the current fiscal year. | C20: Cell E7
A21: Depreciation Amount by Fiscal Year | B21: Calculates annual depreciation estimates for each individual asset or group of assets in columns H and following. Additionally, the template will calculate the organization's total annual depreciation estimate on row 67, columns H and following. | C21: Columns H - AT

Sheet EOD
A1: PostingDate | B1: EffectiveDate | C1: InstrumentId | D1: AttributeId | E1: BALANCES_ENDINGBALANCE_ASSETCOST | F1: ATTRIBUTE_ASSET_NAME_CURRENT | G1: ATTRIBUTE_ACQUISITION_YEAR_CURRENT | H1: ATTRIBUTE_USEFUL_LIFE_CURRENT | I1: ATTRIBUTE_SALVAGE_VALUE_CURRENT

Sheet Depreciation Schedule
E2: Fixed Asset and Depreciation Schedule | M2: Enter input to yellow cells only
G4: Current Fiscal Year | H4: =IF(EOD!$A$2="","",YEAR(EOD!$A$2))
G5: Fixed Assets, at cost | H5: =SUM(E11:E70) -> 0
G6: Accumulated Depreciation as of FYE | H6: =(SUMIF(J10:AW10,"<="&H4,J71:AW71))+I71 -> 0
G7: Fixed Assets, net of depreciation, as of FYE | H7: =H5-H6 -> 0
A9: Asset | E9: Cost | F9: Fiscal Year put into service (yyyy) | G9: Useful Life (in years) | H9: Salvage Value (if other than $0) | K9: Depreciation Amount by Fiscal Year | AY9: Transaction
B10: InstrumentID | C10: PostingDate | D10: AtrributeID | I10: Prior | J10: 2023 | K10: 2023 | L10: 2024 | M10: 2024 | N10: 2025 | O10: 2025 | P10: 2026 | Q10: 2026 | R10: 2027 | S10: 2027 | T10: 2028 | U10: 2028 | V10: 2029 | W10: 2029 | X10: 2030 | Y10: 2030 | Z10: 2031 | AA10: 2031 | AB10: 2032 | AC10: 2032 | AD10: 2033 | AE10: 2033 | AF10: 2034 | AG10: 2034 | AH10: 2035 | AI10: 2035 | AJ10: 2036 | AK10: 2036 | AL10: 2037 | AM10: 2037 | AN10: 2038 | AO10: 2038 | AP10: 2039 | AQ10: 2039 | AR10: 2040 | AS10: 2040 | AT10: 2041 | AU10: 2041 | AV10: 2042 | AW10: 2042 | AY10: PostingDate | AZ10: EffectiveDate | BA10: InstrumentID | BB10: AttributeID | BC10: TransactionName | BD10: Amount
A11: =IF(EOD!$F2="","",EOD!$F2) | B11: =IF(EOD!$C2="","",EOD!$C2) | C11: =IF(EOD!$A2="","",EOD!$A2) | D11: =IF(EOD!$D2="","",EOD!$D2) | E11: =IF(EOD!E2="","",EOD!E2) | F11: =IF(EOD!G2="","",EOD!G2) | G11: =IF(EOD!H2="","",EOD!H2) | H11: =IF(EOD!I2="","",EOD!I2) | I11: =IFERROR(IF(F11<$K$10,(($K$10-F11-1)*((E11-H11)/G11)+(((E11-H11)/G11)/2)),0),0) -> 0 | J11: =IF($F11+$G11=J$10,($E11-$H11)/$G11/2,(IF($F11=J$10,($E11-$H11)/$G11/2,0))) -> #VALUE! | K11: =IFERROR(IF($F11+$G11=K$10,J11,(IF($F11=K$10,J11,(IF($F11>K$10," ",IF(K$10<$G11+$F11,SLN($E11,$H11,$G11)," "))))))," ") | L11: =IF($F11+$G11=L$10,($E11-$H11)/$G11/2,(IF($F11=L$10,($E11-$H11)/$G11/2,0))) -> #VALUE! | M11: =IFERROR(IF($F11+$G11=M$10,L11,(IF($F11=M$10,L11,(IF($F11>M$10," ",IF(M$10<$G11+$F11,SLN($E11,$H11,$G11)," "))))))," ") | N11: =IF($F11+$G11=N$10,($E11-$H11)/$G11/2,(IF($F11=N$10,($E11-$H11)/$G11/2,0))) -> #VALUE! | O11: =IFERROR(IF($F11+$G11=O$10,N11,(IF($F11=O$10,N11,(IF($F11>O$10," ",IF(O$10<$G11+$F11,SLN($E11,$H11,$G11)," "))))))," ") | P11: =IF($F11+$G11=P$10,($E11-$H11)/$G11/2,(IF($F11=P$10,($E11-$H11)/$G11/2,0))) -> #VALUE! | Q11: =IFERROR(IF($F11+$G11=Q$10,P11,(IF($F11=Q$10,P11,(IF($F11>Q$10," ",IF(Q$10<$G11+$F11,SLN($E11,$H11,$G11)," "))))))," ") | R11: =IF($F11+$G11=R$10,($E11-$H11)/$G11/2,(IF($F11=R$10,($E11-$H11)/$G11/2,0))) -> #VALUE! | S11: =IFERROR(IF($F11+$G11=S$10,R11,(IF($F11=S$10,R11,(IF($F11>S$10," ",IF(S$10<$G11+$F11,SLN($E11,$H11,$G11)," "))))))," ") | T11: =IF($F11+$G11=T$10,($E11-$H11)/$G11/2,(IF($F11=T$10,($E11-$H11)/$G11/2,0))) -> #VALUE! | U11: =IFERROR(IF($F11+$G11=U$10,T11,(IF($F11=U$10,T11,(IF($F11>U$10," ",IF(U$10<$G11+$F11,SLN($E11,$H11,$G11)," "))))))," ") | V11: =IF($F11+$G11=V$10,($E11-$H11)/$G11/2,(IF($F11=V$10,($E11-$H11)/$G11/2,0))) -> #VALUE! | W11: =IFERROR(IF($F11+$G11=W$10,V11,(IF($F11=W$10,V11,(IF($F11>W$10," ",IF(W$10<$G11+$F11,SLN($E11,$H11,$G11)," "))))))," ") | X11: =IF($F11+$G11=X$10,($E11-$H11)/$G11/2,(IF($F11=X$10,($E11-$H11)/$G11/2,0))) -> #VALUE! | Y11: =IFERROR(IF($F11+$G11=Y$10,X11,(IF($F11=Y$10,X11,(IF($F11>Y$10," ",IF(Y$10<$G11+$F11,SLN($E11,$H11,$G11)," "))))))," ") | Z11: =IF($F11+$G11=Z$10,($E11-$H11)/$G11/2,(IF($F11=Z$10,($E11-$H11)/$G11/2,0))) -> #VALUE! | AA11: =IFERROR(IF($F11+$G11=AA$10,Z11,(IF($F11=AA$10,Z11,(IF($F11>AA$10," ",IF(AA$10<$G11+$F11,SLN($E11,$H11,$G11)," "))))))," ") | AB11: =IF($F11+$G11=AB$10,($E11-$H11)/$G11/2,(IF($F11=AB$10,($E11-$H11)/$G11/2,0))) -> #VALUE! | AC11: =IFERROR(IF($F11+$G11=AC$10,AB11,(IF($F11=AC$10,AB11,(IF($F11>AC$10," ",IF(AC$10<$G11+$F11,SLN($E11,$H11,$G11)," "))))))," ") | AD11: =IF($F11+$G11=AD$10,($E11-$H11)/$G11/2,(IF($F11=AD$10,($E11-$H11)/$G11/2,0))) -> #VALUE! | AE11: =IFERROR(IF($F11+$G11=AE$10,AD11,(IF($F11=AE$10,AD11,(IF($F11>AE$10," ",IF(AE$10<$G11+$F11,SLN($E11,$H11,$G11)," "))))))," ") | AF11: =IF($F11+$G11=AF$10,($E11-$H11)/$G11/2,(IF($F11=AF$10,($E11-$H11)/$G11/2,0))) -> #VALUE! | AG11: =IFERROR(IF($F11+$G11=AG$10,AF11,(IF($F11=AG$10,AF11,(IF($F11>AG$10," ",IF(AG$10<$G11+$F11,SLN($E11,$H11,$G11)," "))))))," ") | AH11: =IF($F11+$G11=AH$10,($E11-$H11)/$G11/2,(IF($F11=AH$10,($E11-$H11)/$G11/2,0))) -> #VALUE! | AI11: =IFERROR(IF($F11+$G11=AI$10,AH11,(IF($F11=AI$10,AH11,(IF($F11>AI$10," ",IF(AI$10<$G11+$F11,SLN($E11,$H11,$G11)," "))))))," ") | AJ11: =IF($F11+$G11=AJ$10,($E11-$H11)/$G11/2,(IF($F11=AJ$10,($E11-$H11)/$G11/2,0))) -> #VALUE! | AK11: =IFERROR(IF($F11+$G11=AK$10,AJ11,(IF($F11=AK$10,AJ11,(IF($F11>AK$10," ",IF(AK$10<$G11+$F11,SLN($E11,$H11,$G11)," "))))))," ") | AL11: =IF($F11+$G11=AL$10,($E11-$H11)/$G11/2,(IF($F11=AL$10,($E11-$H11)/$G11/2,0))) -> #VALUE! | AM11: =IFERROR(IF($F11+$G11=AM$10,AL11,(IF($F11=AM$10,AL11,(IF($F11>AM$10," ",IF(AM$10<$G11+$F11,SLN($E11,$H11,$G11)," "))))))," ") | AN11: =IF($F11+$G11=AN$10,($E11-$H11)/$G11/2,(IF($F11=AN$10,($E11-$H11)/$G11/2,0))) -> #VALUE! | AO11: =IFERROR(IF($F11+$G11=AO$10,AN11,(IF($F11=AO$10,AN11,(IF($F11>AO$10," ",IF(AO$10<$G11+$F11,SLN($E11,$H11,$G11)," "))))))," ") | AP11: =IF($F11+$G11=AP$10,($E11-$H11)/$G11/2,(IF($F11=AP$10,($E11-$H11)/$G11/2,0))) -> #VALUE! | AQ11: =IFERROR(IF($F11+$G11=AQ$10,AP11,(IF($F11=AQ$10,AP11,(IF($F11>AQ$10," ",IF(AQ$10<$G11+$F11,SLN($E11,$H11,$G11)," "))))))," ") | AR11: =IF($F11+$G11=AR$10,($E11-$H11)/$G11/2,(IF($F11=AR$10,($E11-$H11)/$G11/2,0))) -> #VALUE! | AS11: =IFERROR(IF($F11+$G11=AS$10,AR11,(IF($F11=AS$10,AR11,(IF($F11>AS$10," ",IF(AS$10<$G11+$F11,SLN($E11,$H11,$G11)," "))))))," ") | AT11: =IF($F11+$G11=AT$10,($E11-$H11)/$G11/2,(IF($F11=AT$10,($E11-$H11)/$G11/2,0))) -> #VALUE! | AU11: =IFERROR(IF($F11+$G11=AU$10,AT11,(IF($F11=AU$10,AT11,(IF($F11>AU$10," ",IF(AU$10<$G11+$F11,SLN($E11,$H11,$G11)," "))))))," ") | AV11: =IF($F11+$G11=AV$10,($E11-$H11)/$G11/2,(IF($F11=AV$10,($E11-$H11)/$G11/2,0))) -> #VALUE! | AW11: =IFERROR(IF($F11+$G11=AW$10,AV11,(IF($F11=AW$10,AV11,(IF($F11>AW$10," ",IF(AW$10<$G11+$F11,SLN($E11,$H11,$G11)," "))))))," ") | AY11: =C11 | AZ11: =AY11 | BA11: =B11 | BB11: =D11 | BC11: =IF(BB11="","","Depreciation_Expense") | BD11: =INDEX($K$10:$BD$55, MATCH(BB11, $D$10:$D$55, 0), MATCH($H$4, $K$10:$BD$10, 1)) -> #N/A
A12: =IF(EOD!$F3="","",EOD!$F3) | B12: =IF(EOD!$C3="","",EOD!$C3) | C12: =IF(EOD!$A3="","",EOD!$A3) | D12: =IF(EOD!$D3="","",EOD!$D3) | E12: =IF(EOD!E3="","",EOD!E3) | F12: =IF(EOD!G3="","",EOD!G3) | G12: =IF(EOD!H3="","",EOD!H3) | H12: =IF(EOD!I3="","",EOD!I3) | I12: =IFERROR(IF(F12<$K$10,(($K$10-F12-1)*((E12-H12)/G12)+(((E12-H12)/G12)/2)),0),0) -> 0 | J12: =IF($F12+$G12=J$10,($E12-$H12)/$G12/2,(IF($F12=J$10,($E12-$H12)/$G12/2,0))) -> #VALUE! | K12: =IFERROR(IF($F12+$G12=K$10,J12,(IF($F12=K$10,J12,(IF($F12>K$10," ",IF(K$10<$G12+$F12,SLN($E12,$H12,$G12)," "))))))," ") | L12: =IF($F12+$G12=L$10,($E12-$H12)/$G12/2,(IF($F12=L$10,($E12-$H12)/$G12/2,0))) -> #VALUE! | M12: =IFERROR(IF($F12+$G12=M$10,L12,(IF($F12=M$10,L12,(IF($F12>M$10," ",IF(M$10<$G12+$F12,SLN($E12,$H12,$G12)," "))))))," ") | N12: =IF($F12+$G12=N$10,($E12-$H12)/$G12/2,(IF($F12=N$10,($E12-$H12)/$G12/2,0))) -> #VALUE! | O12: =IFERROR(IF($F12+$G12=O$10,N12,(IF($F12=O$10,N12,(IF($F12>O$10," ",IF(O$10<$G12+$F12,SLN($E12,$H12,$G12)," "))))))," ") | P12: =IF($F12+$G12=P$10,($E12-$H12)/$G12/2,(IF($F12=P$10,($E12-$H12)/$G12/2,0))) -> #VALUE! | Q12: =IFERROR(IF($F12+$G12=Q$10,P12,(IF($F12=Q$10,P12,(IF($F12>Q$10," ",IF(Q$10<$G12+$F12,SLN($E12,$H12,$G12)," "))))))," ") | R12: =IF($F12+$G12=R$10,($E12-$H12)/$G12/2,(IF($F12=R$10,($E12-$H12)/$G12/2,0))) -> #VALUE! | S12: =IFERROR(IF($F12+$G12=S$10,R12,(IF($F12=S$10,R12,(IF($F12>S$10," ",IF(S$10<$G12+$F12,SLN($E12,$H12,$G12)," "))))))," ") | T12: =IF($F12+$G12=T$10,($E12-$H12)/$G12/2,(IF($F12=T$10,($E12-$H12)/$G12/2,0))) -> #VALUE! | U12: =IFERROR(IF($F12+$G12=U$10,T12,(IF($F12=U$10,T12,(IF($F12>U$10," ",IF(U$10<$G12+$F12,SLN($E12,$H12,$G12)," "))))))," ") | V12: =IF($F12+$G12=V$10,($E12-$H12)/$G12/2,(IF($F12=V$10,($E12-$H12)/$G12/2,0))) -> #VALUE! | W12: =IFERROR(IF($F12+$G12=W$10,V12,(IF($F12=W$10,V12,(IF($F12>W$10," ",IF(W$10<$G12+$F12,SLN($E12,$H12,$G12)," "))))))," ") | X12: =IF($F12+$G12=X$10,($E12-$H12)/$G12/2,(IF($F12=X$10,($E12-$H12)/$G12/2,0))) -> #VALUE! | Y12: =IFERROR(IF($F12+$G12=Y$10,X12,(IF($F12=Y$10,X12,(IF($F12>Y$10," ",IF(Y$10<$G12+$F12,SLN($E12,$H12,$G12)," "))))))," ") | Z12: =IF($F12+$G12=Z$10,($E12-$H12)/$G12/2,(IF($F12=Z$10,($E12-$H12)/$G12/2,0))) -> #VALUE! | AA12: =IFERROR(IF($F12+$G12=AA$10,Z12,(IF($F12=AA$10,Z12,(IF($F12>AA$10," ",IF(AA$10<$G12+$F12,SLN($E12,$H12,$G12)," "))))))," ") | AB12: =IF($F12+$G12=AB$10,($E12-$H12)/$G12/2,(IF($F12=AB$10,($E12-$H12)/$G12/2,0))) -> #VALUE! | AC12: =IFERROR(IF($F12+$G12=AC$10,AB12,(IF($F12=AC$10,AB12,(IF($F12>AC$10," ",IF(AC$10<$G12+$F12,SLN($E12,$H12,$G12)," "))))))," ") | AD12: =IF($F12+$G12=AD$10,($E12-$H12)/$G12/2,(IF($F12=AD$10,($E12-$H12)/$G12/2,0))) -> #VALUE! | AE12: =IFERROR(IF($F12+$G12=AE$10,AD12,(IF($F12=AE$10,AD12,(IF($F12>AE$10," ",IF(AE$10<$G12+$F12,SLN($E12,$H12,$G12)," "))))))," ") | AF12: =IF($F12+$G12=AF$10,($E12-$H12)/$G12/2,(IF($F12=AF$10,($E12-$H12)/$G12/2,0))) -> #VALUE! | AG12: =IFERROR(IF($F12+$G12=AG$10,AF12,(IF($F12=AG$10,AF12,(IF($F12>AG$10," ",IF(AG$10<$G12+$F12,SLN($E12,$H12,$G12)," "))))))," ") | AH12: =IF($F12+$G12=AH$10,($E12-$H12)/$G12/2,(IF($F12=AH$10,($E12-$H12)/$G12/2,0))) -> #VALUE! | AI12: =IFERROR(IF($F12+$G12=AI$10,AH12,(IF($F12=AI$10,AH12,(IF($F12>AI$10," ",IF(AI$10<$G12+$F12,SLN($E12,$H12,$G12)," "))))))," ") | AJ12: =IF($F12+$G12=AJ$10,($E12-$H12)/$G12/2,(IF($F12=AJ$10,($E12-$H12)/$G12/2,0))) -> #VALUE! | AK12: =IFERROR(IF($F12+$G12=AK$10,AJ12,(IF($F12=AK$10,AJ12,(IF($F12>AK$10," ",IF(AK$10<$G12+$F12,SLN($E12,$H12,$G12)," "))))))," ") | AL12: =IF($F12+$G12=AL$10,($E12-$H12)/$G12/2,(IF($F12=AL$10,($E12-$H12)/$G12/2,0))) -> #VALUE! | AM12: =IFERROR(IF($F12+$G12=AM$10,AL12,(IF($F12=AM$10,AL12,(IF($F12>AM$10," ",IF(AM$10<$G12+$F12,SLN($E12,$H12,$G12)," "))))))," ") | AN12: =IF($F12+$G12=AN$10,($E12-$H12)/$G12/2,(IF($F12=AN$10,($E12-$H12)/$G12/2,0))) -> #VALUE! | AO12: =IFERROR(IF($F12+$G12=AO$10,AN12,(IF($F12=AO$10,AN12,(IF($F12>AO$10," ",IF(AO$10<$G12+$F12,SLN($E12,$H12,$G12)," "))))))," ") | AP12: =IF($F12+$G12=AP$10,($E12-$H12)/$G12/2,(IF($F12=AP$10,($E12-$H12)/$G12/2,0))) -> #VALUE! | AQ12: =IFERROR(IF($F12+$G12=AQ$10,AP12,(IF($F12=AQ$10,AP12,(IF($F12>AQ$10," ",IF(AQ$10<$G12+$F12,SLN($E12,$H12,$G12)," "))))))," ") | AR12: =IF($F12+$G12=AR$10,($E12-$H12)/$G12/2,(IF($F12=AR$10,($E12-$H12)/$G12/2,0))) -> #VALUE! | AS12: =IFERROR(IF($F12+$G12=AS$10,AR12,(IF($F12=AS$10,AR12,(IF($F12>AS$10," ",IF(AS$10<$G12+$F12,SLN($E12,$H12,$G12)," "))))))," ") | AT12: =IF($F12+$G12=AT$10,($E12-$H12)/$G12/2,(IF($F12=AT$10,($E12-$H12)/$G12/2,0))) -> #VALUE! | AU12: =IFERROR(IF($F12+$G12=AU$10,AT12,(IF($F12=AU$10,AT12,(IF($F12>AU$10," ",IF(AU$10<$G12+$F12,SLN($E12,$H12,$G12)," "))))))," ") | AV12: =IF($F12+$G12=AV$10,($E12-$H12)/$G12/2,(IF($F12=AV$10,($E12-$H12)/$G12/2,0))) -> #VALUE! | AW12: =IFERROR(IF($F12+$G12=AW$10,AV12,(IF($F12=AW$10,AV12,(IF($F12>AW$10," ",IF(AW$10<$G12+$F12,SLN($E12,$H12,$G12)," "))))))," ") | AY12: =C12 | AZ12: =AY12 | BA12: =B12 | BB12: =D12 | BC12: =IF(BB12="","","Depreciation_Expense") | BD12: =INDEX($K$10:$BD$55, MATCH(BB12, $D$10:$D$55, 0), MATCH($H$4, $K$10:$BD$10, 1)) -> #N/A
A13: =IF(EOD!$F4="","",EOD!$F4) | B13: =IF(EOD!$C4="","",EOD!$C4) | C13: =IF(EOD!$A4="","",EOD!$A4) | D13: =IF(EOD!$D4="","",EOD!$D4) | E13: =IF(EOD!E4="","",EOD!E4) | F13: =IF(EOD!G4="","",EOD!G4) | G13: =IF(EOD!H4="","",EOD!H4) | H13: =IF(EOD!I4="","",EOD!I4) | I13: =IFERROR(IF(F13<$K$10,(($K$10-F13-1)*((E13-H13)/G13)+(((E13-H13)/G13)/2)),0),0) -> 0 | J13: =IF($F13+$G13=J$10,($E13-$H13)/$G13/2,(IF($F13=J$10,($E13-$H13)/$G13/2,0))) -> #VALUE! | K13: =IFERROR(IF($F13+$G13=K$10,J13,(IF($F13=K$10,J13,(IF($F13>K$10," ",IF(K$10<$G13+$F13,SLN($E13,$H13,$G13)," "))))))," ") | L13: =IF($F13+$G13=L$10,($E13-$H13)/$G13/2,(IF($F13=L$10,($E13-$H13)/$G13/2,0))) -> #VALUE! | M13: =IFERROR(IF($F13+$G13=M$10,L13,(IF($F13=M$10,L13,(IF($F13>M$10," ",IF(M$10<$G13+$F13,SLN($E13,$H13,$G13)," "))))))," ") | N13: =IF($F13+$G13=N$10,($E13-$H13)/$G13/2,(IF($F13=N$10,($E13-$H13)/$G13/2,0))) -> #VALUE! | O13: =IFERROR(IF($F13+$G13=O$10,N13,(IF($F13=O$10,N13,(IF($F13>O$10," ",IF(O$10<$G13+$F13,SLN($E13,$H13,$G13)," "))))))," ") | P13: =IF($F13+$G13=P$10,($E13-$H13)/$G13/2,(IF($F13=P$10,($E13-$H13)/$G13/2,0))) -> #VALUE! | Q13: =IFERROR(IF($F13+$G13=Q$10,P13,(IF($F13=Q$10,P13,(IF($F13>Q$10," ",IF(Q$10<$G13+$F13,SLN($E13,$H13,$G13)," "))))))," ") | R13: =IF($F13+$G13=R$10,($E13-$H13)/$G13/2,(IF($F13=R$10,($E13-$H13)/$G13/2,0))) -> #VALUE! | S13: =IFERROR(IF($F13+$G13=S$10,R13,(IF($F13=S$10,R13,(IF($F13>S$10," ",IF(S$10<$G13+$F13,SLN($E13,$H13,$G13)," "))))))," ") | T13: =IF($F13+$G13=T$10,($E13-$H13)/$G13/2,(IF($F13=T$10,($E13-$H13)/$G13/2,0))) -> #VALUE! | U13: =IFERROR(IF($F13+$G13=U$10,T13,(IF($F13=U$10,T13,(IF($F13>U$10," ",IF(U$10<$G13+$F13,SLN($E13,$H13,$G13)," "))))))," ") | V13: =IF($F13+$G13=V$10,($E13-$H13)/$G13/2,(IF($F13=V$10,($E13-$H13)/$G13/2,0))) -> #VALUE! | W13: =IFERROR(IF($F13+$G13=W$10,V13,(IF($F13=W$10,V13,(IF($F13>W$10," ",IF(W$10<$G13+$F13,SLN($E13,$H13,$G13)," "))))))," ") | X13: =IF($F13+$G13=X$10,($E13-$H13)/$G13/2,(IF($F13=X$10,($E13-$H13)/$G13/2,0))) -> #VALUE! | Y13: =IFERROR(IF($F13+$G13=Y$10,X13,(IF($F13=Y$10,X13,(IF($F13>Y$10," ",IF(Y$10<$G13+$F13,SLN($E13,$H13,$G13)," "))))))," ") | Z13: =IF($F13+$G13=Z$10,($E13-$H13)/$G13/2,(IF($F13=Z$10,($E13-$H13)/$G13/2,0))) -> #VALUE! | AA13: =IFERROR(IF($F13+$G13=AA$10,Z13,(IF($F13=AA$10,Z13,(IF($F13>AA$10," ",IF(AA$10<$G13+$F13,SLN($E13,$H13,$G13)," "))))))," ") | AB13: =IF($F13+$G13=AB$10,($E13-$H13)/$G13/2,(IF($F13=AB$10,($E13-$H13)/$G13/2,0))) -> #VALUE! | AC13: =IFERROR(IF($F13+$G13=AC$10,AB13,(IF($F13=AC$10,AB13,(IF($F13>AC$10," ",IF(AC$10<$G13+$F13,SLN($E13,$H13,$G13)," "))))))," ") | AD13: =IF($F13+$G13=AD$10,($E13-$H13)/$G13/2,(IF($F13=AD$10,($E13-$H13)/$G13/2,0))) -> #VALUE! | AE13: =IFERROR(IF($F13+$G13=AE$10,AD13,(IF($F13=AE$10,AD13,(IF($F13>AE$10," ",IF(AE$10<$G13+$F13,SLN($E13,$H13,$G13)," "))))))," ") | AF13: =IF($F13+$G13=AF$10,($E13-$H13)/$G13/2,(IF($F13=AF$10,($E13-$H13)/$G13/2,0))) -> #VALUE! | AG13: =IFERROR(IF($F13+$G13=AG$10,AF13,(IF($F13=AG$10,AF13,(IF($F13>AG$10," ",IF(AG$10<$G13+$F13,SLN($E13,$H13,$G13)," "))))))," ") | AH13: =IF($F13+$G13=AH$10,($E13-$H13)/$G13/2,(IF($F13=AH$10,($E13-$H13)/$G13/2,0))) -> #VALUE! | AI13: =IFERROR(IF($F13+$G13=AI$10,AH13,(IF($F13=AI$10,AH13,(IF($F13>AI$10," ",IF(AI$10<$G13+$F13,SLN($E13,$H13,$G13)," "))))))," ") | AJ13: =IF($F13+$G13=AJ$10,($E13-$H13)/$G13/2,(IF($F13=AJ$10,($E13-$H13)/$G13/2,0))) -> #VALUE! | AK13: =IFERROR(IF($F13+$G13=AK$10,AJ13,(IF($F13=AK$10,AJ13,(IF($F13>AK$10," ",IF(AK$10<$G13+$F13,SLN($E13,$H13,$G13)," "))))))," ") | AL13: =IF($F13+$G13=AL$10,($E13-$H13)/$G13/2,(IF($F13=AL$10,($E13-$H13)/$G13/2,0))) -> #VALUE! | AM13: =IFERROR(IF($F13+$G13=AM$10,AL13,(IF($F13=AM$10,AL13,(IF($F13>AM$10," ",IF(AM$10<$G13+$F13,SLN($E13,$H13,$G13)," "))))))," ") | AN13: =IF($F13+$G13=AN$10,($E13-$H13)/$G13/2,(IF($F13=AN$10,($E13-$H13)/$G13/2,0))) -> #VALUE! | AO13: =IFERROR(IF($F13+$G13=AO$10,AN13,(IF($F13=AO$10,AN13,(IF($F13>AO$10," ",IF(AO$10<$G13+$F13,SLN($E13,$H13,$G13)," "))))))," ") | AP13: =IF($F13+$G13=AP$10,($E13-$H13)/$G13/2,(IF($F13=AP$10,($E13-$H13)/$G13/2,0))) -> #VALUE! | AQ13: =IFERROR(IF($F13+$G13=AQ$10,AP13,(IF($F13=AQ$10,AP13,(IF($F13>AQ$10," ",IF(AQ$10<$G13+$F13,SLN($E13,$H13,$G13)," "))))))," ") | AR13: =IF($F13+$G13=AR$10,($E13-$H13)/$G13/2,(IF($F13=AR$10,($E13-$H13)/$G13/2,0))) -> #VALUE! | AS13: =IFERROR(IF($F13+$G13=AS$10,AR13,(IF($F13=AS$10,AR13,(IF($F13>AS$10," ",IF(AS$10<$G13+$F13,SLN($E13,$H13,$G13)," "))))))," ") | AT13: =IF($F13+$G13=AT$10,($E13-$H13)/$G13/2,(IF($F13=AT$10,($E13-$H13)/$G13/2,0))) -> #VALUE! | AU13: =IFERROR(IF($F13+$G13=AU$10,AT13,(IF($F13=AU$10,AT13,(IF($F13>AU$10," ",IF(AU$10<$G13+$F13,SLN($E13,$H13,$G13)," "))))))," ") | AV13: =IF($F13+$G13=AV$10,($E13-$H13)/$G13/2,(IF($F13=AV$10,($E13-$H13)/$G13/2,0))) -> #VALUE! | AW13: =IFERROR(IF($F13+$G13=AW$10,AV13,(IF($F13=AW$10,AV13,(IF($F13>AW$10," ",IF(AW$10<$G13+$F13,SLN($E13,$H13,$G13)," "))))))," ") | AY13: =C13 | AZ13: =AY13 | BA13: =B13 | BB13: =D13 | BC13: =IF(BB13="","","Depreciation_Expense") | BD13: =INDEX($K$10:$BD$55, MATCH(BB13, $D$10:$D$55, 0), MATCH($H$4, $K$10:$BD$10, 1)) -> #N/A
A14: =IF(EOD!$F5="","",EOD!$F5) | B14: =IF(EOD!$C5="","",EOD!$C5) | C14: =IF(EOD!$A5="","",EOD!$A5) | D14: =IF(EOD!$D5="","",EOD!$D5) | E14: =IF(EOD!E5="","",EOD!E5) | F14: =IF(EOD!G5="","",EOD!G5) | G14: =IF(EOD!H5="","",EOD!H5) | H14: =IF(EOD!I5="","",EOD!I5) | I14: =IFERROR(IF(F14<$K$10,(($K$10-F14-1)*((E14-H14)/G14)+(((E14-H14)/G14)/2)),0),0) -> 0 | J14: =IF($F14+$G14=J$10,($E14-$H14)/$G14/2,(IF($F14=J$10,($E14-$H14)/$G14/2,0))) -> #VALUE! | K14: =IFERROR(IF($F14+$G14=K$10,J14,(IF($F14=K$10,J14,(IF($F14>K$10," ",IF(K$10<$G14+$F14,SLN($E14,$H14,$G14)," "))))))," ") | L14: =IF($F14+$G14=L$10,($E14-$H14)/$G14/2,(IF($F14=L$10,($E14-$H14)/$G14/2,0))) -> #VALUE! | M14: =IFERROR(IF($F14+$G14=M$10,L14,(IF($F14=M$10,L14,(IF($F14>M$10," ",IF(M$10<$G14+$F14,SLN($E14,$H14,$G14)," "))))))," ") | N14: =IF($F14+$G14=N$10,($E14-$H14)/$G14/2,(IF($F14=N$10,($E14-$H14)/$G14/2,0))) -> #VALUE! | O14: =IFERROR(IF($F14+$G14=O$10,N14,(IF($F14=O$10,N14,(IF($F14>O$10," ",IF(O$10<$G14+$F14,SLN($E14,$H14,$G14)," "))))))," ") | P14: =IF($F14+$G14=P$10,($E14-$H14)/$G14/2,(IF($F14=P$10,($E14-$H14)/$G14/2,0))) -> #VALUE! | Q14: =IFERROR(IF($F14+$G14=Q$10,P14,(IF($F14=Q$10,P14,(IF($F14>Q$10," ",IF(Q$10<$G14+$F14,SLN($E14,$H14,$G14)," "))))))," ") | R14: =IF($F14+$G14=R$10,($E14-$H14)/$G14/2,(IF($F14=R$10,($E14-$H14)/$G14/2,0))) -> #VALUE! | S14: =IFERROR(IF($F14+$G14=S$10,R14,(IF($F14=S$10,R14,(IF($F14>S$10," ",IF(S$10<$G14+$F14,SLN($E14,$H14,$G14)," "))))))," ") | T14: =IF($F14+$G14=T$10,($E14-$H14)/$G14/2,(IF($F14=T$10,($E14-$H14)/$G14/2,0))) -> #VALUE! | U14: =IFERROR(IF($F14+$G14=U$10,T14,(IF($F14=U$10,T14,(IF($F14>U$10," ",IF(U$10<$G14+$F14,SLN($E14,$H14,$G14)," "))))))," ") | V14: =IF($F14+$G14=V$10,($E14-$H14)/$G14/2,(IF($F14=V$10,($E14-$H14)/$G14/2,0))) -> #VALUE! | W14: =IFERROR(IF($F14+$G14=W$10,V14,(IF($F14=W$10,V14,(IF($F14>W$10," ",IF(W$10<$G14+$F14,SLN($E14,$H14,$G14)," "))))))," ") | X14: =IF($F14+$G14=X$10,($E14-$H14)/$G14/2,(IF($F14=X$10,($E14-$H14)/$G14/2,0))) -> #VALUE! | Y14: =IFERROR(IF($F14+$G14=Y$10,X14,(IF($F14=Y$10,X14,(IF($F14>Y$10," ",IF(Y$10<$G14+$F14,SLN($E14,$H14,$G14)," "))))))," ") | Z14: =IF($F14+$G14=Z$10,($E14-$H14)/$G14/2,(IF($F14=Z$10,($E14-$H14)/$G14/2,0))) -> #VALUE! | AA14: =IFERROR(IF($F14+$G14=AA$10,Z14,(IF($F14=AA$10,Z14,(IF($F14>AA$10," ",IF(AA$10<$G14+$F14,SLN($E14,$H14,$G14)," "))))))," ") | AB14: =IF($F14+$G14=AB$10,($E14-$H14)/$G14/2,(IF($F14=AB$10,($E14-$H14)/$G14/2,0))) -> #VALUE! | AC14: =IFERROR(IF($F14+$G14=AC$10,AB14,(IF($F14=AC$10,AB14,(IF($F14>AC$10," ",IF(AC$10<$G14+$F14,SLN($E14,$H14,$G14)," "))))))," ") | AD14: =IF($F14+$G14=AD$10,($E14-$H14)/$G14/2,(IF($F14=AD$10,($E14-$H14)/$G14/2,0))) -> #VALUE! | AE14: =IFERROR(IF($F14+$G14=AE$10,AD14,(IF($F14=AE$10,AD14,(IF($F14>AE$10," ",IF(AE$10<$G14+$F14,SLN($E14,$H14,$G14)," "))))))," ") | AF14: =IF($F14+$G14=AF$10,($E14-$H14)/$G14/2,(IF($F14=AF$10,($E14-$H14)/$G14/2,0))) -> #VALUE! | AG14: =IFERROR(IF($F14+$G14=AG$10,AF14,(IF($F14=AG$10,AF14,(IF($F14>AG$10," ",IF(AG$10<$G14+$F14,SLN($E14,$H14,$G14)," "))))))," ") | AH14: =IF($F14+$G14=AH$10,($E14-$H14)/$G14/2,(IF($F14=AH$10,($E14-$H14)/$G14/2,0))) -> #VALUE! | AI14: =IFERROR(IF($F14+$G14=AI$10,AH14,(IF($F14=AI$10,AH14,(IF($F14>AI$10," ",IF(AI$10<$G14+$F14,SLN($E14,$H14,$G14)," "))))))," ") | AJ14: =IF($F14+$G14=AJ$10,($E14-$H14)/$G14/2,(IF($F14=AJ$10,($E14-$H14)/$G14/2,0))) -> #VALUE! | AK14: =IFERROR(IF($F14+$G14=AK$10,AJ14,(IF($F14=AK$10,AJ14,(IF($F14>AK$10," ",IF(AK$10<$G14+$F14,SLN($E14,$H14,$G14)," "))))))," ") | AL14: =IF($F14+$G14=AL$10,($E14-$H14)/$G14/2,(IF($F14=AL$10,($E14-$H14)/$G14/2,0))) -> #VALUE! | AM14: =IFERROR(IF($F14+$G14=AM$10,AL14,(IF($F14=AM$10,AL14,(IF($F14>AM$10," ",IF(AM$10<$G14+$F14,SLN($E14,$H14,$G14)," "))))))," ") | AN14: =IF($F14+$G14=AN$10,($E14-$H14)/$G14/2,(IF($F14=AN$10,($E14-$H14)/$G14/2,0))) -> #VALUE! | AO14: =IFERROR(IF($F14+$G14=AO$10,AN14,(IF($F14=AO$10,AN14,(IF($F14>AO$10," ",IF(AO$10<$G14+$F14,SLN($E14,$H14,$G14)," "))))))," ") | AP14: =IF($F14+$G14=AP$10,($E14-$H14)/$G14/2,(IF($F14=AP$10,($E14-$H14)/$G14/2,0))) -> #VALUE! | AQ14: =IFERROR(IF($F14+$G14=AQ$10,AP14,(IF($F14=AQ$10,AP14,(IF($F14>AQ$10," ",IF(AQ$10<$G14+$F14,SLN($E14,$H14,$G14)," "))))))," ") | AR14: =IF($F14+$G14=AR$10,($E14-$H14)/$G14/2,(IF($F14=AR$10,($E14-$H14)/$G14/2,0))) -> #VALUE! | AS14: =IFERROR(IF($F14+$G14=AS$10,AR14,(IF($F14=AS$10,AR14,(IF($F14>AS$10," ",IF(AS$10<$G14+$F14,SLN($E14,$H14,$G14)," "))))))," ") | AT14: =IF($F14+$G14=AT$10,($E14-$H14)/$G14/2,(IF($F14=AT$10,($E14-$H14)/$G14/2,0))) -> #VALUE! | AU14: =IFERROR(IF($F14+$G14=AU$10,AT14,(IF($F14=AU$10,AT14,(IF($F14>AU$10," ",IF(AU$10<$G14+$F14,SLN($E14,$H14,$G14)," "))))))," ") | AV14: =IF($F14+$G14=AV$10,($E14-$H14)/$G14/2,(IF($F14=AV$10,($E14-$H14)/$G14/2,0))) -> #VALUE! | AW14: =IFERROR(IF($F14+$G14=AW$10,AV14,(IF($F14=AW$10,AV14,(IF($F14>AW$10," ",IF(AW$10<$G14+$F14,SLN($E14,$H14,$G14)," "))))))," ") | AY14: =C14 | AZ14: =AY14 | BA14: =B14 | BB14: =D14 | BC14: =IF(BB14="","","Depreciation_Expense") | BD14: =INDEX($K$10:$BD$55, MATCH(BB14, $D$10:$D$55, 0), MATCH($H$4, $K$10:$BD$10, 1)) -> #N/A
A15: =IF(EOD!$F6="","",EOD!$F6) | B15: =IF(EOD!$C6="","",EOD!$C6) | C15: =IF(EOD!$A6="","",EOD!$A6) | D15: =IF(EOD!$D6="","",EOD!$D6) | E15: =IF(EOD!E6="","",EOD!E6) | F15: =IF(EOD!G6="","",EOD!G6) | G15: =IF(EOD!H6="","",EOD!H6) | H15: =IF(EOD!I6="","",EOD!I6) | I15: =IFERROR(IF(F15<$K$10,(($K$10-F15-1)*((E15-H15)/G15)+(((E15-H15)/G15)/2)),0),0) -> 0 | J15: =IF($F15+$G15=J$10,($E15-$H15)/$G15/2,(IF($F15=J$10,($E15-$H15)/$G15/2,0))) -> #VALUE! | K15: =IFERROR(IF($F15+$G15=K$10,J15,(IF($F15=K$10,J15,(IF($F15>K$10," ",IF(K$10<$G15+$F15,SLN($E15,$H15,$G15)," "))))))," ") | L15: =IF($F15+$G15=L$10,($E15-$H15)/$G15/2,(IF($F15=L$10,($E15-$H15)/$G15/2,0))) -> #VALUE! | M15: =IFERROR(IF($F15+$G15=M$10,L15,(IF($F15=M$10,L15,(IF($F15>M$10," ",IF(M$10<$G15+$F15,SLN($E15,$H15,$G15)," "))))))," ") | N15: =IF($F15+$G15=N$10,($E15-$H15)/$G15/2,(IF($F15=N$10,($E15-$H15)/$G15/2,0))) -> #VALUE! | O15: =IFERROR(IF($F15+$G15=O$10,N15,(IF($F15=O$10,N15,(IF($F15>O$10," ",IF(O$10<$G15+$F15,SLN($E15,$H15,$G15)," "))))))," ") | P15: =IF($F15+$G15=P$10,($E15-$H15)/$G15/2,(IF($F15=P$10,($E15-$H15)/$G15/2,0))) -> #VALUE! | Q15: =IFERROR(IF($F15+$G15=Q$10,P15,(IF($F15=Q$10,P15,(IF($F15>Q$10," ",IF(Q$10<$G15+$F15,SLN($E15,$H15,$G15)," "))))))," ") | R15: =IF($F15+$G15=R$10,($E15-$H15)/$G15/2,(IF($F15=R$10,($E15-$H15)/$G15/2,0))) -> #VALUE! | S15: =IFERROR(IF($F15+$G15=S$10,R15,(IF($F15=S$10,R15,(IF($F15>S$10," ",IF(S$10<$G15+$F15,SLN($E15,$H15,$G15)," "))))))," ") | T15: =IF($F15+$G15=T$10,($E15-$H15)/$G15/2,(IF($F15=T$10,($E15-$H15)/$G15/2,0))) -> #VALUE! | U15: =IFERROR(IF($F15+$G15=U$10,T15,(IF($F15=U$10,T15,(IF($F15>U$10," ",IF(U$10<$G15+$F15,SLN($E15,$H15,$G15)," "))))))," ") | V15: =IF($F15+$G15=V$10,($E15-$H15)/$G15/2,(IF($F15=V$10,($E15-$H15)/$G15/2,0))) -> #VALUE! | W15: =IFERROR(IF($F15+$G15=W$10,V15,(IF($F15=W$10,V15,(IF($F15>W$10," ",IF(W$10<$G15+$F15,SLN($E15,$H15,$G15)," "))))))," ") | X15: =IF($F15+$G15=X$10,($E15-$H15)/$G15/2,(IF($F15=X$10,($E15-$H15)/$G15/2,0))) -> #VALUE! | Y15: =IFERROR(IF($F15+$G15=Y$10,X15,(IF($F15=Y$10,X15,(IF($F15>Y$10," ",IF(Y$10<$G15+$F15,SLN($E15,$H15,$G15)," "))))))," ") | Z15: =IF($F15+$G15=Z$10,($E15-$H15)/$G15/2,(IF($F15=Z$10,($E15-$H15)/$G15/2,0))) -> #VALUE! | AA15: =IFERROR(IF($F15+$G15=AA$10,Z15,(IF($F15=AA$10,Z15,(IF($F15>AA$10," ",IF(AA$10<$G15+$F15,SLN($E15,$H15,$G15)," "))))))," ") | AB15: =IF($F15+$G15=AB$10,($E15-$H15)/$G15/2,(IF($F15=AB$10,($E15-$H15)/$G15/2,0))) -> #VALUE! | AC15: =IFERROR(IF($F15+$G15=AC$10,AB15,(IF($F15=AC$10,AB15,(IF($F15>AC$10," ",IF(AC$10<$G15+$F15,SLN($E15,$H15,$G15)," "))))))," ") | AD15: =IF($F15+$G15=AD$10,($E15-$H15)/$G15/2,(IF($F15=AD$10,($E15-$H15)/$G15/2,0))) -> #VALUE! | AE15: =IFERROR(IF($F15+$G15=AE$10,AD15,(IF($F15=AE$10,AD15,(IF($F15>AE$10," ",IF(AE$10<$G15+$F15,SLN($E15,$H15,$G15)," "))))))," ") | AF15: =IF($F15+$G15=AF$10,($E15-$H15)/$G15/2,(IF($F15=AF$10,($E15-$H15)/$G15/2,0))) -> #VALUE! | AG15: =IFERROR(IF($F15+$G15=AG$10,AF15,(IF($F15=AG$10,AF15,(IF($F15>AG$10," ",IF(AG$10<$G15+$F15,SLN($E15,$H15,$G15)," "))))))," ") | AH15: =IF($F15+$G15=AH$10,($E15-$H15)/$G15/2,(IF($F15=AH$10,($E15-$H15)/$G15/2,0))) -> #VALUE! | AI15: =IFERROR(IF($F15+$G15=AI$10,AH15,(IF($F15=AI$10,AH15,(IF($F15>AI$10," ",IF(AI$10<$G15+$F15,SLN($E15,$H15,$G15)," "))))))," ") | AJ15: =IF($F15+$G15=AJ$10,($E15-$H15)/$G15/2,(IF($F15=AJ$10,($E15-$H15)/$G15/2,0))) -> #VALUE! | AK15: =IFERROR(IF($F15+$G15=AK$10,AJ15,(IF($F15=AK$10,AJ15,(IF($F15>AK$10," ",IF(AK$10<$G15+$F15,SLN($E15,$H15,$G15)," "))))))," ") | AL15: =IF($F15+$G15=AL$10,($E15-$H15)/$G15/2,(IF($F15=AL$10,($E15-$H15)/$G15/2,0))) -> #VALUE! | AM15: =IFERROR(IF($F15+$G15=AM$10,AL15,(IF($F15=AM$10,AL15,(IF($F15>AM$10," ",IF(AM$10<$G15+$F15,SLN($E15,$H15,$G15)," "))))))," ") | AN15: =IF($F15+$G15=AN$10,($E15-$H15)/$G15/2,(IF($F15=AN$10,($E15-$H15)/$G15/2,0))) -> #VALUE! | AO15: =IFERROR(IF($F15+$G15=AO$10,AN15,(IF($F15=AO$10,AN15,(IF($F15>AO$10," ",IF(AO$10<$G15+$F15,SLN($E15,$H15,$G15)," "))))))," ") | AP15: =IF($F15+$G15=AP$10,($E15-$H15)/$G15/2,(IF($F15=AP$10,($E15-$H15)/$G15/2,0))) -> #VALUE! | AQ15: =IFERROR(IF($F15+$G15=AQ$10,AP15,(IF($F15=AQ$10,AP15,(IF($F15>AQ$10," ",IF(AQ$10<$G15+$F15,SLN($E15,$H15,$G15)," "))))))," ") | AR15: =IF($F15+$G15=AR$10,($E15-$H15)/$G15/2,(IF($F15=AR$10,($E15-$H15)/$G15/2,0))) -> #VALUE! | AS15: =IFERROR(IF($F15+$G15=AS$10,AR15,(IF($F15=AS$10,AR15,(IF($F15>AS$10," ",IF(AS$10<$G15+$F15,SLN($E15,$H15,$G15)," "))))))," ") | AT15: =IF($F15+$G15=AT$10,($E15-$H15)/$G15/2,(IF($F15=AT$10,($E15-$H15)/$G15/2,0))) -> #VALUE! | AU15: =IFERROR(IF($F15+$G15=AU$10,AT15,(IF($F15=AU$10,AT15,(IF($F15>AU$10," ",IF(AU$10<$G15+$F15,SLN($E15,$H15,$G15)," "))))))," ") | AV15: =IF($F15+$G15=AV$10,($E15-$H15)/$G15/2,(IF($F15=AV$10,($E15-$H15)/$G15/2,0))) -> #VALUE! | AW15: =IFERROR(IF($F15+$G15=AW$10,AV15,(IF($F15=AW$10,AV15,(IF($F15>AW$10," ",IF(AW$10<$G15+$F15,SLN($E15,$H15,$G15)," "))))))," ") | AY15: =C15 | AZ15: =AY15 | BA15: =B15 | BB15: =D15 | BC15: =IF(BB15="","","Depreciation_Expense") | BD15: =INDEX($K$10:$BD$55, MATCH(BB15, $D$10:$D$55, 0), MATCH($H$4, $K$10:$BD$10, 1)) -> #N/A
A16: =IF(EOD!$F7="","",EOD!$F7) | B16: =IF(EOD!$C7="","",EOD!$C7) | C16: =IF(EOD!$A7="","",EOD!$A7) | D16: =IF(EOD!$D7="","",EOD!$D7) | E16: =IF(EOD!E7="","",EOD!E7) | F16: =IF(EOD!G7="","",EOD!G7) | G16: =IF(EOD!H7="","",EOD!H7) | H16: =IF(EOD!I7="","",EOD!I7) | I16: =IFERROR(IF(F16<$K$10,(($K$10-F16-1)*((E16-H16)/G16)+(((E16-H16)/G16)/2)),0),0) -> 0 | J16: =IF($F16+$G16=J$10,($E16-$H16)/$G16/2,(IF($F16=J$10,($E16-$H16)/$G16/2,0))) -> #VALUE! | K16: =IFERROR(IF($F16+$G16=K$10,J16,(IF($F16=K$10,J16,(IF($F16>K$10," ",IF(K$10<$G16+$F16,SLN($E16,$H16,$G16)," "))))))," ") | L16: =IF($F16+$G16=L$10,($E16-$H16)/$G16/2,(IF($F16=L$10,($E16-$H16)/$G16/2,0))) -> #VALUE! | M16: =IFERROR(IF($F16+$G16=M$10,L16,(IF($F16=M$10,L16,(IF($F16>M$10," ",IF(M$10<$G16+$F16,SLN($E16,$H16,$G16)," "))))))," ") | N16: =IF($F16+$G16=N$10,($E16-$H16)/$G16/2,(IF($F16=N$10,($E16-$H16)/$G16/2,0))) -> #VALUE! | O16: =IFERROR(IF($F16+$G16=O$10,N16,(IF($F16=O$10,N16,(IF($F16>O$10," ",IF(O$10<$G16+$F16,SLN($E16,$H16,$G16)," "))))))," ") | P16: =IF($F16+$G16=P$10,($E16-$H16)/$G16/2,(IF($F16=P$10,($E16-$H16)/$G16/2,0))) -> #VALUE! | Q16: =IFERROR(IF($F16+$G16=Q$10,P16,(IF($F16=Q$10,P16,(IF($F16>Q$10," ",IF(Q$10<$G16+$F16,SLN($E16,$H16,$G16)," "))))))," ") | R16: =IF($F16+$G16=R$10,($E16-$H16)/$G16/2,(IF($F16=R$10,($E16-$H16)/$G16/2,0))) -> #VALUE! | S16: =IFERROR(IF($F16+$G16=S$10,R16,(IF($F16=S$10,R16,(IF($F16>S$10," ",IF(S$10<$G16+$F16,SLN($E16,$H16,$G16)," "))))))," ") | T16: =IF($F16+$G16=T$10,($E16-$H16)/$G16/2,(IF($F16=T$10,($E16-$H16)/$G16/2,0))) -> #VALUE! | U16: =IFERROR(IF($F16+$G16=U$10,T16,(IF($F16=U$10,T16,(IF($F16>U$10," ",IF(U$10<$G16+$F16,SLN($E16,$H16,$G16)," "))))))," ") | V16: =IF($F16+$G16=V$10,($E16-$H16)/$G16/2,(IF($F16=V$10,($E16-$H16)/$G16/2,0))) -> #VALUE! | W16: =IFERROR(IF($F16+$G16=W$10,V16,(IF($F16=W$10,V16,(IF($F16>W$10," ",IF(W$10<$G16+$F16,SLN($E16,$H16,$G16)," "))))))," ") | X16: =IF($F16+$G16=X$10,($E16-$H16)/$G16/2,(IF($F16=X$10,($E16-$H16)/$G16/2,0))) -> #VALUE! | Y16: =IFERROR(IF($F16+$G16=Y$10,X16,(IF($F16=Y$10,X16,(IF($F16>Y$10," ",IF(Y$10<$G16+$F16,SLN($E16,$H16,$G16)," "))))))," ") | Z16: =IF($F16+$G16=Z$10,($E16-$H16)/$G16/2,(IF($F16=Z$10,($E16-$H16)/$G16/2,0))) -> #VALUE! | AA16: =IFERROR(IF($F16+$G16=AA$10,Z16,(IF($F16=AA$10,Z16,(IF($F16>AA$10," ",IF(AA$10<$G16+$F16,SLN($E16,$H16,$G16)," "))))))," ") | AB16: =IF($F16+$G16=AB$10,($E16-$H16)/$G16/2,(IF($F16=AB$10,($E16-$H16)/$G16/2,0))) -> #VALUE! | AC16: =IFERROR(IF($F16+$G16=AC$10,AB16,(IF($F16=AC$10,AB16,(IF($F16>AC$10," ",IF(AC$10<$G16+$F16,SLN($E16,$H16,$G16)," "))))))," ") | AD16: =IF($F16+$G16=AD$10,($E16-$H16)/$G16/2,(IF($F16=AD$10,($E16-$H16)/$G16/2,0))) -> #VALUE! | AE16: =IFERROR(IF($F16+$G16=AE$10,AD16,(IF($F16=AE$10,AD16,(IF($F16>AE$10," ",IF(AE$10<$G16+$F16,SLN($E16,$H16,$G16)," "))))))," ") | AF16: =IF($F16+$G16=AF$10,($E16-$H16)/$G16/2,(IF($F16=AF$10,($E16-$H16)/$G16/2,0))) -> #VALUE! | AG16: =IFERROR(IF($F16+$G16=AG$10,AF16,(IF($F16=AG$10,AF16,(IF($F16>AG$10," ",IF(AG$10<$G16+$F16,SLN($E16,$H16,$G16)," "))))))," ") | AH16: =IF($F16+$G16=AH$10,($E16-$H16)/$G16/2,(IF($F16=AH$10,($E16-$H16)/$G16/2,0))) -> #VALUE! | AI16: =IFERROR(IF($F16+$G16=AI$10,AH16,(IF($F16=AI$10,AH16,(IF($F16>AI$10," ",IF(AI$10<$G16+$F16,SLN($E16,$H16,$G16)," "))))))," ") | AJ16: =IF($F16+$G16=AJ$10,($E16-$H16)/$G16/2,(IF($F16=AJ$10,($E16-$H16)/$G16/2,0))) -> #VALUE! | AK16: =IFERROR(IF($F16+$G16=AK$10,AJ16,(IF($F16=AK$10,AJ16,(IF($F16>AK$10," ",IF(AK$10<$G16+$F16,SLN($E16,$H16,$G16)," "))))))," ") | AL16: =IF($F16+$G16=AL$10,($E16-$H16)/$G16/2,(IF($F16=AL$10,($E16-$H16)/$G16/2,0))) -> #VALUE! | AM16: =IFERROR(IF($F16+$G16=AM$10,AL16,(IF($F16=AM$10,AL16,(IF($F16>AM$10," ",IF(AM$10<$G16+$F16,SLN($E16,$H16,$G16)," "))))))," ") | AN16: =IF($F16+$G16=AN$10,($E16-$H16)/$G16/2,(IF($F16=AN$10,($E16-$H16)/$G16/2,0))) -> #VALUE! | AO16: =IFERROR(IF($F16+$G16=AO$10,AN16,(IF($F16=AO$10,AN16,(IF($F16>AO$10," ",IF(AO$10<$G16+$F16,SLN($E16,$H16,$G16)," "))))))," ") | AP16: =IF($F16+$G16=AP$10,($E16-$H16)/$G16/2,(IF($F16=AP$10,($E16-$H16)/$G16/2,0))) -> #VALUE! | AQ16: =IFERROR(IF($F16+$G16=AQ$10,AP16,(IF($F16=AQ$10,AP16,(IF($F16>AQ$10," ",IF(AQ$10<$G16+$F16,SLN($E16,$H16,$G16)," "))))))," ") | AR16: =IF($F16+$G16=AR$10,($E16-$H16)/$G16/2,(IF($F16=AR$10,($E16-$H16)/$G16/2,0))) -> #VALUE! | AS16: =IFERROR(IF($F16+$G16=AS$10,AR16,(IF($F16=AS$10,AR16,(IF($F16>AS$10," ",IF(AS$10<$G16+$F16,SLN($E16,$H16,$G16)," "))))))," ") | AT16: =IF($F16+$G16=AT$10,($E16-$H16)/$G16/2,(IF($F16=AT$10,($E16-$H16)/$G16/2,0))) -> #VALUE! | AU16: =IFERROR(IF($F16+$G16=AU$10,AT16,(IF($F16=AU$10,AT16,(IF($F16>AU$10," ",IF(AU$10<$G16+$F16,SLN($E16,$H16,$G16)," "))))))," ") | AV16: =IF($F16+$G16=AV$10,($E16-$H16)/$G16/2,(IF($F16=AV$10,($E16-$H16)/$G16/2,0))) -> #VALUE! | AW16: =IFERROR(IF($F16+$G16=AW$10,AV16,(IF($F16=AW$10,AV16,(IF($F16>AW$10," ",IF(AW$10<$G16+$F16,SLN($E16,$H16,$G16)," "))))))," ") | AY16: =C16 | AZ16: =AY16 | BA16: =B16 | BB16: =D16 | BC16: =IF(BB16="","","Depreciation_Expense") | BD16: =INDEX($K$10:$BD$55, MATCH(BB16, $D$10:$D$55, 0), MATCH($H$4, $K$10:$BD$10, 1)) -> #N/A
A17: =IF(EOD!$F8="","",EOD!$F8) | B17: =IF(EOD!$C8="","",EOD!$C8) | C17: =IF(EOD!$A8="","",EOD!$A8) | D17: =IF(EOD!$D8="","",EOD!$D8) | E17: =IF(EOD!E8="","",EOD!E8) | F17: =IF(EOD!G8="","",EOD!G8) | G17: =IF(EOD!H8="","",EOD!H8) | H17: =IF(EOD!I8="","",EOD!I8) | I17: =IFERROR(IF(F17<$K$10,(($K$10-F17-1)*((E17-H17)/G17)+(((E17-H17)/G17)/2)),0),0) -> 0 | J17: =IF($F17+$G17=J$10,($E17-$H17)/$G17/2,(IF($F17=J$10,($E17-$H17)/$G17/2,0))) -> #VALUE! | K17: =IFERROR(IF($F17+$G17=K$10,J17,(IF($F17=K$10,J17,(IF($F17>K$10," ",IF(K$10<$G17+$F17,SLN($E17,$H17,$G17)," "))))))," ") | L17: =IF($F17+$G17=L$10,($E17-$H17)/$G17/2,(IF($F17=L$10,($E17-$H17)/$G17/2,0))) -> #VALUE! | M17: =IFERROR(IF($F17+$G17=M$10,L17,(IF($F17=M$10,L17,(IF($F17>M$10," ",IF(M$10<$G17+$F17,SLN($E17,$H17,$G17)," "))))))," ") | N17: =IF($F17+$G17=N$10,($E17-$H17)/$G17/2,(IF($F17=N$10,($E17-$H17)/$G17/2,0))) -> #VALUE! | O17: =IFERROR(IF($F17+$G17=O$10,N17,(IF($F17=O$10,N17,(IF($F17>O$10," ",IF(O$10<$G17+$F17,SLN($E17,$H17,$G17)," "))))))," ") | P17: =IF($F17+$G17=P$10,($E17-$H17)/$G17/2,(IF($F17=P$10,($E17-$H17)/$G17/2,0))) -> #VALUE! | Q17: =IFERROR(IF($F17+$G17=Q$10,P17,(IF($F17=Q$10,P17,(IF($F17>Q$10," ",IF(Q$10<$G17+$F17,SLN($E17,$H17,$G17)," "))))))," ") | R17: =IF($F17+$G17=R$10,($E17-$H17)/$G17/2,(IF($F17=R$10,($E17-$H17)/$G17/2,0))) -> #VALUE! | S17: =IFERROR(IF($F17+$G17=S$10,R17,(IF($F17=S$10,R17,(IF($F17>S$10," ",IF(S$10<$G17+$F17,SLN($E17,$H17,$G17)," "))))))," ") | T17: =IF($F17+$G17=T$10,($E17-$H17)/$G17/2,(IF($F17=T$10,($E17-$H17)/$G17/2,0))) -> #VALUE! | U17: =IFERROR(IF($F17+$G17=U$10,T17,(IF($F17=U$10,T17,(IF($F17>U$10," ",IF(U$10<$G17+$F17,SLN($E17,$H17,$G17)," "))))))," ") | V17: =IF($F17+$G17=V$10,($E17-$H17)/$G17/2,(IF($F17=V$10,($E17-$H17)/$G17/2,0))) -> #VALUE! | W17: =IFERROR(IF($F17+$G17=W$10,V17,(IF($F17=W$10,V17,(IF($F17>W$10," ",IF(W$10<$G17+$F17,SLN($E17,$H17,$G17)," "))))))," ") | X17: =IF($F17+$G17=X$10,($E17-$H17)/$G17/2,(IF($F17=X$10,($E17-$H17)/$G17/2,0))) -> #VALUE! | Y17: =IFERROR(IF($F17+$G17=Y$10,X17,(IF($F17=Y$10,X17,(IF($F17>Y$10," ",IF(Y$10<$G17+$F17,SLN($E17,$H17,$G17)," "))))))," ") | Z17: =IF($F17+$G17=Z$10,($E17-$H17)/$G17/2,(IF($F17=Z$10,($E17-$H17)/$G17/2,0))) -> #VALUE! | AA17: =IFERROR(IF($F17+$G17=AA$10,Z17,(IF($F17=AA$10,Z17,(IF($F17>AA$10," ",IF(AA$10<$G17+$F17,SLN($E17,$H17,$G17)," "))))))," ") | AB17: =IF($F17+$G17=AB$10,($E17-$H17)/$G17/2,(IF($F17=AB$10,($E17-$H17)/$G17/2,0))) -> #VALUE! | AC17: =IFERROR(IF($F17+$G17=AC$10,AB17,(IF($F17=AC$10,AB17,(IF($F17>AC$10," ",IF(AC$10<$G17+$F17,SLN($E17,$H17,$G17)," "))))))," ") | AD17: =IF($F17+$G17=AD$10,($E17-$H17)/$G17/2,(IF($F17=AD$10,($E17-$H17)/$G17/2,0))) -> #VALUE! | AE17: =IFERROR(IF($F17+$G17=AE$10,AD17,(IF($F17=AE$10,AD17,(IF($F17>AE$10," ",IF(AE$10<$G17+$F17,SLN($E17,$H17,$G17)," "))))))," ") | AF17: =IF($F17+$G17=AF$10,($E17-$H17)/$G17/2,(IF($F17=AF$10,($E17-$H17)/$G17/2,0))) -> #VALUE! | AG17: =IFERROR(IF($F17+$G17=AG$10,AF17,(IF($F17=AG$10,AF17,(IF($F17>AG$10," ",IF(AG$10<$G17+$F17,SLN($E17,$H17,$G17)," "))))))," ") | AH17: =IF($F17+$G17=AH$10,($E17-$H17)/$G17/2,(IF($F17=AH$10,($E17-$H17)/$G17/2,0))) -> #VALUE! | AI17: =IFERROR(IF($F17+$G17=AI$10,AH17,(IF($F17=AI$10,AH17,(IF($F17>AI$10," ",IF(AI$10<$G17+$F17,SLN($E17,$H17,$G17)," "))))))," ") | AJ17: =IF($F17+$G17=AJ$10,($E17-$H17)/$G17/2,(IF($F17=AJ$10,($E17-$H17)/$G17/2,0))) -> #VALUE! | AK17: =IFERROR(IF($F17+$G17=AK$10,AJ17,(IF($F17=AK$10,AJ17,(IF($F17>AK$10," ",IF(AK$10<$G17+$F17,SLN($E17,$H17,$G17)," "))))))," ") | AL17: =IF($F17+$G17=AL$10,($E17-$H17)/$G17/2,(IF($F17=AL$10,($E17-$H17)/$G17/2,0))) -> #VALUE! | AM17: =IFERROR(IF($F17+$G17=AM$10,AL17,(IF($F17=AM$10,AL17,(IF($F17>AM$10," ",IF(AM$10<$G17+$F17,SLN($E17,$H17,$G17)," "))))))," ") | AN17: =IF($F17+$G17=AN$10,($E17-$H17)/$G17/2,(IF($F17=AN$10,($E17-$H17)/$G17/2,0))) -> #VALUE! | AO17: =IFERROR(IF($F17+$G17=AO$10,AN17,(IF($F17=AO$10,AN17,(IF($F17>AO$10," ",IF(AO$10<$G17+$F17,SLN($E17,$H17,$G17)," "))))))," ") | AP17: =IF($F17+$G17=AP$10,($E17-$H17)/$G17/2,(IF($F17=AP$10,($E17-$H17)/$G17/2,0))) -> #VALUE! | AQ17: =IFERROR(IF($F17+$G17=AQ$10,AP17,(IF($F17=AQ$10,AP17,(IF($F17>AQ$10," ",IF(AQ$10<$G17+$F17,SLN($E17,$H17,$G17)," "))))))," ") | AR17: =IF($F17+$G17=AR$10,($E17-$H17)/$G17/2,(IF($F17=AR$10,($E17-$H17)/$G17/2,0))) -> #VALUE! | AS17: =IFERROR(IF($F17+$G17=AS$10,AR17,(IF($F17=AS$10,AR17,(IF($F17>AS$10," ",IF(AS$10<$G17+$F17,SLN($E17,$H17,$G17)," "))))))," ") | AT17: =IF($F17+$G17=AT$10,($E17-$H17)/$G17/2,(IF($F17=AT$10,($E17-$H17)/$G17/2,0))) -> #VALUE! | AU17: =IFERROR(IF($F17+$G17=AU$10,AT17,(IF($F17=AU$10,AT17,(IF($F17>AU$10," ",IF(AU$10<$G17+$F17,SLN($E17,$H17,$G17)," "))))))," ") | AV17: =IF($F17+$G17=AV$10,($E17-$H17)/$G17/2,(IF($F17=AV$10,($E17-$H17)/$G17/2,0))) -> #VALUE! | AW17: =IFERROR(IF($F17+$G17=AW$10,AV17,(IF($F17=AW$10,AV17,(IF($F17>AW$10," ",IF(AW$10<$G17+$F17,SLN($E17,$H17,$G17)," "))))))," ") | AY17: =C17 | AZ17: =AY17 | BA17: =B17 | BB17: =D17 | BC17: =IF(BB17="","","Depreciation_Expense") | BD17: =INDEX($K$10:$BD$55, MATCH(BB17, $D$10:$D$55, 0), MATCH($H$4, $K$10:$BD$10, 1)) -> #N/A
A18: =IF(EOD!$F9="","",EOD!$F9) | B18: =IF(EOD!$C9="","",EOD!$C9) | C18: =IF(EOD!$A9="","",EOD!$A9) | D18: =IF(EOD!$D9="","",EOD!$D9) | E18: =IF(EOD!E9="","",EOD!E9) | F18: =IF(EOD!G9="","",EOD!G9) | G18: =IF(EOD!H9="","",EOD!H9) | H18: =IF(EOD!I9="","",EOD!I9) | I18: =IFERROR(IF(F18<$K$10,(($K$10-F18-1)*((E18-H18)/G18)+(((E18-H18)/G18)/2)),0),0) -> 0 | J18: =IF($F18+$G18=J$10,($E18-$H18)/$G18/2,(IF($F18=J$10,($E18-$H18)/$G18/2,0))) -> #VALUE! | K18: =IFERROR(IF($F18+$G18=K$10,J18,(IF($F18=K$10,J18,(IF($F18>K$10," ",IF(K$10<$G18+$F18,SLN($E18,$H18,$G18)," "))))))," ") | L18: =IF($F18+$G18=L$10,($E18-$H18)/$G18/2,(IF($F18=L$10,($E18-$H18)/$G18/2,0))) -> #VALUE! | M18: =IFERROR(IF($F18+$G18=M$10,L18,(IF($F18=M$10,L18,(IF($F18>M$10," ",IF(M$10<$G18+$F18,SLN($E18,$H18,$G18)," "))))))," ") | N18: =IF($F18+$G18=N$10,($E18-$H18)/$G18/2,(IF($F18=N$10,($E18-$H18)/$G18/2,0))) -> #VALUE! | O18: =IFERROR(IF($F18+$G18=O$10,N18,(IF($F18=O$10,N18,(IF($F18>O$10," ",IF(O$10<$G18+$F18,SLN($E18,$H18,$G18)," "))))))," ") | P18: =IF($F18+$G18=P$10,($E18-$H18)/$G18/2,(IF($F18=P$10,($E18-$H18)/$G18/2,0))) -> #VALUE! | Q18: =IFERROR(IF($F18+$G18=Q$10,P18,(IF($F18=Q$10,P18,(IF($F18>Q$10," ",IF(Q$10<$G18+$F18,SLN($E18,$H18,$G18)," "))))))," ") | R18: =IF($F18+$G18=R$10,($E18-$H18)/$G18/2,(IF($F18=R$10,($E18-$H18)/$G18/2,0))) -> #VALUE! | S18: =IFERROR(IF($F18+$G18=S$10,R18,(IF($F18=S$10,R18,(IF($F18>S$10," ",IF(S$10<$G18+$F18,SLN($E18,$H18,$G18)," "))))))," ") | T18: =IF($F18+$G18=T$10,($E18-$H18)/$G18/2,(IF($F18=T$10,($E18-$H18)/$G18/2,0))) -> #VALUE! | U18: =IFERROR(IF($F18+$G18=U$10,T18,(IF($F18=U$10,T18,(IF($F18>U$10," ",IF(U$10<$G18+$F18,SLN($E18,$H18,$G18)," "))))))," ") | V18: =IF($F18+$G18=V$10,($E18-$H18)/$G18/2,(IF($F18=V$10,($E18-$H18)/$G18/2,0))) -> #VALUE! | W18: =IFERROR(IF($F18+$G18=W$10,V18,(IF($F18=W$10,V18,(IF($F18>W$10," ",IF(W$10<$G18+$F18,SLN($E18,$H18,$G18)," "))))))," ") | X18: =IF($F18+$G18=X$10,($E18-$H18)/$G18/2,(IF($F18=X$10,($E18-$H18)/$G18/2,0))) -> #VALUE! | Y18: =IFERROR(IF($F18+$G18=Y$10,X18,(IF($F18=Y$10,X18,(IF($F18>Y$10," ",IF(Y$10<$G18+$F18,SLN($E18,$H18,$G18)," "))))))," ") | Z18: =IF($F18+$G18=Z$10,($E18-$H18)/$G18/2,(IF($F18=Z$10,($E18-$H18)/$G18/2,0))) -> #VALUE! | AA18: =IFERROR(IF($F18+$G18=AA$10,Z18,(IF($F18=AA$10,Z18,(IF($F18>AA$10," ",IF(AA$10<$G18+$F18,SLN($E18,$H18,$G18)," "))))))," ") | AB18: =IF($F18+$G18=AB$10,($E18-$H18)/$G18/2,(IF($F18=AB$10,($E18-$H18)/$G18/2,0))) -> #VALUE! | AC18: =IFERROR(IF($F18+$G18=AC$10,AB18,(IF($F18=AC$10,AB18,(IF($F18>AC$10," ",IF(AC$10<$G18+$F18,SLN($E18,$H18,$G18)," "))))))," ") | AD18: =IF($F18+$G18=AD$10,($E18-$H18)/$G18/2,(IF($F18=AD$10,($E18-$H18)/$G18/2,0))) -> #VALUE! | AE18: =IFERROR(IF($F18+$G18=AE$10,AD18,(IF($F18=AE$10,AD18,(IF($F18>AE$10," ",IF(AE$10<$G18+$F18,SLN($E18,$H18,$G18)," "))))))," ") | AF18: =IF($F18+$G18=AF$10,($E18-$H18)/$G18/2,(IF($F18=AF$10,($E18-$H18)/$G18/2,0))) -> #VALUE! | AG18: =IFERROR(IF($F18+$G18=AG$10,AF18,(IF($F18=AG$10,AF18,(IF($F18>AG$10," ",IF(AG$10<$G18+$F18,SLN($E18,$H18,$G18)," "))))))," ") | AH18: =IF($F18+$G18=AH$10,($E18-$H18)/$G18/2,(IF($F18=AH$10,($E18-$H18)/$G18/2,0))) -> #VALUE! | AI18: =IFERROR(IF($F18+$G18=AI$10,AH18,(IF($F18=AI$10,AH18,(IF($F18>AI$10," ",IF(AI$10<$G18+$F18,SLN($E18,$H18,$G18)," "))))))," ") | AJ18: =IF($F18+$G18=AJ$10,($E18-$H18)/$G18/2,(IF($F18=AJ$10,($E18-$H18)/$G18/2,0))) -> #VALUE! | AK18: =IFERROR(IF($F18+$G18=AK$10,AJ18,(IF($F18=AK$10,AJ18,(IF($F18>AK$10," ",IF(AK$10<$G18+$F18,SLN($E18,$H18,$G18)," "))))))," ") | AL18: =IF($F18+$G18=AL$10,($E18-$H18)/$G18/2,(IF($F18=AL$10,($E18-$H18)/$G18/2,0))) -> #VALUE! | AM18: =IFERROR(IF($F18+$G18=AM$10,AL18,(IF($F18=AM$10,AL18,(IF($F18>AM$10," ",IF(AM$10<$G18+$F18,SLN($E18,$H18,$G18)," "))))))," ") | AN18: =IF($F18+$G18=AN$10,($E18-$H18)/$G18/2,(IF($F18=AN$10,($E18-$H18)/$G18/2,0))) -> #VALUE! | AO18: =IFERROR(IF($F18+$G18=AO$10,AN18,(IF($F18=AO$10,AN18,(IF($F18>AO$10," ",IF(AO$10<$G18+$F18,SLN($E18,$H18,$G18)," "))))))," ") | AP18: =IF($F18+$G18=AP$10,($E18-$H18)/$G18/2,(IF($F18=AP$10,($E18-$H18)/$G18/2,0))) -> #VALUE! | AQ18: =IFERROR(IF($F18+$G18=AQ$10,AP18,(IF($F18=AQ$10,AP18,(IF($F18>AQ$10," ",IF(AQ$10<$G18+$F18,SLN($E18,$H18,$G18)," "))))))," ") | AR18: =IF($F18+$G18=AR$10,($E18-$H18)/$G18/2,(IF($F18=AR$10,($E18-$H18)/$G18/2,0))) -> #VALUE! | AS18: =IFERROR(IF($F18+$G18=AS$10,AR18,(IF($F18=AS$10,AR18,(IF($F18>AS$10," ",IF(AS$10<$G18+$F18,SLN($E18,$H18,$G18)," "))))))," ") | AT18: =IF($F18+$G18=AT$10,($E18-$H18)/$G18/2,(IF($F18=AT$10,($E18-$H18)/$G18/2,0))) -> #VALUE! | AU18: =IFERROR(IF($F18+$G18=AU$10,AT18,(IF($F18=AU$10,AT18,(IF($F18>AU$10," ",IF(AU$10<$G18+$F18,SLN($E18,$H18,$G18)," "))))))," ") | AV18: =IF($F18+$G18=AV$10,($E18-$H18)/$G18/2,(IF($F18=AV$10,($E18-$H18)/$G18/2,0))) -> #VALUE! | AW18: =IFERROR(IF($F18+$G18=AW$10,AV18,(IF($F18=AW$10,AV18,(IF($F18>AW$10," ",IF(AW$10<$G18+$F18,SLN($E18,$H18,$G18)," "))))))," ") | AY18: =C18 | AZ18: =AY18 | BA18: =B18 | BB18: =D18 | BC18: =IF(BB18="","","Depreciation_Expense") | BD18: =INDEX($K$10:$BD$55, MATCH(BB18, $D$10:$D$55, 0), MATCH($H$4, $K$10:$BD$10, 1)) -> #N/A
A19: =IF(EOD!$F10="","",EOD!$F10) | B19: =IF(EOD!$C10="","",EOD!$C10) | C19: =IF(EOD!$A10="","",EOD!$A10) | D19: =IF(EOD!$D10="","",EOD!$D10) | E19: =IF(EOD!E10="","",EOD!E10) | F19: =IF(EOD!G10="","",EOD!G10) | G19: =IF(EOD!H10="","",EOD!H10) | H19: =IF(EOD!I10="","",EOD!I10) | I19: =IFERROR(IF(F19<$K$10,(($K$10-F19-1)*((E19-H19)/G19)+(((E19-H19)/G19)/2)),0),0) -> 0 | J19: =IF($F19+$G19=J$10,($E19-$H19)/$G19/2,(IF($F19=J$10,($E19-$H19)/$G19/2,0))) -> #VALUE! | K19: =IFERROR(IF($F19+$G19=K$10,J19,(IF($F19=K$10,J19,(IF($F19>K$10," ",IF(K$10<$G19+$F19,SLN($E19,$H19,$G19)," "))))))," ") | L19: =IF($F19+$G19=L$10,($E19-$H19)/$G19/2,(IF($F19=L$10,($E19-$H19)/$G19/2,0))) -> #VALUE! | M19: =IFERROR(IF($F19+$G19=M$10,L19,(IF($F19=M$10,L19,(IF($F19>M$10," ",IF(M$10<$G19+$F19,SLN($E19,$H19,$G19)," "))))))," ") | N19: =IF($F19+$G19=N$10,($E19-$H19)/$G19/2,(IF($F19=N$10,($E19-$H19)/$G19/2,0))) -> #VALUE! | O19: =IFERROR(IF($F19+$G19=O$10,N19,(IF($F19=O$10,N19,(IF($F19>O$10," ",IF(O$10<$G19+$F19,SLN($E19,$H19,$G19)," "))))))," ") | P19: =IF($F19+$G19=P$10,($E19-$H19)/$G19/2,(IF($F19=P$10,($E19-$H19)/$G19/2,0))) -> #VALUE! | Q19: =IFERROR(IF($F19+$G19=Q$10,P19,(IF($F19=Q$10,P19,(IF($F19>Q$10," ",IF(Q$10<$G19+$F19,SLN($E19,$H19,$G19)," "))))))," ") | R19: =IF($F19+$G19=R$10,($E19-$H19)/$G19/2,(IF($F19=R$10,($E19-$H19)/$G19/2,0))) -> #VALUE! | S19: =IFERROR(IF($F19+$G19=S$10,R19,(IF($F19=S$10,R19,(IF($F19>S$10," ",IF(S$10<$G19+$F19,SLN($E19,$H19,$G19)," "))))))," ") | T19: =IF($F19+$G19=T$10,($E19-$H19)/$G19/2,(IF($F19=T$10,($E19-$H19)/$G19/2,0))) -> #VALUE! | U19: =IFERROR(IF($F19+$G19=U$10,T19,(IF($F19=U$10,T19,(IF($F19>U$10," ",IF(U$10<$G19+$F19,SLN($E19,$H19,$G19)," "))))))," ") | V19: =IF($F19+$G19=V$10,($E19-$H19)/$G19/2,(IF($F19=V$10,($E19-$H19)/$G19/2,0))) -> #VALUE! | W19: =IFERROR(IF($F19+$G19=W$10,V19,(IF($F19=W$10,V19,(IF($F19>W$10," ",IF(W$10<$G19+$F19,SLN($E19,$H19,$G19)," "))))))," ") | X19: =IF($F19+$G19=X$10,($E19-$H19)/$G19/2,(IF($F19=X$10,($E19-$H19)/$G19/2,0))) -> #VALUE! | Y19: =IFERROR(IF($F19+$G19=Y$10,X19,(IF($F19=Y$10,X19,(IF($F19>Y$10," ",IF(Y$10<$G19+$F19,SLN($E19,$H19,$G19)," "))))))," ") | Z19: =IF($F19+$G19=Z$10,($E19-$H19)/$G19/2,(IF($F19=Z$10,($E19-$H19)/$G19/2,0))) -> #VALUE! | AA19: =IFERROR(IF($F19+$G19=AA$10,Z19,(IF($F19=AA$10,Z19,(IF($F19>AA$10," ",IF(AA$10<$G19+$F19,SLN($E19,$H19,$G19)," "))))))," ") | AB19: =IF($F19+$G19=AB$10,($E19-$H19)/$G19/2,(IF($F19=AB$10,($E19-$H19)/$G19/2,0))) -> #VALUE! | AC19: =IFERROR(IF($F19+$G19=AC$10,AB19,(IF($F19=AC$10,AB19,(IF($F19>AC$10," ",IF(AC$10<$G19+$F19,SLN($E19,$H19,$G19)," "))))))," ") | AD19: =IF($F19+$G19=AD$10,($E19-$H19)/$G19/2,(IF($F19=AD$10,($E19-$H19)/$G19/2,0))) -> #VALUE! | AE19: =IFERROR(IF($F19+$G19=AE$10,AD19,(IF($F19=AE$10,AD19,(IF($F19>AE$10," ",IF(AE$10<$G19+$F19,SLN($E19,$H19,$G19)," "))))))," ") | AF19: =IF($F19+$G19=AF$10,($E19-$H19)/$G19/2,(IF($F19=AF$10,($E19-$H19)/$G19/2,0))) -> #VALUE! | AG19: =IFERROR(IF($F19+$G19=AG$10,AF19,(IF($F19=AG$10,AF19,(IF($F19>AG$10," ",IF(AG$10<$G19+$F19,SLN($E19,$H19,$G19)," "))))))," ") | AH19: =IF($F19+$G19=AH$10,($E19-$H19)/$G19/2,(IF($F19=AH$10,($E19-$H19)/$G19/2,0))) -> #VALUE! | AI19: =IFERROR(IF($F19+$G19=AI$10,AH19,(IF($F19=AI$10,AH19,(IF($F19>AI$10," ",IF(AI$10<$G19+$F19,SLN($E19,$H19,$G19)," "))))))," ") | AJ19: =IF($F19+$G19=AJ$10,($E19-$H19)/$G19/2,(IF($F19=AJ$10,($E19-$H19)/$G19/2,0))) -> #VALUE! | AK19: =IFERROR(IF($F19+$G19=AK$10,AJ19,(IF($F19=AK$10,AJ19,(IF($F19>AK$10," ",IF(AK$10<$G19+$F19,SLN($E19,$H19,$G19)," "))))))," ") | AL19: =IF($F19+$G19=AL$10,($E19-$H19)/$G19/2,(IF($F19=AL$10,($E19-$H19)/$G19/2,0))) -> #VALUE! | AM19: =IFERROR(IF($F19+$G19=AM$10,AL19,(IF($F19=AM$10,AL19,(IF($F19>AM$10," ",IF(AM$10<$G19+$F19,SLN($E19,$H19,$G19)," "))))))," ") | AN19: =IF($F19+$G19=AN$10,($E19-$H19)/$G19/2,(IF($F19=AN$10,($E19-$H19)/$G19/2,0))) -> #VALUE! | AO19: =IFERROR(IF($F19+$G19=AO$10,AN19,(IF($F19=AO$10,AN19,(IF($F19>AO$10," ",IF(AO$10<$G19+$F19,SLN($E19,$H19,$G19)," "))))))," ") | AP19: =IF($F19+$G19=AP$10,($E19-$H19)/$G19/2,(IF($F19=AP$10,($E19-$H19)/$G19/2,0))) -> #VALUE! | AQ19: =IFERROR(IF($F19+$G19=AQ$10,AP19,(IF($F19=AQ$10,AP19,(IF($F19>AQ$10," ",IF(AQ$10<$G19+$F19,SLN($E19,$H19,$G19)," "))))))," ") | AR19: =IF($F19+$G19=AR$10,($E19-$H19)/$G19/2,(IF($F19=AR$10,($E19-$H19)/$G19/2,0))) -> #VALUE! | AS19: =IFERROR(IF($F19+$G19=AS$10,AR19,(IF($F19=AS$10,AR19,(IF($F19>AS$10," ",IF(AS$10<$G19+$F19,SLN($E19,$H19,$G19)," "))))))," ") | AT19: =IF($F19+$G19=AT$10,($E19-$H19)/$G19/2,(IF($F19=AT$10,($E19-$H19)/$G19/2,0))) -> #VALUE! | AU19: =IFERROR(IF($F19+$G19=AU$10,AT19,(IF($F19=AU$10,AT19,(IF($F19>AU$10," ",IF(AU$10<$G19+$F19,SLN($E19,$H19,$G19)," "))))))," ") | AV19: =IF($F19+$G19=AV$10,($E19-$H19)/$G19/2,(IF($F19=AV$10,($E19-$H19)/$G19/2,0))) -> #VALUE! | AW19: =IFERROR(IF($F19+$G19=AW$10,AV19,(IF($F19=AW$10,AV19,(IF($F19>AW$10," ",IF(AW$10<$G19+$F19,SLN($E19,$H19,$G19)," "))))))," ") | AY19: =C19 | AZ19: =AY19 | BA19: =B19 | BB19: =D19 | BC19: =IF(BB19="","","Depreciation_Expense") | BD19: =INDEX($K$10:$BD$55, MATCH(BB19, $D$10:$D$55, 0), MATCH($H$4, $K$10:$BD$10, 1)) -> #N/A
A20: =IF(EOD!$F11="","",EOD!$F11) | B20: =IF(EOD!$C11="","",EOD!$C11) | C20: =IF(EOD!$A11="","",EOD!$A11) | D20: =IF(EOD!$D11="","",EOD!$D11) | E20: =IF(EOD!E11="","",EOD!E11) | F20: =IF(EOD!G11="","",EOD!G11) | G20: =IF(EOD!H11="","",EOD!H11) | H20: =IF(EOD!I11="","",EOD!I11) | I20: =IFERROR(IF(F20<$K$10,(($K$10-F20-1)*((E20-H20)/G20)+(((E20-H20)/G20)/2)),0),0) -> 0 | J20: =IF($F20+$G20=J$10,($E20-$H20)/$G20/2,(IF($F20=J$10,($E20-$H20)/$G20/2,0))) -> #VALUE! | K20: =IFERROR(IF($F20+$G20=K$10,J20,(IF($F20=K$10,J20,(IF($F20>K$10," ",IF(K$10<$G20+$F20,SLN($E20,$H20,$G20)," "))))))," ") | L20: =IF($F20+$G20=L$10,($E20-$H20)/$G20/2,(IF($F20=L$10,($E20-$H20)/$G20/2,0))) -> #VALUE! | M20: =IFERROR(IF($F20+$G20=M$10,L20,(IF($F20=M$10,L20,(IF($F20>M$10," ",IF(M$10<$G20+$F20,SLN($E20,$H20,$G20)," "))))))," ") | N20: =IF($F20+$G20=N$10,($E20-$H20)/$G20/2,(IF($F20=N$10,($E20-$H20)/$G20/2,0))) -> #VALUE! | O20: =IFERROR(IF($F20+$G20=O$10,N20,(IF($F20=O$10,N20,(IF($F20>O$10," ",IF(O$10<$G20+$F20,SLN($E20,$H20,$G20)," "))))))," ") | P20: =IF($F20+$G20=P$10,($E20-$H20)/$G20/2,(IF($F20=P$10,($E20-$H20)/$G20/2,0))) -> #VALUE! | Q20: =IFERROR(IF($F20+$G20=Q$10,P20,(IF($F20=Q$10,P20,(IF($F20>Q$10," ",IF(Q$10<$G20+$F20,SLN($E20,$H20,$G20)," "))))))," ") | R20: =IF($F20+$G20=R$10,($E20-$H20)/$G20/2,(IF($F20=R$10,($E20-$H20)/$G20/2,0))) -> #VALUE! | S20: =IFERROR(IF($F20+$G20=S$10,R20,(IF($F20=S$10,R20,(IF($F20>S$10," ",IF(S$10<$G20+$F20,SLN($E20,$H20,$G20)," "))))))," ") | T20: =IF($F20+$G20=T$10,($E20-$H20)/$G20/2,(IF($F20=T$10,($E20-$H20)/$G20/2,0))) -> #VALUE! | U20: =IFERROR(IF($F20+$G20=U$10,T20,(IF($F20=U$10,T20,(IF($F20>U$10," ",IF(U$10<$G20+$F20,SLN($E20,$H20,$G20)," "))))))," ") | V20: =IF($F20+$G20=V$10,($E20-$H20)/$G20/2,(IF($F20=V$10,($E20-$H20)/$G20/2,0))) -> #VALUE! | W20: =IFERROR(IF($F20+$G20=W$10,V20,(IF($F20=W$10,V20,(IF($F20>W$10," ",IF(W$10<$G20+$F20,SLN($E20,$H20,$G20)," "))))))," ") | X20: =IF($F20+$G20=X$10,($E20-$H20)/$G20/2,(IF($F20=X$10,($E20-$H20)/$G20/2,0))) -> #VALUE! | Y20: =IFERROR(IF($F20+$G20=Y$10,X20,(IF($F20=Y$10,X20,(IF($F20>Y$10," ",IF(Y$10<$G20+$F20,SLN($E20,$H20,$G20)," "))))))," ") | Z20: =IF($F20+$G20=Z$10,($E20-$H20)/$G20/2,(IF($F20=Z$10,($E20-$H20)/$G20/2,0))) -> #VALUE! | AA20: =IFERROR(IF($F20+$G20=AA$10,Z20,(IF($F20=AA$10,Z20,(IF($F20>AA$10," ",IF(AA$10<$G20+$F20,SLN($E20,$H20,$G20)," "))))))," ") | AB20: =IF($F20+$G20=AB$10,($E20-$H20)/$G20/2,(IF($F20=AB$10,($E20-$H20)/$G20/2,0))) -> #VALUE! | AC20: =IFERROR(IF($F20+$G20=AC$10,AB20,(IF($F20=AC$10,AB20,(IF($F20>AC$10," ",IF(AC$10<$G20+$F20,SLN($E20,$H20,$G20)," "))))))," ") | AD20: =IF($F20+$G20=AD$10,($E20-$H20)/$G20/2,(IF($F20=AD$10,($E20-$H20)/$G20/2,0))) -> #VALUE! | AE20: =IFERROR(IF($F20+$G20=AE$10,AD20,(IF($F20=AE$10,AD20,(IF($F20>AE$10," ",IF(AE$10<$G20+$F20,SLN($E20,$H20,$G20)," "))))))," ") | AF20: =IF($F20+$G20=AF$10,($E20-$H20)/$G20/2,(IF($F20=AF$10,($E20-$H20)/$G20/2,0))) -> #VALUE! | AG20: =IFERROR(IF($F20+$G20=AG$10,AF20,(IF($F20=AG$10,AF20,(IF($F20>AG$10," ",IF(AG$10<$G20+$F20,SLN($E20,$H20,$G20)," "))))))," ") | AH20: =IF($F20+$G20=AH$10,($E20-$H20)/$G20/2,(IF($F20=AH$10,($E20-$H20)/$G20/2,0))) -> #VALUE! | AI20: =IFERROR(IF($F20+$G20=AI$10,AH20,(IF($F20=AI$10,AH20,(IF($F20>AI$10," ",IF(AI$10<$G20+$F20,SLN($E20,$H20,$G20)," "))))))," ") | AJ20: =IF($F20+$G20=AJ$10,($E20-$H20)/$G20/2,(IF($F20=AJ$10,($E20-$H20)/$G20/2,0))) -> #VALUE! | AK20: =IFERROR(IF($F20+$G20=AK$10,AJ20,(IF($F20=AK$10,AJ20,(IF($F20>AK$10," ",IF(AK$10<$G20+$F20,SLN($E20,$H20,$G20)," "))))))," ") | AL20: =IF($F20+$G20=AL$10,($E20-$H20)/$G20/2,(IF($F20=AL$10,($E20-$H20)/$G20/2,0))) -> #VALUE! | AM20: =IFERROR(IF($F20+$G20=AM$10,AL20,(IF($F20=AM$10,AL20,(IF($F20>AM$10," ",IF(AM$10<$G20+$F20,SLN($E20,$H20,$G20)," "))))))," ") | AN20: =IF($F20+$G20=AN$10,($E20-$H20)/$G20/2,(IF($F20=AN$10,($E20-$H20)/$G20/2,0))) -> #VALUE! | AO20: =IFERROR(IF($F20+$G20=AO$10,AN20,(IF($F20=AO$10,AN20,(IF($F20>AO$10," ",IF(AO$10<$G20+$F20,SLN($E20,$H20,$G20)," "))))))," ") | AP20: =IF($F20+$G20=AP$10,($E20-$H20)/$G20/2,(IF($F20=AP$10,($E20-$H20)/$G20/2,0))) -> #VALUE! | AQ20: =IFERROR(IF($F20+$G20=AQ$10,AP20,(IF($F20=AQ$10,AP20,(IF($F20>AQ$10," ",IF(AQ$10<$G20+$F20,SLN($E20,$H20,$G20)," "))))))," ") | AR20: =IF($F20+$G20=AR$10,($E20-$H20)/$G20/2,(IF($F20=AR$10,($E20-$H20)/$G20/2,0))) -> #VALUE! | AS20: =IFERROR(IF($F20+$G20=AS$10,AR20,(IF($F20=AS$10,AR20,(IF($F20>AS$10," ",IF(AS$10<$G20+$F20,SLN($E20,$H20,$G20)," "))))))," ") | AT20: =IF($F20+$G20=AT$10,($E20-$H20)/$G20/2,(IF($F20=AT$10,($E20-$H20)/$G20/2,0))) -> #VALUE! | AU20: =IFERROR(IF($F20+$G20=AU$10,AT20,(IF($F20=AU$10,AT20,(IF($F20>AU$10," ",IF(AU$10<$G20+$F20,SLN($E20,$H20,$G20)," "))))))," ") | AV20: =IF($F20+$G20=AV$10,($E20-$H20)/$G20/2,(IF($F20=AV$10,($E20-$H20)/$G20/2,0))) -> #VALUE! | AW20: =IFERROR(IF($F20+$G20=AW$10,AV20,(IF($F20=AW$10,AV20,(IF($F20>AW$10," ",IF(AW$10<$G20+$F20,SLN($E20,$H20,$G20)," "))))))," ") | AY20: =C20 | AZ20: =AY20 | BA20: =B20 | BB20: =D20 | BC20: =IF(BB20="","","Depreciation_Expense") | BD20: =INDEX($K$10:$BD$55, MATCH(BB20, $D$10:$D$55, 0), MATCH($H$4, $K$10:$BD$10, 1)) -> #N/A
A21: =IF(EOD!$F12="","",EOD!$F12) | B21: =IF(EOD!$C12="","",EOD!$C12) | C21: =IF(EOD!$A12="","",EOD!$A12) | D21: =IF(EOD!$D12="","",EOD!$D12) | E21: =IF(EOD!E12="","",EOD!E12) | F21: =IF(EOD!G12="","",EOD!G12) | G21: =IF(EOD!H12="","",EOD!H12) | H21: =IF(EOD!I12="","",EOD!I12) | I21: =IFERROR(IF(F21<$K$10,(($K$10-F21-1)*((E21-H21)/G21)+(((E21-H21)/G21)/2)),0),0) -> 0 | J21: =IF($F21+$G21=J$10,($E21-$H21)/$G21/2,(IF($F21=J$10,($E21-$H21)/$G21/2,0))) -> #VALUE! | K21: =IFERROR(IF($F21+$G21=K$10,J21,(IF($F21=K$10,J21,(IF($F21>K$10," ",IF(K$10<$G21+$F21,SLN($E21,$H21,$G21)," "))))))," ") | L21: =IF($F21+$G21=L$10,($E21-$H21)/$G21/2,(IF($F21=L$10,($E21-$H21)/$G21/2,0))) -> #VALUE! | M21: =IFERROR(IF($F21+$G21=M$10,L21,(IF($F21=M$10,L21,(IF($F21>M$10," ",IF(M$10<$G21+$F21,SLN($E21,$H21,$G21)," "))))))," ") | N21: =IF($F21+$G21=N$10,($E21-$H21)/$G21/2,(IF($F21=N$10,($E21-$H21)/$G21/2,0))) -> #VALUE! | O21: =IFERROR(IF($F21+$G21=O$10,N21,(IF($F21=O$10,N21,(IF($F21>O$10," ",IF(O$10<$G21+$F21,SLN($E21,$H21,$G21)," "))))))," ") | P21: =IF($F21+$G21=P$10,($E21-$H21)/$G21/2,(IF($F21=P$10,($E21-$H21)/$G21/2,0))) -> #VALUE! | Q21: =IFERROR(IF($F21+$G21=Q$10,P21,(IF($F21=Q$10,P21,(IF($F21>Q$10," ",IF(Q$10<$G21+$F21,SLN($E21,$H21,$G21)," "))))))," ") | R21: =IF($F21+$G21=R$10,($E21-$H21)/$G21/2,(IF($F21=R$10,($E21-$H21)/$G21/2,0))) -> #VALUE! | S21: =IFERROR(IF($F21+$G21=S$10,R21,(IF($F21=S$10,R21,(IF($F21>S$10," ",IF(S$10<$G21+$F21,SLN($E21,$H21,$G21)," "))))))," ") | T21: =IF($F21+$G21=T$10,($E21-$H21)/$G21/2,(IF($F21=T$10,($E21-$H21)/$G21/2,0))) -> #VALUE! | U21: =IFERROR(IF($F21+$G21=U$10,T21,(IF($F21=U$10,T21,(IF($F21>U$10," ",IF(U$10<$G21+$F21,SLN($E21,$H21,$G21)," "))))))," ") | V21: =IF($F21+$G21=V$10,($E21-$H21)/$G21/2,(IF($F21=V$10,($E21-$H21)/$G21/2,0))) -> #VALUE! | W21: =IFERROR(IF($F21+$G21=W$10,V21,(IF($F21=W$10,V21,(IF($F21>W$10," ",IF(W$10<$G21+$F21,SLN($E21,$H21,$G21)," "))))))," ") | X21: =IF($F21+$G21=X$10,($E21-$H21)/$G21/2,(IF($F21=X$10,($E21-$H21)/$G21/2,0))) -> #VALUE! | Y21: =IFERROR(IF($F21+$G21=Y$10,X21,(IF($F21=Y$10,X21,(IF($F21>Y$10," ",IF(Y$10<$G21+$F21,SLN($E21,$H21,$G21)," "))))))," ") | Z21: =IF($F21+$G21=Z$10,($E21-$H21)/$G21/2,(IF($F21=Z$10,($E21-$H21)/$G21/2,0))) -> #VALUE! | AA21: =IFERROR(IF($F21+$G21=AA$10,Z21,(IF($F21=AA$10,Z21,(IF($F21>AA$10," ",IF(AA$10<$G21+$F21,SLN($E21,$H21,$G21)," "))))))," ") | AB21: =IF($F21+$G21=AB$10,($E21-$H21)/$G21/2,(IF($F21=AB$10,($E21-$H21)/$G21/2,0))) -> #VALUE! | AC21: =IFERROR(IF($F21+$G21=AC$10,AB21,(IF($F21=AC$10,AB21,(IF($F21>AC$10," ",IF(AC$10<$G21+$F21,SLN($E21,$H21,$G21)," "))))))," ") | AD21: =IF($F21+$G21=AD$10,($E21-$H21)/$G21/2,(IF($F21=AD$10,($E21-$H21)/$G21/2,0))) -> #VALUE! | AE21: =IFERROR(IF($F21+$G21=AE$10,AD21,(IF($F21=AE$10,AD21,(IF($F21>AE$10," ",IF(AE$10<$G21+$F21,SLN($E21,$H21,$G21)," "))))))," ") | AF21: =IF($F21+$G21=AF$10,($E21-$H21)/$G21/2,(IF($F21=AF$10,($E21-$H21)/$G21/2,0))) -> #VALUE! | AG21: =IFERROR(IF($F21+$G21=AG$10,AF21,(IF($F21=AG$10,AF21,(IF($F21>AG$10," ",IF(AG$10<$G21+$F21,SLN($E21,$H21,$G21)," "))))))," ") | AH21: =IF($F21+$G21=AH$10,($E21-$H21)/$G21/2,(IF($F21=AH$10,($E21-$H21)/$G21/2,0))) -> #VALUE! | AI21: =IFERROR(IF($F21+$G21=AI$10,AH21,(IF($F21=AI$10,AH21,(IF($F21>AI$10," ",IF(AI$10<$G21+$F21,SLN($E21,$H21,$G21)," "))))))," ") | AJ21: =IF($F21+$G21=AJ$10,($E21-$H21)/$G21/2,(IF($F21=AJ$10,($E21-$H21)/$G21/2,0))) -> #VALUE! | AK21: =IFERROR(IF($F21+$G21=AK$10,AJ21,(IF($F21=AK$10,AJ21,(IF($F21>AK$10," ",IF(AK$10<$G21+$F21,SLN($E21,$H21,$G21)," "))))))," ") | AL21: =IF($F21+$G21=AL$10,($E21-$H21)/$G21/2,(IF($F21=AL$10,($E21-$H21)/$G21/2,0))) -> #VALUE! | AM21: =IFERROR(IF($F21+$G21=AM$10,AL21,(IF($F21=AM$10,AL21,(IF($F21>AM$10," ",IF(AM$10<$G21+$F21,SLN($E21,$H21,$G21)," "))))))," ") | AN21: =IF($F21+$G21=AN$10,($E21-$H21)/$G21/2,(IF($F21=AN$10,($E21-$H21)/$G21/2,0))) -> #VALUE! | AO21: =IFERROR(IF($F21+$G21=AO$10,AN21,(IF($F21=AO$10,AN21,(IF($F21>AO$10," ",IF(AO$10<$G21+$F21,SLN($E21,$H21,$G21)," "))))))," ") | AP21: =IF($F21+$G21=AP$10,($E21-$H21)/$G21/2,(IF($F21=AP$10,($E21-$H21)/$G21/2,0))) -> #VALUE! | AQ21: =IFERROR(IF($F21+$G21=AQ$10,AP21,(IF($F21=AQ$10,AP21,(IF($F21>AQ$10," ",IF(AQ$10<$G21+$F21,SLN($E21,$H21,$G21)," "))))))," ") | AR21: =IF($F21+$G21=AR$10,($E21-$H21)/$G21/2,(IF($F21=AR$10,($E21-$H21)/$G21/2,0))) -> #VALUE! | AS21: =IFERROR(IF($F21+$G21=AS$10,AR21,(IF($F21=AS$10,AR21,(IF($F21>AS$10," ",IF(AS$10<$G21+$F21,SLN($E21,$H21,$G21)," "))))))," ") | AT21: =IF($F21+$G21=AT$10,($E21-$H21)/$G21/2,(IF($F21=AT$10,($E21-$H21)/$G21/2,0))) -> #VALUE! | AU21: =IFERROR(IF($F21+$G21=AU$10,AT21,(IF($F21=AU$10,AT21,(IF($F21>AU$10," ",IF(AU$10<$G21+$F21,SLN($E21,$H21,$G21)," "))))))," ") | AV21: =IF($F21+$G21=AV$10,($E21-$H21)/$G21/2,(IF($F21=AV$10,($E21-$H21)/$G21/2,0))) -> #VALUE! | AW21: =IFERROR(IF($F21+$G21=AW$10,AV21,(IF($F21=AW$10,AV21,(IF($F21>AW$10," ",IF(AW$10<$G21+$F21,SLN($E21,$H21,$G21)," "))))))," ") | AY21: =C21 | AZ21: =AY21 | BA21: =B21 | BB21: =D21 | BC21: =IF(BB21="","","Depreciation_Expense") | BD21: =INDEX($K$10:$BD$55, MATCH(BB21, $D$10:$D$55, 0), MATCH($H$4, $K$10:$BD$10, 1)) -> #N/A
A22: =IF(EOD!$F13="","",EOD!$F13) | B22: =IF(EOD!$C13="","",EOD!$C13) | C22: =IF(EOD!$A13="","",EOD!$A13) | D22: =IF(EOD!$D13="","",EOD!$D13) | E22: =IF(EOD!E13="","",EOD!E13) | F22: =IF(EOD!G13="","",EOD!G13) | G22: =IF(EOD!H13="","",EOD!H13) | H22: =IF(EOD!I13="","",EOD!I13) | I22: =IFERROR(IF(F22<$K$10,(($K$10-F22-1)*((E22-H22)/G22)+(((E22-H22)/G22)/2)),0),0) -> 0 | J22: =IF($F22+$G22=J$10,($E22-$H22)/$G22/2,(IF($F22=J$10,($E22-$H22)/$G22/2,0))) -> #VALUE! | K22: =IFERROR(IF($F22+$G22=K$10,J22,(IF($F22=K$10,J22,(IF($F22>K$10," ",IF(K$10<$G22+$F22,SLN($E22,$H22,$G22)," "))))))," ") | L22: =IF($F22+$G22=L$10,($E22-$H22)/$G22/2,(IF($F22=L$10,($E22-$H22)/$G22/2,0))) -> #VALUE! | M22: =IFERROR(IF($F22+$G22=M$10,L22,(IF($F22=M$10,L22,(IF($F22>M$10," ",IF(M$10<$G22+$F22,SLN($E22,$H22,$G22)," "))))))," ") | N22: =IF($F22+$G22=N$10,($E22-$H22)/$G22/2,(IF($F22=N$10,($E22-$H22)/$G22/2,0))) -> #VALUE! | O22: =IFERROR(IF($F22+$G22=O$10,N22,(IF($F22=O$10,N22,(IF($F22>O$10," ",IF(O$10<$G22+$F22,SLN($E22,$H22,$G22)," "))))))," ") | P22: =IF($F22+$G22=P$10,($E22-$H22)/$G22/2,(IF($F22=P$10,($E22-$H22)/$G22/2,0))) -> #VALUE! | Q22: =IFERROR(IF($F22+$G22=Q$10,P22,(IF($F22=Q$10,P22,(IF($F22>Q$10," ",IF(Q$10<$G22+$F22,SLN($E22,$H22,$G22)," "))))))," ") | R22: =IF($F22+$G22=R$10,($E22-$H22)/$G22/2,(IF($F22=R$10,($E22-$H22)/$G22/2,0))) -> #VALUE! | S22: =IFERROR(IF($F22+$G22=S$10,R22,(IF($F22=S$10,R22,(IF($F22>S$10," ",IF(S$10<$G22+$F22,SLN($E22,$H22,$G22)," "))))))," ") | T22: =IF($F22+$G22=T$10,($E22-$H22)/$G22/2,(IF($F22=T$10,($E22-$H22)/$G22/2,0))) -> #VALUE! | U22: =IFERROR(IF($F22+$G22=U$10,T22,(IF($F22=U$10,T22,(IF($F22>U$10," ",IF(U$10<$G22+$F22,SLN($E22,$H22,$G22)," "))))))," ") | V22: =IF($F22+$G22=V$10,($E22-$H22)/$G22/2,(IF($F22=V$10,($E22-$H22)/$G22/2,0))) -> #VALUE! | W22: =IFERROR(IF($F22+$G22=W$10,V22,(IF($F22=W$10,V22,(IF($F22>W$10," ",IF(W$10<$G22+$F22,SLN($E22,$H22,$G22)," "))))))," ") | X22: =IF($F22+$G22=X$10,($E22-$H22)/$G22/2,(IF($F22=X$10,($E22-$H22)/$G22/2,0))) -> #VALUE! | Y22: =IFERROR(IF($F22+$G22=Y$10,X22,(IF($F22=Y$10,X22,(IF($F22>Y$10," ",IF(Y$10<$G22+$F22,SLN($E22,$H22,$G22)," "))))))," ") | Z22: =IF($F22+$G22=Z$10,($E22-$H22)/$G22/2,(IF($F22=Z$10,($E22-$H22)/$G22/2,0))) -> #VALUE! | AA22: =IFERROR(IF($F22+$G22=AA$10,Z22,(IF($F22=AA$10,Z22,(IF($F22>AA$10," ",IF(AA$10<$G22+$F22,SLN($E22,$H22,$G22)," "))))))," ") | AB22: =IF($F22+$G22=AB$10,($E22-$H22)/$G22/2,(IF($F22=AB$10,($E22-$H22)/$G22/2,0))) -> #VALUE! | AC22: =IFERROR(IF($F22+$G22=AC$10,AB22,(IF($F22=AC$10,AB22,(IF($F22>AC$10," ",IF(AC$10<$G22+$F22,SLN($E22,$H22,$G22)," "))))))," ") | AD22: =IF($F22+$G22=AD$10,($E22-$H22)/$G22/2,(IF($F22=AD$10,($E22-$H22)/$G22/2,0))) -> #VALUE! | AE22: =IFERROR(IF($F22+$G22=AE$10,AD22,(IF($F22=AE$10,AD22,(IF($F22>AE$10," ",IF(AE$10<$G22+$F22,SLN($E22,$H22,$G22)," "))))))," ") | AF22: =IF($F22+$G22=AF$10,($E22-$H22)/$G22/2,(IF($F22=AF$10,($E22-$H22)/$G22/2,0))) -> #VALUE! | AG22: =IFERROR(IF($F22+$G22=AG$10,AF22,(IF($F22=AG$10,AF22,(IF($F22>AG$10," ",IF(AG$10<$G22+$F22,SLN($E22,$H22,$G22)," "))))))," ") | AH22: =IF($F22+$G22=AH$10,($E22-$H22)/$G22/2,(IF($F22=AH$10,($E22-$H22)/$G22/2,0))) -> #VALUE! | AI22: =IFERROR(IF($F22+$G22=AI$10,AH22,(IF($F22=AI$10,AH22,(IF($F22>AI$10," ",IF(AI$10<$G22+$F22,SLN($E22,$H22,$G22)," "))))))," ") | AJ22: =IF($F22+$G22=AJ$10,($E22-$H22)/$G22/2,(IF($F22=AJ$10,($E22-$H22)/$G22/2,0))) -> #VALUE! | AK22: =IFERROR(IF($F22+$G22=AK$10,AJ22,(IF($F22=AK$10,AJ22,(IF($F22>AK$10," ",IF(AK$10<$G22+$F22,SLN($E22,$H22,$G22)," "))))))," ") | AL22: =IF($F22+$G22=AL$10,($E22-$H22)/$G22/2,(IF($F22=AL$10,($E22-$H22)/$G22/2,0))) -> #VALUE! | AM22: =IFERROR(IF($F22+$G22=AM$10,AL22,(IF($F22=AM$10,AL22,(IF($F22>AM$10," ",IF(AM$10<$G22+$F22,SLN($E22,$H22,$G22)," "))))))," ") | AN22: =IF($F22+$G22=AN$10,($E22-$H22)/$G22/2,(IF($F22=AN$10,($E22-$H22)/$G22/2,0))) -> #VALUE! | AO22: =IFERROR(IF($F22+$G22=AO$10,AN22,(IF($F22=AO$10,AN22,(IF($F22>AO$10," ",IF(AO$10<$G22+$F22,SLN($E22,$H22,$G22)," "))))))," ") | AP22: =IF($F22+$G22=AP$10,($E22-$H22)/$G22/2,(IF($F22=AP$10,($E22-$H22)/$G22/2,0))) -> #VALUE! | AQ22: =IFERROR(IF($F22+$G22=AQ$10,AP22,(IF($F22=AQ$10,AP22,(IF($F22>AQ$10," ",IF(AQ$10<$G22+$F22,SLN($E22,$H22,$G22)," "))))))," ") | AR22: =IF($F22+$G22=AR$10,($E22-$H22)/$G22/2,(IF($F22=AR$10,($E22-$H22)/$G22/2,0))) -> #VALUE! | AS22: =IFERROR(IF($F22+$G22=AS$10,AR22,(IF($F22=AS$10,AR22,(IF($F22>AS$10," ",IF(AS$10<$G22+$F22,SLN($E22,$H22,$G22)," "))))))," ") | AT22: =IF($F22+$G22=AT$10,($E22-$H22)/$G22/2,(IF($F22=AT$10,($E22-$H22)/$G22/2,0))) -> #VALUE! | AU22: =IFERROR(IF($F22+$G22=AU$10,AT22,(IF($F22=AU$10,AT22,(IF($F22>AU$10," ",IF(AU$10<$G22+$F22,SLN($E22,$H22,$G22)," "))))))," ") | AV22: =IF($F22+$G22=AV$10,($E22-$H22)/$G22/2,(IF($F22=AV$10,($E22-$H22)/$G22/2,0))) -> #VALUE! | AW22: =IFERROR(IF($F22+$G22=AW$10,AV22,(IF($F22=AW$10,AV22,(IF($F22>AW$10," ",IF(AW$10<$G22+$F22,SLN($E22,$H22,$G22)," "))))))," ") | AY22: =C22 | AZ22: =AY22 | BA22: =B22 | BB22: =D22 | BC22: =IF(BB22="","","Depreciation_Expense") | BD22: =INDEX($K$10:$BD$55, MATCH(BB22, $D$10:$D$55, 0), MATCH($H$4, $K$10:$BD$10, 1)) -> #N/A
... A55: =IF(EOD!$F46="","",EOD!$F46) | B55: =IF(EOD!$C46="","",EOD!$C46) | C55: =IF(EOD!$A46="","",EOD!$A46) | D55: =IF(EOD!$D46="","",EOD!$D46) | E55: =IF(EOD!E46="","",EOD!E46) | F55: =IF(EOD!G46="","",EOD!G46) | G55: =IF(EOD!H46="","",EOD!H46) | H55: =IF(EOD!I46="","",EOD!I46) | I55: =IFERROR(IF(F55<$K$10,(($K$10-F55-1)*((E55-H55)/G55)+(((E55-H55)/G55)/2)),0),0) -> 0 | J55: =IF($F55+$G55=J$10,($E55-$H55)/$G55/2,(IF($F55=J$10,($E55-$H55)/$G55/2,0))) -> #VALUE! | K55: =IFERROR(IF($F55+$G55=K$10,J55,(IF($F55=K$10,J55,(IF($F55>K$10," ",IF(K$10<$G55+$F55,SLN($E55,$H55,$G55)," "))))))," ") | L55: =IF($F55+$G55=L$10,($E55-$H55)/$G55/2,(IF($F55=L$10,($E55-$H55)/$G55/2,0))) -> #VALUE! | M55: =IFERROR(IF($F55+$G55=M$10,L55,(IF($F55=M$10,L55,(IF($F55>M$10," ",IF(M$10<$G55+$F55,SLN($E55,$H55,$G55)," "))))))," ") | N55: =IF($F55+$G55=N$10,($E55-$H55)/$G55/2,(IF($F55=N$10,($E55-$H55)/$G55/2,0))) -> #VALUE! | O55: =IFERROR(IF($F55+$G55=O$10,N55,(IF($F55=O$10,N55,(IF($F55>O$10," ",IF(O$10<$G55+$F55,SLN($E55,$H55,$G55)," "))))))," ") | P55: =IF($F55+$G55=P$10,($E55-$H55)/$G55/2,(IF($F55=P$10,($E55-$H55)/$G55/2,0))) -> #VALUE! | Q55: =IFERROR(IF($F55+$G55=Q$10,P55,(IF($F55=Q$10,P55,(IF($F55>Q$10," ",IF(Q$10<$G55+$F55,SLN($E55,$H55,$G55)," "))))))," ") | R55: =IF($F55+$G55=R$10,($E55-$H55)/$G55/2,(IF($F55=R$10,($E55-$H55)/$G55/2,0))) -> #VALUE! | S55: =IFERROR(IF($F55+$G55=S$10,R55,(IF($F55=S$10,R55,(IF($F55>S$10," ",IF(S$10<$G55+$F55,SLN($E55,$H55,$G55)," "))))))," ") | T55: =IF($F55+$G55=T$10,($E55-$H55)/$G55/2,(IF($F55=T$10,($E55-$H55)/$G55/2,0))) -> #VALUE! | U55: =IFERROR(IF($F55+$G55=U$10,T55,(IF($F55=U$10,T55,(IF($F55>U$10," ",IF(U$10<$G55+$F55,SLN($E55,$H55,$G55)," "))))))," ") | V55: =IF($F55+$G55=V$10,($E55-$H55)/$G55/2,(IF($F55=V$10,($E55-$H55)/$G55/2,0))) -> #VALUE! | W55: =IFERROR(IF($F55+$G55=W$10,V55,(IF($F55=W$10,V55,(IF($F55>W$10," ",IF(W$10<$G55+$F55,SLN($E55,$H55,$G55)," "))))))," ") | X55: =IF($F55+$G55=X$10,($E55-$H55)/$G55/2,(IF($F55=X$10,($E55-$H55)/$G55/2,0))) -> #VALUE! | Y55: =IFERROR(IF($F55+$G55=Y$10,X55,(IF($F55=Y$10,X55,(IF($F55>Y$10," ",IF(Y$10<$G55+$F55,SLN($E55,$H55,$G55)," "))))))," ") | Z55: =IF($F55+$G55=Z$10,($E55-$H55)/$G55/2,(IF($F55=Z$10,($E55-$H55)/$G55/2,0))) -> #VALUE! | AA55: =IFERROR(IF($F55+$G55=AA$10,Z55,(IF($F55=AA$10,Z55,(IF($F55>AA$10," ",IF(AA$10<$G55+$F55,SLN($E55,$H55,$G55)," "))))))," ") | AB55: =IF($F55+$G55=AB$10,($E55-$H55)/$G55/2,(IF($F55=AB$10,($E55-$H55)/$G55/2,0))) -> #VALUE! | AC55: =IFERROR(IF($F55+$G55=AC$10,AB55,(IF($F55=AC$10,AB55,(IF($F55>AC$10," ",IF(AC$10<$G55+$F55,SLN($E55,$H55,$G55)," "))))))," ") | AD55: =IF($F55+$G55=AD$10,($E55-$H55)/$G55/2,(IF($F55=AD$10,($E55-$H55)/$G55/2,0))) -> #VALUE! | AE55: =IFERROR(IF($F55+$G55=AE$10,AD55,(IF($F55=AE$10,AD55,(IF($F55>AE$10," ",IF(AE$10<$G55+$F55,SLN($E55,$H55,$G55)," "))))))," ") | AF55: =IF($F55+$G55=AF$10,($E55-$H55)/$G55/2,(IF($F55=AF$10,($E55-$H55)/$G55/2,0))) -> #VALUE! | AG55: =IFERROR(IF($F55+$G55=AG$10,AF55,(IF($F55=AG$10,AF55,(IF($F55>AG$10," ",IF(AG$10<$G55+$F55,SLN($E55,$H55,$G55)," "))))))," ") | AH55: =IF($F55+$G55=AH$10,($E55-$H55)/$G55/2,(IF($F55=AH$10,($E55-$H55)/$G55/2,0))) -> #VALUE! | AI55: =IFERROR(IF($F55+$G55=AI$10,AH55,(IF($F55=AI$10,AH55,(IF($F55>AI$10," ",IF(AI$10<$G55+$F55,SLN($E55,$H55,$G55)," "))))))," ") | AJ55: =IF($F55+$G55=AJ$10,($E55-$H55)/$G55/2,(IF($F55=AJ$10,($E55-$H55)/$G55/2,0))) -> #VALUE! | AK55: =IFERROR(IF($F55+$G55=AK$10,AJ55,(IF($F55=AK$10,AJ55,(IF($F55>AK$10," ",IF(AK$10<$G55+$F55,SLN($E55,$H55,$G55)," "))))))," ") | AL55: =IF($F55+$G55=AL$10,($E55-$H55)/$G55/2,(IF($F55=AL$10,($E55-$H55)/$G55/2,0))) -> #VALUE! | AM55: =IFERROR(IF($F55+$G55=AM$10,AL55,(IF($F55=AM$10,AL55,(IF($F55>AM$10," ",IF(AM$10<$G55+$F55,SLN($E55,$H55,$G55)," "))))))," ") | AN55: =IF($F55+$G55=AN$10,($E55-$H55)/$G55/2,(IF($F55=AN$10,($E55-$H55)/$G55/2,0))) -> #VALUE! | AO55: =IFERROR(IF($F55+$G55=AO$10,AN55,(IF($F55=AO$10,AN55,(IF($F55>AO$10," ",IF(AO$10<$G55+$F55,SLN($E55,$H55,$G55)," "))))))," ") | AP55: =IF($F55+$G55=AP$10,($E55-$H55)/$G55/2,(IF($F55=AP$10,($E55-$H55)/$G55/2,0))) -> #VALUE! | AQ55: =IFERROR(IF($F55+$G55=AQ$10,AP55,(IF($F55=AQ$10,AP55,(IF($F55>AQ$10," ",IF(AQ$10<$G55+$F55,SLN($E55,$H55,$G55)," "))))))," ") | AR55: =IF($F55+$G55=AR$10,($E55-$H55)/$G55/2,(IF($F55=AR$10,($E55-$H55)/$G55/2,0))) -> #VALUE! | AS55: =IFERROR(IF($F55+$G55=AS$10,AR55,(IF($F55=AS$10,AR55,(IF($F55>AS$10," ",IF(AS$10<$G55+$F55,SLN($E55,$H55,$G55)," "))))))," ") | AT55: =IF($F55+$G55=AT$10,($E55-$H55)/$G55/2,(IF($F55=AT$10,($E55-$H55)/$G55/2,0))) -> #VALUE! | AU55: =IFERROR(IF($F55+$G55=AU$10,AT55,(IF($F55=AU$10,AT55,(IF($F55>AU$10," ",IF(AU$10<$G55+$F55,SLN($E55,$H55,$G55)," "))))))," ") | AV55: =IF($F55+$G55=AV$10,($E55-$H55)/$G55/2,(IF($F55=AV$10,($E55-$H55)/$G55/2,0))) -> #VALUE! | AW55: =IFERROR(IF($F55+$G55=AW$10,AV55,(IF($F55=AW$10,AV55,(IF($F55>AW$10," ",IF(AW$10<$G55+$F55,SLN($E55,$H55,$G55)," "))))))," ") | AY55: =C55 | AZ55: =AY55 | BA55: =B55 | BB55: =D55 | BC55: =IF(BB55="","","Depreciation_Expense") | BD55: =INDEX($K$10:$BD$55, MATCH(BB55, $D$10:$D$55, 0), MATCH($H$4, $K$10:$BD$10, 1)) -> #N/A
I56: =IFERROR(IF(F56<$K$10,(($K$10-F56-1)*((E56-H56)/G56)+(((E56-H56)/G56)/2)),0),0) -> 0 | J56: =IF($F56+$G56=J$10,($E56-$H56)/$G56/2,(IF($F56=J$10,($E56-$H56)/$G56/2,0))) -> 0 | K56: =IFERROR(IF($F56+$G56=K$10,J56,(IF($F56=K$10,J56,(IF($F56>K$10," ",IF(K$10<$G56+$F56,SLN($E56,$H56,$G56)," "))))))," ") | L56: =IF($F56+$G56=L$10,($E56-$H56)/$G56/2,(IF($F56=L$10,($E56-$H56)/$G56/2,0))) -> 0 | M56: =IFERROR(IF($F56+$G56=M$10,L56,(IF($F56=M$10,L56,(IF($F56>M$10," ",IF(M$10<$G56+$F56,SLN($E56,$H56,$G56)," "))))))," ") | N56: =IF($F56+$G56=N$10,($E56-$H56)/$G56/2,(IF($F56=N$10,($E56-$H56)/$G56/2,0))) -> 0 | O56: =IFERROR(IF($F56+$G56=O$10,N56,(IF($F56=O$10,N56,(IF($F56>O$10," ",IF(O$10<$G56+$F56,SLN($E56,$H56,$G56)," "))))))," ") | P56: =IF($F56+$G56=P$10,($E56-$H56)/$G56/2,(IF($F56=P$10,($E56-$H56)/$G56/2,0))) -> 0 | Q56: =IFERROR(IF($F56+$G56=Q$10,P56,(IF($F56=Q$10,P56,(IF($F56>Q$10," ",IF(Q$10<$G56+$F56,SLN($E56,$H56,$G56)," "))))))," ") | R56: =IF($F56+$G56=R$10,($E56-$H56)/$G56/2,(IF($F56=R$10,($E56-$H56)/$G56/2,0))) -> 0 | S56: =IFERROR(IF($F56+$G56=S$10,R56,(IF($F56=S$10,R56,(IF($F56>S$10," ",IF(S$10<$G56+$F56,SLN($E56,$H56,$G56)," "))))))," ") | T56: =IF($F56+$G56=T$10,($E56-$H56)/$G56/2,(IF($F56=T$10,($E56-$H56)/$G56/2,0))) -> 0 | U56: =IFERROR(IF($F56+$G56=U$10,T56,(IF($F56=U$10,T56,(IF($F56>U$10," ",IF(U$10<$G56+$F56,SLN($E56,$H56,$G56)," "))))))," ") | V56: =IF($F56+$G56=V$10,($E56-$H56)/$G56/2,(IF($F56=V$10,($E56-$H56)/$G56/2,0))) -> 0 | W56: =IFERROR(IF($F56+$G56=W$10,V56,(IF($F56=W$10,V56,(IF($F56>W$10," ",IF(W$10<$G56+$F56,SLN($E56,$H56,$G56)," "))))))," ") | X56: =IF($F56+$G56=X$10,($E56-$H56)/$G56/2,(IF($F56=X$10,($E56-$H56)/$G56/2,0))) -> 0 | Y56: =IFERROR(IF($F56+$G56=Y$10,X56,(IF($F56=Y$10,X56,(IF($F56>Y$10," ",IF(Y$10<$G56+$F56,SLN($E56,$H56,$G56)," "))))))," ") | Z56: =IF($F56+$G56=Z$10,($E56-$H56)/$G56/2,(IF($F56=Z$10,($E56-$H56)/$G56/2,0))) -> 0 | AA56: =IFERROR(IF($F56+$G56=AA$10,Z56,(IF($F56=AA$10,Z56,(IF($F56>AA$10," ",IF(AA$10<$G56+$F56,SLN($E56,$H56,$G56)," "))))))," ") | AB56: =IF($F56+$G56=AB$10,($E56-$H56)/$G56/2,(IF($F56=AB$10,($E56-$H56)/$G56/2,0))) -> 0 | AC56: =IFERROR(IF($F56+$G56=AC$10,AB56,(IF($F56=AC$10,AB56,(IF($F56>AC$10," ",IF(AC$10<$G56+$F56,SLN($E56,$H56,$G56)," "))))))," ") | AD56: =IF($F56+$G56=AD$10,($E56-$H56)/$G56/2,(IF($F56=AD$10,($E56-$H56)/$G56/2,0))) -> 0 | AE56: =IFERROR(IF($F56+$G56=AE$10,AD56,(IF($F56=AE$10,AD56,(IF($F56>AE$10," ",IF(AE$10<$G56+$F56,SLN($E56,$H56,$G56)," "))))))," ") | AF56: =IF($F56+$G56=AF$10,($E56-$H56)/$G56/2,(IF($F56=AF$10,($E56-$H56)/$G56/2,0))) -> 0 | AG56: =IFERROR(IF($F56+$G56=AG$10,AF56,(IF($F56=AG$10,AF56,(IF($F56>AG$10," ",IF(AG$10<$G56+$F56,SLN($E56,$H56,$G56)," "))))))," ") | AH56: =IF($F56+$G56=AH$10,($E56-$H56)/$G56/2,(IF($F56=AH$10,($E56-$H56)/$G56/2,0))) -> 0 | AI56: =IFERROR(IF($F56+$G56=AI$10,AH56,(IF($F56=AI$10,AH56,(IF($F56>AI$10," ",IF(AI$10<$G56+$F56,SLN($E56,$H56,$G56)," "))))))," ") | AJ56: =IF($F56+$G56=AJ$10,($E56-$H56)/$G56/2,(IF($F56=AJ$10,($E56-$H56)/$G56/2,0))) -> 0 | AK56: =IFERROR(IF($F56+$G56=AK$10,AJ56,(IF($F56=AK$10,AJ56,(IF($F56>AK$10," ",IF(AK$10<$G56+$F56,SLN($E56,$H56,$G56)," "))))))," ") | AL56: =IF($F56+$G56=AL$10,($E56-$H56)/$G56/2,(IF($F56=AL$10,($E56-$H56)/$G56/2,0))) -> 0 | AM56: =IFERROR(IF($F56+$G56=AM$10,AL56,(IF($F56=AM$10,AL56,(IF($F56>AM$10," ",IF(AM$10<$G56+$F56,SLN($E56,$H56,$G56)," "))))))," ") | AN56: =IF($F56+$G56=AN$10,($E56-$H56)/$G56/2,(IF($F56=AN$10,($E56-$H56)/$G56/2,0))) -> 0 | AO56: =IFERROR(IF($F56+$G56=AO$10,AN56,(IF($F56=AO$10,AN56,(IF($F56>AO$10," ",IF(AO$10<$G56+$F56,SLN($E56,$H56,$G56)," "))))))," ") | AP56: =IF($F56+$G56=AP$10,($E56-$H56)/$G56/2,(IF($F56=AP$10,($E56-$H56)/$G56/2,0))) -> 0 | AQ56: =IFERROR(IF($F56+$G56=AQ$10,AP56,(IF($F56=AQ$10,AP56,(IF($F56>AQ$10," ",IF(AQ$10<$G56+$F56,SLN($E56,$H56,$G56)," "))))))," ") | AR56: =IF($F56+$G56=AR$10,($E56-$H56)/$G56/2,(IF($F56=AR$10,($E56-$H56)/$G56/2,0))) -> 0 | AS56: =IFERROR(IF($F56+$G56=AS$10,AR56,(IF($F56=AS$10,AR56,(IF($F56>AS$10," ",IF(AS$10<$G56+$F56,SLN($E56,$H56,$G56)," "))))))," ") | AT56: =IF($F56+$G56=AT$10,($E56-$H56)/$G56/2,(IF($F56=AT$10,($E56-$H56)/$G56/2,0))) -> 0 | AU56: =IFERROR(IF($F56+$G56=AU$10,AT56,(IF($F56=AU$10,AT56,(IF($F56>AU$10," ",IF(AU$10<$G56+$F56,SLN($E56,$H56,$G56)," "))))))," ") | AV56: =IF($F56+$G56=AV$10,($E56-$H56)/$G56/2,(IF($F56=AV$10,($E56-$H56)/$G56/2,0))) -> 0 | AW56: =IFERROR(IF($F56+$G56=AW$10,AV56,(IF($F56=AW$10,AV56,(IF($F56>AW$10," ",IF(AW$10<$G56+$F56,SLN($E56,$H56,$G56)," "))))))," ")
I57: =IFERROR(IF(F57<$K$10,(($K$10-F57-1)*((E57-H57)/G57)+(((E57-H57)/G57)/2)),0),0) -> 0 | J57: =IF($F57+$G57=J$10,($E57-$H57)/$G57/2,(IF($F57=J$10,($E57-$H57)/$G57/2,0))) -> 0 | K57: =IFERROR(IF($F57+$G57=K$10,J57,(IF($F57=K$10,J57,(IF($F57>K$10," ",IF(K$10<$G57+$F57,SLN($E57,$H57,$G57)," "))))))," ") | L57: =IF($F57+$G57=L$10,($E57-$H57)/$G57/2,(IF($F57=L$10,($E57-$H57)/$G57/2,0))) -> 0 | M57: =IFERROR(IF($F57+$G57=M$10,L57,(IF($F57=M$10,L57,(IF($F57>M$10," ",IF(M$10<$G57+$F57,SLN($E57,$H57,$G57)," "))))))," ") | N57: =IF($F57+$G57=N$10,($E57-$H57)/$G57/2,(IF($F57=N$10,($E57-$H57)/$G57/2,0))) -> 0 | O57: =IFERROR(IF($F57+$G57=O$10,N57,(IF($F57=O$10,N57,(IF($F57>O$10," ",IF(O$10<$G57+$F57,SLN($E57,$H57,$G57)," "))))))," ") | P57: =IF($F57+$G57=P$10,($E57-$H57)/$G57/2,(IF($F57=P$10,($E57-$H57)/$G57/2,0))) -> 0 | Q57: =IFERROR(IF($F57+$G57=Q$10,P57,(IF($F57=Q$10,P57,(IF($F57>Q$10," ",IF(Q$10<$G57+$F57,SLN($E57,$H57,$G57)," "))))))," ") | R57: =IF($F57+$G57=R$10,($E57-$H57)/$G57/2,(IF($F57=R$10,($E57-$H57)/$G57/2,0))) -> 0 | S57: =IFERROR(IF($F57+$G57=S$10,R57,(IF($F57=S$10,R57,(IF($F57>S$10," ",IF(S$10<$G57+$F57,SLN($E57,$H57,$G57)," "))))))," ") | T57: =IF($F57+$G57=T$10,($E57-$H57)/$G57/2,(IF($F57=T$10,($E57-$H57)/$G57/2,0))) -> 0 | U57: =IFERROR(IF($F57+$G57=U$10,T57,(IF($F57=U$10,T57,(IF($F57>U$10," ",IF(U$10<$G57+$F57,SLN($E57,$H57,$G57)," "))))))," ") | V57: =IF($F57+$G57=V$10,($E57-$H57)/$G57/2,(IF($F57=V$10,($E57-$H57)/$G57/2,0))) -> 0 | W57: =IFERROR(IF($F57+$G57=W$10,V57,(IF($F57=W$10,V57,(IF($F57>W$10," ",IF(W$10<$G57+$F57,SLN($E57,$H57,$G57)," "))))))," ") | X57: =IF($F57+$G57=X$10,($E57-$H57)/$G57/2,(IF($F57=X$10,($E57-$H57)/$G57/2,0))) -> 0 | Y57: =IFERROR(IF($F57+$G57=Y$10,X57,(IF($F57=Y$10,X57,(IF($F57>Y$10," ",IF(Y$10<$G57+$F57,SLN($E57,$H57,$G57)," "))))))," ") | Z57: =IF($F57+$G57=Z$10,($E57-$H57)/$G57/2,(IF($F57=Z$10,($E57-$H57)/$G57/2,0))) -> 0 | AA57: =IFERROR(IF($F57+$G57=AA$10,Z57,(IF($F57=AA$10,Z57,(IF($F57>AA$10," ",IF(AA$10<$G57+$F57,SLN($E57,$H57,$G57)," "))))))," ") | AB57: =IF($F57+$G57=AB$10,($E57-$H57)/$G57/2,(IF($F57=AB$10,($E57-$H57)/$G57/2,0))) -> 0 | AC57: =IFERROR(IF($F57+$G57=AC$10,AB57,(IF($F57=AC$10,AB57,(IF($F57>AC$10," ",IF(AC$10<$G57+$F57,SLN($E57,$H57,$G57)," "))))))," ") | AD57: =IF($F57+$G57=AD$10,($E57-$H57)/$G57/2,(IF($F57=AD$10,($E57-$H57)/$G57/2,0))) -> 0 | AE57: =IFERROR(IF($F57+$G57=AE$10,AD57,(IF($F57=AE$10,AD57,(IF($F57>AE$10," ",IF(AE$10<$G57+$F57,SLN($E57,$H57,$G57)," "))))))," ") | AF57: =IF($F57+$G57=AF$10,($E57-$H57)/$G57/2,(IF($F57=AF$10,($E57-$H57)/$G57/2,0))) -> 0 | AG57: =IFERROR(IF($F57+$G57=AG$10,AF57,(IF($F57=AG$10,AF57,(IF($F57>AG$10," ",IF(AG$10<$G57+$F57,SLN($E57,$H57,$G57)," "))))))," ") | AH57: =IF($F57+$G57=AH$10,($E57-$H57)/$G57/2,(IF($F57=AH$10,($E57-$H57)/$G57/2,0))) -> 0 | AI57: =IFERROR(IF($F57+$G57=AI$10,AH57,(IF($F57=AI$10,AH57,(IF($F57>AI$10," ",IF(AI$10<$G57+$F57,SLN($E57,$H57,$G57)," "))))))," ") | AJ57: =IF($F57+$G57=AJ$10,($E57-$H57)/$G57/2,(IF($F57=AJ$10,($E57-$H57)/$G57/2,0))) -> 0 | AK57: =IFERROR(IF($F57+$G57=AK$10,AJ57,(IF($F57=AK$10,AJ57,(IF($F57>AK$10," ",IF(AK$10<$G57+$F57,SLN($E57,$H57,$G57)," "))))))," ") | AL57: =IF($F57+$G57=AL$10,($E57-$H57)/$G57/2,(IF($F57=AL$10,($E57-$H57)/$G57/2,0))) -> 0 | AM57: =IFERROR(IF($F57+$G57=AM$10,AL57,(IF($F57=AM$10,AL57,(IF($F57>AM$10," ",IF(AM$10<$G57+$F57,SLN($E57,$H57,$G57)," "))))))," ") | AN57: =IF($F57+$G57=AN$10,($E57-$H57)/$G57/2,(IF($F57=AN$10,($E57-$H57)/$G57/2,0))) -> 0 | AO57: =IFERROR(IF($F57+$G57=AO$10,AN57,(IF($F57=AO$10,AN57,(IF($F57>AO$10," ",IF(AO$10<$G57+$F57,SLN($E57,$H57,$G57)," "))))))," ") | AP57: =IF($F57+$G57=AP$10,($E57-$H57)/$G57/2,(IF($F57=AP$10,($E57-$H57)/$G57/2,0))) -> 0 | AQ57: =IFERROR(IF($F57+$G57=AQ$10,AP57,(IF($F57=AQ$10,AP57,(IF($F57>AQ$10," ",IF(AQ$10<$G57+$F57,SLN($E57,$H57,$G57)," "))))))," ") | AR57: =IF($F57+$G57=AR$10,($E57-$H57)/$G57/2,(IF($F57=AR$10,($E57-$H57)/$G57/2,0))) -> 0 | AS57: =IFERROR(IF($F57+$G57=AS$10,AR57,(IF($F57=AS$10,AR57,(IF($F57>AS$10," ",IF(AS$10<$G57+$F57,SLN($E57,$H57,$G57)," "))))))," ") | AT57: =IF($F57+$G57=AT$10,($E57-$H57)/$G57/2,(IF($F57=AT$10,($E57-$H57)/$G57/2,0))) -> 0 | AU57: =IFERROR(IF($F57+$G57=AU$10,AT57,(IF($F57=AU$10,AT57,(IF($F57>AU$10," ",IF(AU$10<$G57+$F57,SLN($E57,$H57,$G57)," "))))))," ") | AV57: =IF($F57+$G57=AV$10,($E57-$H57)/$G57/2,(IF($F57=AV$10,($E57-$H57)/$G57/2,0))) -> 0 | AW57: =IFERROR(IF($F57+$G57=AW$10,AV57,(IF($F57=AW$10,AV57,(IF($F57>AW$10," ",IF(AW$10<$G57+$F57,SLN($E57,$H57,$G57)," "))))))," ")
I58: =IFERROR(IF(F58<$K$10,(($K$10-F58-1)*((E58-H58)/G58)+(((E58-H58)/G58)/2)),0),0) -> 0 | J58: =IF($F58+$G58=J$10,($E58-$H58)/$G58/2,(IF($F58=J$10,($E58-$H58)/$G58/2,0))) -> 0 | K58: =IFERROR(IF($F58+$G58=K$10,J58,(IF($F58=K$10,J58,(IF($F58>K$10," ",IF(K$10<$G58+$F58,SLN($E58,$H58,$G58)," "))))))," ") | L58: =IF($F58+$G58=L$10,($E58-$H58)/$G58/2,(IF($F58=L$10,($E58-$H58)/$G58/2,0))) -> 0 | M58: =IFERROR(IF($F58+$G58=M$10,L58,(IF($F58=M$10,L58,(IF($F58>M$10," ",IF(M$10<$G58+$F58,SLN($E58,$H58,$G58)," "))))))," ") | N58: =IF($F58+$G58=N$10,($E58-$H58)/$G58/2,(IF($F58=N$10,($E58-$H58)/$G58/2,0))) -> 0 | O58: =IFERROR(IF($F58+$G58=O$10,N58,(IF($F58=O$10,N58,(IF($F58>O$10," ",IF(O$10<$G58+$F58,SLN($E58,$H58,$G58)," "))))))," ") | P58: =IF($F58+$G58=P$10,($E58-$H58)/$G58/2,(IF($F58=P$10,($E58-$H58)/$G58/2,0))) -> 0 | Q58: =IFERROR(IF($F58+$G58=Q$10,P58,(IF($F58=Q$10,P58,(IF($F58>Q$10," ",IF(Q$10<$G58+$F58,SLN($E58,$H58,$G58)," "))))))," ") | R58: =IF($F58+$G58=R$10,($E58-$H58)/$G58/2,(IF($F58=R$10,($E58-$H58)/$G58/2,0))) -> 0 | S58: =IFERROR(IF($F58+$G58=S$10,R58,(IF($F58=S$10,R58,(IF($F58>S$10," ",IF(S$10<$G58+$F58,SLN($E58,$H58,$G58)," "))))))," ") | T58: =IF($F58+$G58=T$10,($E58-$H58)/$G58/2,(IF($F58=T$10,($E58-$H58)/$G58/2,0))) -> 0 | U58: =IFERROR(IF($F58+$G58=U$10,T58,(IF($F58=U$10,T58,(IF($F58>U$10," ",IF(U$10<$G58+$F58,SLN($E58,$H58,$G58)," "))))))," ") | V58: =IF($F58+$G58=V$10,($E58-$H58)/$G58/2,(IF($F58=V$10,($E58-$H58)/$G58/2,0))) -> 0 | W58: =IFERROR(IF($F58+$G58=W$10,V58,(IF($F58=W$10,V58,(IF($F58>W$10," ",IF(W$10<$G58+$F58,SLN($E58,$H58,$G58)," "))))))," ") | X58: =IF($F58+$G58=X$10,($E58-$H58)/$G58/2,(IF($F58=X$10,($E58-$H58)/$G58/2,0))) -> 0 | Y58: =IFERROR(IF($F58+$G58=Y$10,X58,(IF($F58=Y$10,X58,(IF($F58>Y$10," ",IF(Y$10<$G58+$F58,SLN($E58,$H58,$G58)," "))))))," ") | Z58: =IF($F58+$G58=Z$10,($E58-$H58)/$G58/2,(IF($F58=Z$10,($E58-$H58)/$G58/2,0))) -> 0 | AA58: =IFERROR(IF($F58+$G58=AA$10,Z58,(IF($F58=AA$10,Z58,(IF($F58>AA$10," ",IF(AA$10<$G58+$F58,SLN($E58,$H58,$G58)," "))))))," ") | AB58: =IF($F58+$G58=AB$10,($E58-$H58)/$G58/2,(IF($F58=AB$10,($E58-$H58)/$G58/2,0))) -> 0 | AC58: =IFERROR(IF($F58+$G58=AC$10,AB58,(IF($F58=AC$10,AB58,(IF($F58>AC$10," ",IF(AC$10<$G58+$F58,SLN($E58,$H58,$G58)," "))))))," ") | AD58: =IF($F58+$G58=AD$10,($E58-$H58)/$G58/2,(IF($F58=AD$10,($E58-$H58)/$G58/2,0))) -> 0 | AE58: =IFERROR(IF($F58+$G58=AE$10,AD58,(IF($F58=AE$10,AD58,(IF($F58>AE$10," ",IF(AE$10<$G58+$F58,SLN($E58,$H58,$G58)," "))))))," ") | AF58: =IF($F58+$G58=AF$10,($E58-$H58)/$G58/2,(IF($F58=AF$10,($E58-$H58)/$G58/2,0))) -> 0 | AG58: =IFERROR(IF($F58+$G58=AG$10,AF58,(IF($F58=AG$10,AF58,(IF($F58>AG$10," ",IF(AG$10<$G58+$F58,SLN($E58,$H58,$G58)," "))))))," ") | AH58: =IF($F58+$G58=AH$10,($E58-$H58)/$G58/2,(IF($F58=AH$10,($E58-$H58)/$G58/2,0))) -> 0 | AI58: =IFERROR(IF($F58+$G58=AI$10,AH58,(IF($F58=AI$10,AH58,(IF($F58>AI$10," ",IF(AI$10<$G58+$F58,SLN($E58,$H58,$G58)," "))))))," ") | AJ58: =IF($F58+$G58=AJ$10,($E58-$H58)/$G58/2,(IF($F58=AJ$10,($E58-$H58)/$G58/2,0))) -> 0 | AK58: =IFERROR(IF($F58+$G58=AK$10,AJ58,(IF($F58=AK$10,AJ58,(IF($F58>AK$10," ",IF(AK$10<$G58+$F58,SLN($E58,$H58,$G58)," "))))))," ") | AL58: =IF($F58+$G58=AL$10,($E58-$H58)/$G58/2,(IF($F58=AL$10,($E58-$H58)/$G58/2,0))) -> 0 | AM58: =IFERROR(IF($F58+$G58=AM$10,AL58,(IF($F58=AM$10,AL58,(IF($F58>AM$10," ",IF(AM$10<$G58+$F58,SLN($E58,$H58,$G58)," "))))))," ") | AN58: =IF($F58+$G58=AN$10,($E58-$H58)/$G58/2,(IF($F58=AN$10,($E58-$H58)/$G58/2,0))) -> 0 | AO58: =IFERROR(IF($F58+$G58=AO$10,AN58,(IF($F58=AO$10,AN58,(IF($F58>AO$10," ",IF(AO$10<$G58+$F58,SLN($E58,$H58,$G58)," "))))))," ") | AP58: =IF($F58+$G58=AP$10,($E58-$H58)/$G58/2,(IF($F58=AP$10,($E58-$H58)/$G58/2,0))) -> 0 | AQ58: =IFERROR(IF($F58+$G58=AQ$10,AP58,(IF($F58=AQ$10,AP58,(IF($F58>AQ$10," ",IF(AQ$10<$G58+$F58,SLN($E58,$H58,$G58)," "))))))," ") | AR58: =IF($F58+$G58=AR$10,($E58-$H58)/$G58/2,(IF($F58=AR$10,($E58-$H58)/$G58/2,0))) -> 0 | AS58: =IFERROR(IF($F58+$G58=AS$10,AR58,(IF($F58=AS$10,AR58,(IF($F58>AS$10," ",IF(AS$10<$G58+$F58,SLN($E58,$H58,$G58)," "))))))," ") | AT58: =IF($F58+$G58=AT$10,($E58-$H58)/$G58/2,(IF($F58=AT$10,($E58-$H58)/$G58/2,0))) -> 0 | AU58: =IFERROR(IF($F58+$G58=AU$10,AT58,(IF($F58=AU$10,AT58,(IF($F58>AU$10," ",IF(AU$10<$G58+$F58,SLN($E58,$H58,$G58)," "))))))," ") | AV58: =IF($F58+$G58=AV$10,($E58-$H58)/$G58/2,(IF($F58=AV$10,($E58-$H58)/$G58/2,0))) -> 0 | AW58: =IFERROR(IF($F58+$G58=AW$10,AV58,(IF($F58=AW$10,AV58,(IF($F58>AW$10," ",IF(AW$10<$G58+$F58,SLN($E58,$H58,$G58)," "))))))," ")
I59: =IFERROR(IF(F59<$K$10,(($K$10-F59-1)*((E59-H59)/G59)+(((E59-H59)/G59)/2)),0),0) -> 0 | J59: =IF($F59+$G59=J$10,($E59-$H59)/$G59/2,(IF($F59=J$10,($E59-$H59)/$G59/2,0))) -> 0 | K59: =IFERROR(IF($F59+$G59=K$10,J59,(IF($F59=K$10,J59,(IF($F59>K$10," ",IF(K$10<$G59+$F59,SLN($E59,$H59,$G59)," "))))))," ") | L59: =IF($F59+$G59=L$10,($E59-$H59)/$G59/2,(IF($F59=L$10,($E59-$H59)/$G59/2,0))) -> 0 | M59: =IFERROR(IF($F59+$G59=M$10,L59,(IF($F59=M$10,L59,(IF($F59>M$10," ",IF(M$10<$G59+$F59,SLN($E59,$H59,$G59)," "))))))," ") | N59: =IF($F59+$G59=N$10,($E59-$H59)/$G59/2,(IF($F59=N$10,($E59-$H59)/$G59/2,0))) -> 0 | O59: =IFERROR(IF($F59+$G59=O$10,N59,(IF($F59=O$10,N59,(IF($F59>O$10," ",IF(O$10<$G59+$F59,SLN($E59,$H59,$G59)," "))))))," ") | P59: =IF($F59+$G59=P$10,($E59-$H59)/$G59/2,(IF($F59=P$10,($E59-$H59)/$G59/2,0))) -> 0 | Q59: =IFERROR(IF($F59+$G59=Q$10,P59,(IF($F59=Q$10,P59,(IF($F59>Q$10," ",IF(Q$10<$G59+$F59,SLN($E59,$H59,$G59)," "))))))," ") | R59: =IF($F59+$G59=R$10,($E59-$H59)/$G59/2,(IF($F59=R$10,($E59-$H59)/$G59/2,0))) -> 0 | S59: =IFERROR(IF($F59+$G59=S$10,R59,(IF($F59=S$10,R59,(IF($F59>S$10," ",IF(S$10<$G59+$F59,SLN($E59,$H59,$G59)," "))))))," ") | T59: =IF($F59+$G59=T$10,($E59-$H59)/$G59/2,(IF($F59=T$10,($E59-$H59)/$G59/2,0))) -> 0 | U59: =IFERROR(IF($F59+$G59=U$10,T59,(IF($F59=U$10,T59,(IF($F59>U$10," ",IF(U$10<$G59+$F59,SLN($E59,$H59,$G59)," "))))))," ") | V59: =IF($F59+$G59=V$10,($E59-$H59)/$G59/2,(IF($F59=V$10,($E59-$H59)/$G59/2,0))) -> 0 | W59: =IFERROR(IF($F59+$G59=W$10,V59,(IF($F59=W$10,V59,(IF($F59>W$10," ",IF(W$10<$G59+$F59,SLN($E59,$H59,$G59)," "))))))," ") | X59: =IF($F59+$G59=X$10,($E59-$H59)/$G59/2,(IF($F59=X$10,($E59-$H59)/$G59/2,0))) -> 0 | Y59: =IFERROR(IF($F59+$G59=Y$10,X59,(IF($F59=Y$10,X59,(IF($F59>Y$10," ",IF(Y$10<$G59+$F59,SLN($E59,$H59,$G59)," "))))))," ") | Z59: =IF($F59+$G59=Z$10,($E59-$H59)/$G59/2,(IF($F59=Z$10,($E59-$H59)/$G59/2,0))) -> 0 | AA59: =IFERROR(IF($F59+$G59=AA$10,Z59,(IF($F59=AA$10,Z59,(IF($F59>AA$10," ",IF(AA$10<$G59+$F59,SLN($E59,$H59,$G59)," "))))))," ") | AB59: =IF($F59+$G59=AB$10,($E59-$H59)/$G59/2,(IF($F59=AB$10,($E59-$H59)/$G59/2,0))) -> 0 | AC59: =IFERROR(IF($F59+$G59=AC$10,AB59,(IF($F59=AC$10,AB59,(IF($F59>AC$10," ",IF(AC$10<$G59+$F59,SLN($E59,$H59,$G59)," "))))))," ") | AD59: =IF($F59+$G59=AD$10,($E59-$H59)/$G59/2,(IF($F59=AD$10,($E59-$H59)/$G59/2,0))) -> 0 | AE59: =IFERROR(IF($F59+$G59=AE$10,AD59,(IF($F59=AE$10,AD59,(IF($F59>AE$10," ",IF(AE$10<$G59+$F59,SLN($E59,$H59,$G59)," "))))))," ") | AF59: =IF($F59+$G59=AF$10,($E59-$H59)/$G59/2,(IF($F59=AF$10,($E59-$H59)/$G59/2,0))) -> 0 | AG59: =IFERROR(IF($F59+$G59=AG$10,AF59,(IF($F59=AG$10,AF59,(IF($F59>AG$10," ",IF(AG$10<$G59+$F59,SLN($E59,$H59,$G59)," "))))))," ") | AH59: =IF($F59+$G59=AH$10,($E59-$H59)/$G59/2,(IF($F59=AH$10,($E59-$H59)/$G59/2,0))) -> 0 | AI59: =IFERROR(IF($F59+$G59=AI$10,AH59,(IF($F59=AI$10,AH59,(IF($F59>AI$10," ",IF(AI$10<$G59+$F59,SLN($E59,$H59,$G59)," "))))))," ") | AJ59: =IF($F59+$G59=AJ$10,($E59-$H59)/$G59/2,(IF($F59=AJ$10,($E59-$H59)/$G59/2,0))) -> 0 | AK59: =IFERROR(IF($F59+$G59=AK$10,AJ59,(IF($F59=AK$10,AJ59,(IF($F59>AK$10," ",IF(AK$10<$G59+$F59,SLN($E59,$H59,$G59)," "))))))," ") | AL59: =IF($F59+$G59=AL$10,($E59-$H59)/$G59/2,(IF($F59=AL$10,($E59-$H59)/$G59/2,0))) -> 0 | AM59: =IFERROR(IF($F59+$G59=AM$10,AL59,(IF($F59=AM$10,AL59,(IF($F59>AM$10," ",IF(AM$10<$G59+$F59,SLN($E59,$H59,$G59)," "))))))," ") | AN59: =IF($F59+$G59=AN$10,($E59-$H59)/$G59/2,(IF($F59=AN$10,($E59-$H59)/$G59/2,0))) -> 0 | AO59: =IFERROR(IF($F59+$G59=AO$10,AN59,(IF($F59=AO$10,AN59,(IF($F59>AO$10," ",IF(AO$10<$G59+$F59,SLN($E59,$H59,$G59)," "))))))," ") | AP59: =IF($F59+$G59=AP$10,($E59-$H59)/$G59/2,(IF($F59=AP$10,($E59-$H59)/$G59/2,0))) -> 0 | AQ59: =IFERROR(IF($F59+$G59=AQ$10,AP59,(IF($F59=AQ$10,AP59,(IF($F59>AQ$10," ",IF(AQ$10<$G59+$F59,SLN($E59,$H59,$G59)," "))))))," ") | AR59: =IF($F59+$G59=AR$10,($E59-$H59)/$G59/2,(IF($F59=AR$10,($E59-$H59)/$G59/2,0))) -> 0 | AS59: =IFERROR(IF($F59+$G59=AS$10,AR59,(IF($F59=AS$10,AR59,(IF($F59>AS$10," ",IF(AS$10<$G59+$F59,SLN($E59,$H59,$G59)," "))))))," ") | AT59: =IF($F59+$G59=AT$10,($E59-$H59)/$G59/2,(IF($F59=AT$10,($E59-$H59)/$G59/2,0))) -> 0 | AU59: =IFERROR(IF($F59+$G59=AU$10,AT59,(IF($F59=AU$10,AT59,(IF($F59>AU$10," ",IF(AU$10<$G59+$F59,SLN($E59,$H59,$G59)," "))))))," ") | AV59: =IF($F59+$G59=AV$10,($E59-$H59)/$G59/2,(IF($F59=AV$10,($E59-$H59)/$G59/2,0))) -> 0 | AW59: =IFERROR(IF($F59+$G59=AW$10,AV59,(IF($F59=AW$10,AV59,(IF($F59>AW$10," ",IF(AW$10<$G59+$F59,SLN($E59,$H59,$G59)," "))))))," ")
I60: =IFERROR(IF(F60<$K$10,(($K$10-F60-1)*((E60-H60)/G60)+(((E60-H60)/G60)/2)),0),0) -> 0 | J60: =IF($F60+$G60=J$10,($E60-$H60)/$G60/2,(IF($F60=J$10,($E60-$H60)/$G60/2,0))) -> 0 | K60: =IFERROR(IF($F60+$G60=K$10,J60,(IF($F60=K$10,J60,(IF($F60>K$10," ",IF(K$10<$G60+$F60,SLN($E60,$H60,$G60)," "))))))," ") | L60: =IF($F60+$G60=L$10,($E60-$H60)/$G60/2,(IF($F60=L$10,($E60-$H60)/$G60/2,0))) -> 0 | M60: =IFERROR(IF($F60+$G60=M$10,L60,(IF($F60=M$10,L60,(IF($F60>M$10," ",IF(M$10<$G60+$F60,SLN($E60,$H60,$G60)," "))))))," ") | N60: =IF($F60+$G60=N$10,($E60-$H60)/$G60/2,(IF($F60=N$10,($E60-$H60)/$G60/2,0))) -> 0 | O60: =IFERROR(IF($F60+$G60=O$10,N60,(IF($F60=O$10,N60,(IF($F60>O$10," ",IF(O$10<$G60+$F60,SLN($E60,$H60,$G60)," "))))))," ") | P60: =IF($F60+$G60=P$10,($E60-$H60)/$G60/2,(IF($F60=P$10,($E60-$H60)/$G60/2,0))) -> 0 | Q60: =IFERROR(IF($F60+$G60=Q$10,P60,(IF($F60=Q$10,P60,(IF($F60>Q$10," ",IF(Q$10<$G60+$F60,SLN($E60,$H60,$G60)," "))))))," ") | R60: =IF($F60+$G60=R$10,($E60-$H60)/$G60/2,(IF($F60=R$10,($E60-$H60)/$G60/2,0))) -> 0 | S60: =IFERROR(IF($F60+$G60=S$10,R60,(IF($F60=S$10,R60,(IF($F60>S$10," ",IF(S$10<$G60+$F60,SLN($E60,$H60,$G60)," "))))))," ") | T60: =IF($F60+$G60=T$10,($E60-$H60)/$G60/2,(IF($F60=T$10,($E60-$H60)/$G60/2,0))) -> 0 | U60: =IFERROR(IF($F60+$G60=U$10,T60,(IF($F60=U$10,T60,(IF($F60>U$10," ",IF(U$10<$G60+$F60,SLN($E60,$H60,$G60)," "))))))," ") | V60: =IF($F60+$G60=V$10,($E60-$H60)/$G60/2,(IF($F60=V$10,($E60-$H60)/$G60/2,0))) -> 0 | W60: =IFERROR(IF($F60+$G60=W$10,V60,(IF($F60=W$10,V60,(IF($F60>W$10," ",IF(W$10<$G60+$F60,SLN($E60,$H60,$G60)," "))))))," ") | X60: =IF($F60+$G60=X$10,($E60-$H60)/$G60/2,(IF($F60=X$10,($E60-$H60)/$G60/2,0))) -> 0 | Y60: =IFERROR(IF($F60+$G60=Y$10,X60,(IF($F60=Y$10,X60,(IF($F60>Y$10," ",IF(Y$10<$G60+$F60,SLN($E60,$H60,$G60)," "))))))," ") | Z60: =IF($F60+$G60=Z$10,($E60-$H60)/$G60/2,(IF($F60=Z$10,($E60-$H60)/$G60/2,0))) -> 0 | AA60: =IFERROR(IF($F60+$G60=AA$10,Z60,(IF($F60=AA$10,Z60,(IF($F60>AA$10," ",IF(AA$10<$G60+$F60,SLN($E60,$H60,$G60)," "))))))," ") | AB60: =IF($F60+$G60=AB$10,($E60-$H60)/$G60/2,(IF($F60=AB$10,($E60-$H60)/$G60/2,0))) -> 0 | AC60: =IFERROR(IF($F60+$G60=AC$10,AB60,(IF($F60=AC$10,AB60,(IF($F60>AC$10," ",IF(AC$10<$G60+$F60,SLN($E60,$H60,$G60)," "))))))," ") | AD60: =IF($F60+$G60=AD$10,($E60-$H60)/$G60/2,(IF($F60=AD$10,($E60-$H60)/$G60/2,0))) -> 0 | AE60: =IFERROR(IF($F60+$G60=AE$10,AD60,(IF($F60=AE$10,AD60,(IF($F60>AE$10," ",IF(AE$10<$G60+$F60,SLN($E60,$H60,$G60)," "))))))," ") | AF60: =IF($F60+$G60=AF$10,($E60-$H60)/$G60/2,(IF($F60=AF$10,($E60-$H60)/$G60/2,0))) -> 0 | AG60: =IFERROR(IF($F60+$G60=AG$10,AF60,(IF($F60=AG$10,AF60,(IF($F60>AG$10," ",IF(AG$10<$G60+$F60,SLN($E60,$H60,$G60)," "))))))," ") | AH60: =IF($F60+$G60=AH$10,($E60-$H60)/$G60/2,(IF($F60=AH$10,($E60-$H60)/$G60/2,0))) -> 0 | AI60: =IFERROR(IF($F60+$G60=AI$10,AH60,(IF($F60=AI$10,AH60,(IF($F60>AI$10," ",IF(AI$10<$G60+$F60,SLN($E60,$H60,$G60)," "))))))," ") | AJ60: =IF($F60+$G60=AJ$10,($E60-$H60)/$G60/2,(IF($F60=AJ$10,($E60-$H60)/$G60/2,0))) -> 0 | AK60: =IFERROR(IF($F60+$G60=AK$10,AJ60,(IF($F60=AK$10,AJ60,(IF($F60>AK$10," ",IF(AK$10<$G60+$F60,SLN($E60,$H60,$G60)," "))))))," ") | AL60: =IF($F60+$G60=AL$10,($E60-$H60)/$G60/2,(IF($F60=AL$10,($E60-$H60)/$G60/2,0))) -> 0 | AM60: =IFERROR(IF($F60+$G60=AM$10,AL60,(IF($F60=AM$10,AL60,(IF($F60>AM$10," ",IF(AM$10<$G60+$F60,SLN($E60,$H60,$G60)," "))))))," ") | AN60: =IF($F60+$G60=AN$10,($E60-$H60)/$G60/2,(IF($F60=AN$10,($E60-$H60)/$G60/2,0))) -> 0 | AO60: =IFERROR(IF($F60+$G60=AO$10,AN60,(IF($F60=AO$10,AN60,(IF($F60>AO$10," ",IF(AO$10<$G60+$F60,SLN($E60,$H60,$G60)," "))))))," ") | AP60: =IF($F60+$G60=AP$10,($E60-$H60)/$G60/2,(IF($F60=AP$10,($E60-$H60)/$G60/2,0))) -> 0 | AQ60: =IFERROR(IF($F60+$G60=AQ$10,AP60,(IF($F60=AQ$10,AP60,(IF($F60>AQ$10," ",IF(AQ$10<$G60+$F60,SLN($E60,$H60,$G60)," "))))))," ") | AR60: =IF($F60+$G60=AR$10,($E60-$H60)/$G60/2,(IF($F60=AR$10,($E60-$H60)/$G60/2,0))) -> 0 | AS60: =IFERROR(IF($F60+$G60=AS$10,AR60,(IF($F60=AS$10,AR60,(IF($F60>AS$10," ",IF(AS$10<$G60+$F60,SLN($E60,$H60,$G60)," "))))))," ") | AT60: =IF($F60+$G60=AT$10,($E60-$H60)/$G60/2,(IF($F60=AT$10,($E60-$H60)/$G60/2,0))) -> 0 | AU60: =IFERROR(IF($F60+$G60=AU$10,AT60,(IF($F60=AU$10,AT60,(IF($F60>AU$10," ",IF(AU$10<$G60+$F60,SLN($E60,$H60,$G60)," "))))))," ") | AV60: =IF($F60+$G60=AV$10,($E60-$H60)/$G60/2,(IF($F60=AV$10,($E60-$H60)/$G60/2,0))) -> 0 | AW60: =IFERROR(IF($F60+$G60=AW$10,AV60,(IF($F60=AW$10,AV60,(IF($F60>AW$10," ",IF(AW$10<$G60+$F60,SLN($E60,$H60,$G60)," "))))))," ")
I61: =IFERROR(IF(F61<$K$10,(($K$10-F61-1)*((E61-H61)/G61)+(((E61-H61)/G61)/2)),0),0) -> 0 | J61: =IF($F61+$G61=J$10,($E61-$H61)/$G61/2,(IF($F61=J$10,($E61-$H61)/$G61/2,0))) -> 0 | K61: =IFERROR(IF($F61+$G61=K$10,J61,(IF($F61=K$10,J61,(IF($F61>K$10," ",IF(K$10<$G61+$F61,SLN($E61,$H61,$G61)," "))))))," ") | L61: =IF($F61+$G61=L$10,($E61-$H61)/$G61/2,(IF($F61=L$10,($E61-$H61)/$G61/2,0))) -> 0 | M61: =IFERROR(IF($F61+$G61=M$10,L61,(IF($F61=M$10,L61,(IF($F61>M$10," ",IF(M$10<$G61+$F61,SLN($E61,$H61,$G61)," "))))))," ") | N61: =IF($F61+$G61=N$10,($E61-$H61)/$G61/2,(IF($F61=N$10,($E61-$H61)/$G61/2,0))) -> 0 | O61: =IFERROR(IF($F61+$G61=O$10,N61,(IF($F61=O$10,N61,(IF($F61>O$10," ",IF(O$10<$G61+$F61,SLN($E61,$H61,$G61)," "))))))," ") | P61: =IF($F61+$G61=P$10,($E61-$H61)/$G61/2,(IF($F61=P$10,($E61-$H61)/$G61/2,0))) -> 0 | Q61: =IFERROR(IF($F61+$G61=Q$10,P61,(IF($F61=Q$10,P61,(IF($F61>Q$10," ",IF(Q$10<$G61+$F61,SLN($E61,$H61,$G61)," "))))))," ") | R61: =IF($F61+$G61=R$10,($E61-$H61)/$G61/2,(IF($F61=R$10,($E61-$H61)/$G61/2,0))) -> 0 | S61: =IFERROR(IF($F61+$G61=S$10,R61,(IF($F61=S$10,R61,(IF($F61>S$10," ",IF(S$10<$G61+$F61,SLN($E61,$H61,$G61)," "))))))," ") | T61: =IF($F61+$G61=T$10,($E61-$H61)/$G61/2,(IF($F61=T$10,($E61-$H61)/$G61/2,0))) -> 0 | U61: =IFERROR(IF($F61+$G61=U$10,T61,(IF($F61=U$10,T61,(IF($F61>U$10," ",IF(U$10<$G61+$F61,SLN($E61,$H61,$G61)," "))))))," ") | V61: =IF($F61+$G61=V$10,($E61-$H61)/$G61/2,(IF($F61=V$10,($E61-$H61)/$G61/2,0))) -> 0 | W61: =IFERROR(IF($F61+$G61=W$10,V61,(IF($F61=W$10,V61,(IF($F61>W$10," ",IF(W$10<$G61+$F61,SLN($E61,$H61,$G61)," "))))))," ") | X61: =IF($F61+$G61=X$10,($E61-$H61)/$G61/2,(IF($F61=X$10,($E61-$H61)/$G61/2,0))) -> 0 | Y61: =IFERROR(IF($F61+$G61=Y$10,X61,(IF($F61=Y$10,X61,(IF($F61>Y$10," ",IF(Y$10<$G61+$F61,SLN($E61,$H61,$G61)," "))))))," ") | Z61: =IF($F61+$G61=Z$10,($E61-$H61)/$G61/2,(IF($F61=Z$10,($E61-$H61)/$G61/2,0))) -> 0 | AA61: =IFERROR(IF($F61+$G61=AA$10,Z61,(IF($F61=AA$10,Z61,(IF($F61>AA$10," ",IF(AA$10<$G61+$F61,SLN($E61,$H61,$G61)," "))))))," ") | AB61: =IF($F61+$G61=AB$10,($E61-$H61)/$G61/2,(IF($F61=AB$10,($E61-$H61)/$G61/2,0))) -> 0 | AC61: =IFERROR(IF($F61+$G61=AC$10,AB61,(IF($F61=AC$10,AB61,(IF($F61>AC$10," ",IF(AC$10<$G61+$F61,SLN($E61,$H61,$G61)," "))))))," ") | AD61: =IF($F61+$G61=AD$10,($E61-$H61)/$G61/2,(IF($F61=AD$10,($E61-$H61)/$G61/2,0))) -> 0 | AE61: =IFERROR(IF($F61+$G61=AE$10,AD61,(IF($F61=AE$10,AD61,(IF($F61>AE$10," ",IF(AE$10<$G61+$F61,SLN($E61,$H61,$G61)," "))))))," ") | AF61: =IF($F61+$G61=AF$10,($E61-$H61)/$G61/2,(IF($F61=AF$10,($E61-$H61)/$G61/2,0))) -> 0 | AG61: =IFERROR(IF($F61+$G61=AG$10,AF61,(IF($F61=AG$10,AF61,(IF($F61>AG$10," ",IF(AG$10<$G61+$F61,SLN($E61,$H61,$G61)," "))))))," ") | AH61: =IF($F61+$G61=AH$10,($E61-$H61)/$G61/2,(IF($F61=AH$10,($E61-$H61)/$G61/2,0))) -> 0 | AI61: =IFERROR(IF($F61+$G61=AI$10,AH61,(IF($F61=AI$10,AH61,(IF($F61>AI$10," ",IF(AI$10<$G61+$F61,SLN($E61,$H61,$G61)," "))))))," ") | AJ61: =IF($F61+$G61=AJ$10,($E61-$H61)/$G61/2,(IF($F61=AJ$10,($E61-$H61)/$G61/2,0))) -> 0 | AK61: =IFERROR(IF($F61+$G61=AK$10,AJ61,(IF($F61=AK$10,AJ61,(IF($F61>AK$10," ",IF(AK$10<$G61+$F61,SLN($E61,$H61,$G61)," "))))))," ") | AL61: =IF($F61+$G61=AL$10,($E61-$H61)/$G61/2,(IF($F61=AL$10,($E61-$H61)/$G61/2,0))) -> 0 | AM61: =IFERROR(IF($F61+$G61=AM$10,AL61,(IF($F61=AM$10,AL61,(IF($F61>AM$10," ",IF(AM$10<$G61+$F61,SLN($E61,$H61,$G61)," "))))))," ") | AN61: =IF($F61+$G61=AN$10,($E61-$H61)/$G61/2,(IF($F61=AN$10,($E61-$H61)/$G61/2,0))) -> 0 | AO61: =IFERROR(IF($F61+$G61=AO$10,AN61,(IF($F61=AO$10,AN61,(IF($F61>AO$10," ",IF(AO$10<$G61+$F61,SLN($E61,$H61,$G61)," "))))))," ") | AP61: =IF($F61+$G61=AP$10,($E61-$H61)/$G61/2,(IF($F61=AP$10,($E61-$H61)/$G61/2,0))) -> 0 | AQ61: =IFERROR(IF($F61+$G61=AQ$10,AP61,(IF($F61=AQ$10,AP61,(IF($F61>AQ$10," ",IF(AQ$10<$G61+$F61,SLN($E61,$H61,$G61)," "))))))," ") | AR61: =IF($F61+$G61=AR$10,($E61-$H61)/$G61/2,(IF($F61=AR$10,($E61-$H61)/$G61/2,0))) -> 0 | AS61: =IFERROR(IF($F61+$G61=AS$10,AR61,(IF($F61=AS$10,AR61,(IF($F61>AS$10," ",IF(AS$10<$G61+$F61,SLN($E61,$H61,$G61)," "))))))," ") | AT61: =IF($F61+$G61=AT$10,($E61-$H61)/$G61/2,(IF($F61=AT$10,($E61-$H61)/$G61/2,0))) -> 0 | AU61: =IFERROR(IF($F61+$G61=AU$10,AT61,(IF($F61=AU$10,AT61,(IF($F61>AU$10," ",IF(AU$10<$G61+$F61,SLN($E61,$H61,$G61)," "))))))," ") | AV61: =IF($F61+$G61=AV$10,($E61-$H61)/$G61/2,(IF($F61=AV$10,($E61-$H61)/$G61/2,0))) -> 0 | AW61: =IFERROR(IF($F61+$G61=AW$10,AV61,(IF($F61=AW$10,AV61,(IF($F61>AW$10," ",IF(AW$10<$G61+$F61,SLN($E61,$H61,$G61)," "))))))," ")
I62: =IFERROR(IF(F62<$K$10,(($K$10-F62-1)*((E62-H62)/G62)+(((E62-H62)/G62)/2)),0),0) -> 0 | J62: =IF($F62+$G62=J$10,($E62-$H62)/$G62/2,(IF($F62=J$10,($E62-$H62)/$G62/2,0))) -> 0 | K62: =IFERROR(IF($F62+$G62=K$10,J62,(IF($F62=K$10,J62,(IF($F62>K$10," ",IF(K$10<$G62+$F62,SLN($E62,$H62,$G62)," "))))))," ") | L62: =IF($F62+$G62=L$10,($E62-$H62)/$G62/2,(IF($F62=L$10,($E62-$H62)/$G62/2,0))) -> 0 | M62: =IFERROR(IF($F62+$G62=M$10,L62,(IF($F62=M$10,L62,(IF($F62>M$10," ",IF(M$10<$G62+$F62,SLN($E62,$H62,$G62)," "))))))," ") | N62: =IF($F62+$G62=N$10,($E62-$H62)/$G62/2,(IF($F62=N$10,($E62-$H62)/$G62/2,0))) -> 0 | O62: =IFERROR(IF($F62+$G62=O$10,N62,(IF($F62=O$10,N62,(IF($F62>O$10," ",IF(O$10<$G62+$F62,SLN($E62,$H62,$G62)," "))))))," ") | P62: =IF($F62+$G62=P$10,($E62-$H62)/$G62/2,(IF($F62=P$10,($E62-$H62)/$G62/2,0))) -> 0 | Q62: =IFERROR(IF($F62+$G62=Q$10,P62,(IF($F62=Q$10,P62,(IF($F62>Q$10," ",IF(Q$10<$G62+$F62,SLN($E62,$H62,$G62)," "))))))," ") | R62: =IF($F62+$G62=R$10,($E62-$H62)/$G62/2,(IF($F62=R$10,($E62-$H62)/$G62/2,0))) -> 0 | S62: =IFERROR(IF($F62+$G62=S$10,R62,(IF($F62=S$10,R62,(IF($F62>S$10," ",IF(S$10<$G62+$F62,SLN($E62,$H62,$G62)," "))))))," ") | T62: =IF($F62+$G62=T$10,($E62-$H62)/$G62/2,(IF($F62=T$10,($E62-$H62)/$G62/2,0))) -> 0 | U62: =IFERROR(IF($F62+$G62=U$10,T62,(IF($F62=U$10,T62,(IF($F62>U$10," ",IF(U$10<$G62+$F62,SLN($E62,$H62,$G62)," "))))))," ") | V62: =IF($F62+$G62=V$10,($E62-$H62)/$G62/2,(IF($F62=V$10,($E62-$H62)/$G62/2,0))) -> 0 | W62: =IFERROR(IF($F62+$G62=W$10,V62,(IF($F62=W$10,V62,(IF($F62>W$10," ",IF(W$10<$G62+$F62,SLN($E62,$H62,$G62)," "))))))," ") | X62: =IF($F62+$G62=X$10,($E62-$H62)/$G62/2,(IF($F62=X$10,($E62-$H62)/$G62/2,0))) -> 0 | Y62: =IFERROR(IF($F62+$G62=Y$10,X62,(IF($F62=Y$10,X62,(IF($F62>Y$10," ",IF(Y$10<$G62+$F62,SLN($E62,$H62,$G62)," "))))))," ") | Z62: =IF($F62+$G62=Z$10,($E62-$H62)/$G62/2,(IF($F62=Z$10,($E62-$H62)/$G62/2,0))) -> 0 | AA62: =IFERROR(IF($F62+$G62=AA$10,Z62,(IF($F62=AA$10,Z62,(IF($F62>AA$10," ",IF(AA$10<$G62+$F62,SLN($E62,$H62,$G62)," "))))))," ") | AB62: =IF($F62+$G62=AB$10,($E62-$H62)/$G62/2,(IF($F62=AB$10,($E62-$H62)/$G62/2,0))) -> 0 | AC62: =IFERROR(IF($F62+$G62=AC$10,AB62,(IF($F62=AC$10,AB62,(IF($F62>AC$10," ",IF(AC$10<$G62+$F62,SLN($E62,$H62,$G62)," "))))))," ") | AD62: =IF($F62+$G62=AD$10,($E62-$H62)/$G62/2,(IF($F62=AD$10,($E62-$H62)/$G62/2,0))) -> 0 | AE62: =IFERROR(IF($F62+$G62=AE$10,AD62,(IF($F62=AE$10,AD62,(IF($F62>AE$10," ",IF(AE$10<$G62+$F62,SLN($E62,$H62,$G62)," "))))))," ") | AF62: =IF($F62+$G62=AF$10,($E62-$H62)/$G62/2,(IF($F62=AF$10,($E62-$H62)/$G62/2,0))) -> 0 | AG62: =IFERROR(IF($F62+$G62=AG$10,AF62,(IF($F62=AG$10,AF62,(IF($F62>AG$10," ",IF(AG$10<$G62+$F62,SLN($E62,$H62,$G62)," "))))))," ") | AH62: =IF($F62+$G62=AH$10,($E62-$H62)/$G62/2,(IF($F62=AH$10,($E62-$H62)/$G62/2,0))) -> 0 | AI62: =IFERROR(IF($F62+$G62=AI$10,AH62,(IF($F62=AI$10,AH62,(IF($F62>AI$10," ",IF(AI$10<$G62+$F62,SLN($E62,$H62,$G62)," "))))))," ") | AJ62: =IF($F62+$G62=AJ$10,($E62-$H62)/$G62/2,(IF($F62=AJ$10,($E62-$H62)/$G62/2,0))) -> 0 | AK62: =IFERROR(IF($F62+$G62=AK$10,AJ62,(IF($F62=AK$10,AJ62,(IF($F62>AK$10," ",IF(AK$10<$G62+$F62,SLN($E62,$H62,$G62)," "))))))," ") | AL62: =IF($F62+$G62=AL$10,($E62-$H62)/$G62/2,(IF($F62=AL$10,($E62-$H62)/$G62/2,0))) -> 0 | AM62: =IFERROR(IF($F62+$G62=AM$10,AL62,(IF($F62=AM$10,AL62,(IF($F62>AM$10," ",IF(AM$10<$G62+$F62,SLN($E62,$H62,$G62)," "))))))," ") | AN62: =IF($F62+$G62=AN$10,($E62-$H62)/$G62/2,(IF($F62=AN$10,($E62-$H62)/$G62/2,0))) -> 0 | AO62: =IFERROR(IF($F62+$G62=AO$10,AN62,(IF($F62=AO$10,AN62,(IF($F62>AO$10," ",IF(AO$10<$G62+$F62,SLN($E62,$H62,$G62)," "))))))," ") | AP62: =IF($F62+$G62=AP$10,($E62-$H62)/$G62/2,(IF($F62=AP$10,($E62-$H62)/$G62/2,0))) -> 0 | AQ62: =IFERROR(IF($F62+$G62=AQ$10,AP62,(IF($F62=AQ$10,AP62,(IF($F62>AQ$10," ",IF(AQ$10<$G62+$F62,SLN($E62,$H62,$G62)," "))))))," ") | AR62: =IF($F62+$G62=AR$10,($E62-$H62)/$G62/2,(IF($F62=AR$10,($E62-$H62)/$G62/2,0))) -> 0 | AS62: =IFERROR(IF($F62+$G62=AS$10,AR62,(IF($F62=AS$10,AR62,(IF($F62>AS$10," ",IF(AS$10<$G62+$F62,SLN($E62,$H62,$G62)," "))))))," ") | AT62: =IF($F62+$G62=AT$10,($E62-$H62)/$G62/2,(IF($F62=AT$10,($E62-$H62)/$G62/2,0))) -> 0 | AU62: =IFERROR(IF($F62+$G62=AU$10,AT62,(IF($F62=AU$10,AT62,(IF($F62>AU$10," ",IF(AU$10<$G62+$F62,SLN($E62,$H62,$G62)," "))))))," ") | AV62: =IF($F62+$G62=AV$10,($E62-$H62)/$G62/2,(IF($F62=AV$10,($E62-$H62)/$G62/2,0))) -> 0 | AW62: =IFERROR(IF($F62+$G62=AW$10,AV62,(IF($F62=AW$10,AV62,(IF($F62>AW$10," ",IF(AW$10<$G62+$F62,SLN($E62,$H62,$G62)," "))))))," ")
I63: =IFERROR(IF(F63<$K$10,(($K$10-F63-1)*((E63-H63)/G63)+(((E63-H63)/G63)/2)),0),0) -> 0 | J63: =IF($F63+$G63=J$10,($E63-$H63)/$G63/2,(IF($F63=J$10,($E63-$H63)/$G63/2,0))) -> 0 | K63: =IFERROR(IF($F63+$G63=K$10,J63,(IF($F63=K$10,J63,(IF($F63>K$10," ",IF(K$10<$G63+$F63,SLN($E63,$H63,$G63)," "))))))," ") | L63: =IF($F63+$G63=L$10,($E63-$H63)/$G63/2,(IF($F63=L$10,($E63-$H63)/$G63/2,0))) -> 0 | M63: =IFERROR(IF($F63+$G63=M$10,L63,(IF($F63=M$10,L63,(IF($F63>M$10," ",IF(M$10<$G63+$F63,SLN($E63,$H63,$G63)," "))))))," ") | N63: =IF($F63+$G63=N$10,($E63-$H63)/$G63/2,(IF($F63=N$10,($E63-$H63)/$G63/2,0))) -> 0 | O63: =IFERROR(IF($F63+$G63=O$10,N63,(IF($F63=O$10,N63,(IF($F63>O$10," ",IF(O$10<$G63+$F63,SLN($E63,$H63,$G63)," "))))))," ") | P63: =IF($F63+$G63=P$10,($E63-$H63)/$G63/2,(IF($F63=P$10,($E63-$H63)/$G63/2,0))) -> 0 | Q63: =IFERROR(IF($F63+$G63=Q$10,P63,(IF($F63=Q$10,P63,(IF($F63>Q$10," ",IF(Q$10<$G63+$F63,SLN($E63,$H63,$G63)," "))))))," ") | R63: =IF($F63+$G63=R$10,($E63-$H63)/$G63/2,(IF($F63=R$10,($E63-$H63)/$G63/2,0))) -> 0 | S63: =IFERROR(IF($F63+$G63=S$10,R63,(IF($F63=S$10,R63,(IF($F63>S$10," ",IF(S$10<$G63+$F63,SLN($E63,$H63,$G63)," "))))))," ") | T63: =IF($F63+$G63=T$10,($E63-$H63)/$G63/2,(IF($F63=T$10,($E63-$H63)/$G63/2,0))) -> 0 | U63: =IFERROR(IF($F63+$G63=U$10,T63,(IF($F63=U$10,T63,(IF($F63>U$10," ",IF(U$10<$G63+$F63,SLN($E63,$H63,$G63)," "))))))," ") | V63: =IF($F63+$G63=V$10,($E63-$H63)/$G63/2,(IF($F63=V$10,($E63-$H63)/$G63/2,0))) -> 0 | W63: =IFERROR(IF($F63+$G63=W$10,V63,(IF($F63=W$10,V63,(IF($F63>W$10," ",IF(W$10<$G63+$F63,SLN($E63,$H63,$G63)," "))))))," ") | X63: =IF($F63+$G63=X$10,($E63-$H63)/$G63/2,(IF($F63=X$10,($E63-$H63)/$G63/2,0))) -> 0 | Y63: =IFERROR(IF($F63+$G63=Y$10,X63,(IF($F63=Y$10,X63,(IF($F63>Y$10," ",IF(Y$10<$G63+$F63,SLN($E63,$H63,$G63)," "))))))," ") | Z63: =IF($F63+$G63=Z$10,($E63-$H63)/$G63/2,(IF($F63=Z$10,($E63-$H63)/$G63/2,0))) -> 0 | AA63: =IFERROR(IF($F63+$G63=AA$10,Z63,(IF($F63=AA$10,Z63,(IF($F63>AA$10," ",IF(AA$10<$G63+$F63,SLN($E63,$H63,$G63)," "))))))," ") | AB63: =IF($F63+$G63=AB$10,($E63-$H63)/$G63/2,(IF($F63=AB$10,($E63-$H63)/$G63/2,0))) -> 0 | AC63: =IFERROR(IF($F63+$G63=AC$10,AB63,(IF($F63=AC$10,AB63,(IF($F63>AC$10," ",IF(AC$10<$G63+$F63,SLN($E63,$H63,$G63)," "))))))," ") | AD63: =IF($F63+$G63=AD$10,($E63-$H63)/$G63/2,(IF($F63=AD$10,($E63-$H63)/$G63/2,0))) -> 0 | AE63: =IFERROR(IF($F63+$G63=AE$10,AD63,(IF($F63=AE$10,AD63,(IF($F63>AE$10," ",IF(AE$10<$G63+$F63,SLN($E63,$H63,$G63)," "))))))," ") | AF63: =IF($F63+$G63=AF$10,($E63-$H63)/$G63/2,(IF($F63=AF$10,($E63-$H63)/$G63/2,0))) -> 0 | AG63: =IFERROR(IF($F63+$G63=AG$10,AF63,(IF($F63=AG$10,AF63,(IF($F63>AG$10," ",IF(AG$10<$G63+$F63,SLN($E63,$H63,$G63)," "))))))," ") | AH63: =IF($F63+$G63=AH$10,($E63-$H63)/$G63/2,(IF($F63=AH$10,($E63-$H63)/$G63/2,0))) -> 0 | AI63: =IFERROR(IF($F63+$G63=AI$10,AH63,(IF($F63=AI$10,AH63,(IF($F63>AI$10," ",IF(AI$10<$G63+$F63,SLN($E63,$H63,$G63)," "))))))," ") | AJ63: =IF($F63+$G63=AJ$10,($E63-$H63)/$G63/2,(IF($F63=AJ$10,($E63-$H63)/$G63/2,0))) -> 0 | AK63: =IFERROR(IF($F63+$G63=AK$10,AJ63,(IF($F63=AK$10,AJ63,(IF($F63>AK$10," ",IF(AK$10<$G63+$F63,SLN($E63,$H63,$G63)," "))))))," ") | AL63: =IF($F63+$G63=AL$10,($E63-$H63)/$G63/2,(IF($F63=AL$10,($E63-$H63)/$G63/2,0))) -> 0 | AM63: =IFERROR(IF($F63+$G63=AM$10,AL63,(IF($F63=AM$10,AL63,(IF($F63>AM$10," ",IF(AM$10<$G63+$F63,SLN($E63,$H63,$G63)," "))))))," ") | AN63: =IF($F63+$G63=AN$10,($E63-$H63)/$G63/2,(IF($F63=AN$10,($E63-$H63)/$G63/2,0))) -> 0 | AO63: =IFERROR(IF($F63+$G63=AO$10,AN63,(IF($F63=AO$10,AN63,(IF($F63>AO$10," ",IF(AO$10<$G63+$F63,SLN($E63,$H63,$G63)," "))))))," ") | AP63: =IF($F63+$G63=AP$10,($E63-$H63)/$G63/2,(IF($F63=AP$10,($E63-$H63)/$G63/2,0))) -> 0 | AQ63: =IFERROR(IF($F63+$G63=AQ$10,AP63,(IF($F63=AQ$10,AP63,(IF($F63>AQ$10," ",IF(AQ$10<$G63+$F63,SLN($E63,$H63,$G63)," "))))))," ") | AR63: =IF($F63+$G63=AR$10,($E63-$H63)/$G63/2,(IF($F63=AR$10,($E63-$H63)/$G63/2,0))) -> 0 | AS63: =IFERROR(IF($F63+$G63=AS$10,AR63,(IF($F63=AS$10,AR63,(IF($F63>AS$10," ",IF(AS$10<$G63+$F63,SLN($E63,$H63,$G63)," "))))))," ") | AT63: =IF($F63+$G63=AT$10,($E63-$H63)/$G63/2,(IF($F63=AT$10,($E63-$H63)/$G63/2,0))) -> 0 | AU63: =IFERROR(IF($F63+$G63=AU$10,AT63,(IF($F63=AU$10,AT63,(IF($F63>AU$10," ",IF(AU$10<$G63+$F63,SLN($E63,$H63,$G63)," "))))))," ") | AV63: =IF($F63+$G63=AV$10,($E63-$H63)/$G63/2,(IF($F63=AV$10,($E63-$H63)/$G63/2,0))) -> 0 | AW63: =IFERROR(IF($F63+$G63=AW$10,AV63,(IF($F63=AW$10,AV63,(IF($F63>AW$10," ",IF(AW$10<$G63+$F63,SLN($E63,$H63,$G63)," "))))))," ")
I64: =IFERROR(IF(F64<$K$10,(($K$10-F64-1)*((E64-H64)/G64)+(((E64-H64)/G64)/2)),0),0) -> 0 | J64: =IF($F64+$G64=J$10,($E64-$H64)/$G64/2,(IF($F64=J$10,($E64-$H64)/$G64/2,0))) -> 0 | K64: =IFERROR(IF($F64+$G64=K$10,J64,(IF($F64=K$10,J64,(IF($F64>K$10," ",IF(K$10<$G64+$F64,SLN($E64,$H64,$G64)," "))))))," ") | L64: =IF($F64+$G64=L$10,($E64-$H64)/$G64/2,(IF($F64=L$10,($E64-$H64)/$G64/2,0))) -> 0 | M64: =IFERROR(IF($F64+$G64=M$10,L64,(IF($F64=M$10,L64,(IF($F64>M$10," ",IF(M$10<$G64+$F64,SLN($E64,$H64,$G64)," "))))))," ") | N64: =IF($F64+$G64=N$10,($E64-$H64)/$G64/2,(IF($F64=N$10,($E64-$H64)/$G64/2,0))) -> 0 | O64: =IFERROR(IF($F64+$G64=O$10,N64,(IF($F64=O$10,N64,(IF($F64>O$10," ",IF(O$10<$G64+$F64,SLN($E64,$H64,$G64)," "))))))," ") | P64: =IF($F64+$G64=P$10,($E64-$H64)/$G64/2,(IF($F64=P$10,($E64-$H64)/$G64/2,0))) -> 0 | Q64: =IFERROR(IF($F64+$G64=Q$10,P64,(IF($F64=Q$10,P64,(IF($F64>Q$10," ",IF(Q$10<$G64+$F64,SLN($E64,$H64,$G64)," "))))))," ") | R64: =IF($F64+$G64=R$10,($E64-$H64)/$G64/2,(IF($F64=R$10,($E64-$H64)/$G64/2,0))) -> 0 | S64: =IFERROR(IF($F64+$G64=S$10,R64,(IF($F64=S$10,R64,(IF($F64>S$10," ",IF(S$10<$G64+$F64,SLN($E64,$H64,$G64)," "))))))," ") | T64: =IF($F64+$G64=T$10,($E64-$H64)/$G64/2,(IF($F64=T$10,($E64-$H64)/$G64/2,0))) -> 0 | U64: =IFERROR(IF($F64+$G64=U$10,T64,(IF($F64=U$10,T64,(IF($F64>U$10," ",IF(U$10<$G64+$F64,SLN($E64,$H64,$G64)," "))))))," ") | V64: =IF($F64+$G64=V$10,($E64-$H64)/$G64/2,(IF($F64=V$10,($E64-$H64)/$G64/2,0))) -> 0 | W64: =IFERROR(IF($F64+$G64=W$10,V64,(IF($F64=W$10,V64,(IF($F64>W$10," ",IF(W$10<$G64+$F64,SLN($E64,$H64,$G64)," "))))))," ") | X64: =IF($F64+$G64=X$10,($E64-$H64)/$G64/2,(IF($F64=X$10,($E64-$H64)/$G64/2,0))) -> 0 | Y64: =IFERROR(IF($F64+$G64=Y$10,X64,(IF($F64=Y$10,X64,(IF($F64>Y$10," ",IF(Y$10<$G64+$F64,SLN($E64,$H64,$G64)," "))))))," ") | Z64: =IF($F64+$G64=Z$10,($E64-$H64)/$G64/2,(IF($F64=Z$10,($E64-$H64)/$G64/2,0))) -> 0 | AA64: =IFERROR(IF($F64+$G64=AA$10,Z64,(IF($F64=AA$10,Z64,(IF($F64>AA$10," ",IF(AA$10<$G64+$F64,SLN($E64,$H64,$G64)," "))))))," ") | AB64: =IF($F64+$G64=AB$10,($E64-$H64)/$G64/2,(IF($F64=AB$10,($E64-$H64)/$G64/2,0))) -> 0 | AC64: =IFERROR(IF($F64+$G64=AC$10,AB64,(IF($F64=AC$10,AB64,(IF($F64>AC$10," ",IF(AC$10<$G64+$F64,SLN($E64,$H64,$G64)," "))))))," ") | AD64: =IF($F64+$G64=AD$10,($E64-$H64)/$G64/2,(IF($F64=AD$10,($E64-$H64)/$G64/2,0))) -> 0 | AE64: =IFERROR(IF($F64+$G64=AE$10,AD64,(IF($F64=AE$10,AD64,(IF($F64>AE$10," ",IF(AE$10<$G64+$F64,SLN($E64,$H64,$G64)," "))))))," ") | AF64: =IF($F64+$G64=AF$10,($E64-$H64)/$G64/2,(IF($F64=AF$10,($E64-$H64)/$G64/2,0))) -> 0 | AG64: =IFERROR(IF($F64+$G64=AG$10,AF64,(IF($F64=AG$10,AF64,(IF($F64>AG$10," ",IF(AG$10<$G64+$F64,SLN($E64,$H64,$G64)," "))))))," ") | AH64: =IF($F64+$G64=AH$10,($E64-$H64)/$G64/2,(IF($F64=AH$10,($E64-$H64)/$G64/2,0))) -> 0 | AI64: =IFERROR(IF($F64+$G64=AI$10,AH64,(IF($F64=AI$10,AH64,(IF($F64>AI$10," ",IF(AI$10<$G64+$F64,SLN($E64,$H64,$G64)," "))))))," ") | AJ64: =IF($F64+$G64=AJ$10,($E64-$H64)/$G64/2,(IF($F64=AJ$10,($E64-$H64)/$G64/2,0))) -> 0 | AK64: =IFERROR(IF($F64+$G64=AK$10,AJ64,(IF($F64=AK$10,AJ64,(IF($F64>AK$10," ",IF(AK$10<$G64+$F64,SLN($E64,$H64,$G64)," "))))))," ") | AL64: =IF($F64+$G64=AL$10,($E64-$H64)/$G64/2,(IF($F64=AL$10,($E64-$H64)/$G64/2,0))) -> 0 | AM64: =IFERROR(IF($F64+$G64=AM$10,AL64,(IF($F64=AM$10,AL64,(IF($F64>AM$10," ",IF(AM$10<$G64+$F64,SLN($E64,$H64,$G64)," "))))))," ") | AN64: =IF($F64+$G64=AN$10,($E64-$H64)/$G64/2,(IF($F64=AN$10,($E64-$H64)/$G64/2,0))) -> 0 | AO64: =IFERROR(IF($F64+$G64=AO$10,AN64,(IF($F64=AO$10,AN64,(IF($F64>AO$10," ",IF(AO$10<$G64+$F64,SLN($E64,$H64,$G64)," "))))))," ") | AP64: =IF($F64+$G64=AP$10,($E64-$H64)/$G64/2,(IF($F64=AP$10,($E64-$H64)/$G64/2,0))) -> 0 | AQ64: =IFERROR(IF($F64+$G64=AQ$10,AP64,(IF($F64=AQ$10,AP64,(IF($F64>AQ$10," ",IF(AQ$10<$G64+$F64,SLN($E64,$H64,$G64)," "))))))," ") | AR64: =IF($F64+$G64=AR$10,($E64-$H64)/$G64/2,(IF($F64=AR$10,($E64-$H64)/$G64/2,0))) -> 0 | AS64: =IFERROR(IF($F64+$G64=AS$10,AR64,(IF($F64=AS$10,AR64,(IF($F64>AS$10," ",IF(AS$10<$G64+$F64,SLN($E64,$H64,$G64)," "))))))," ") | AT64: =IF($F64+$G64=AT$10,($E64-$H64)/$G64/2,(IF($F64=AT$10,($E64-$H64)/$G64/2,0))) -> 0 | AU64: =IFERROR(IF($F64+$G64=AU$10,AT64,(IF($F64=AU$10,AT64,(IF($F64>AU$10," ",IF(AU$10<$G64+$F64,SLN($E64,$H64,$G64)," "))))))," ") | AV64: =IF($F64+$G64=AV$10,($E64-$H64)/$G64/2,(IF($F64=AV$10,($E64-$H64)/$G64/2,0))) -> 0 | AW64: =IFERROR(IF($F64+$G64=AW$10,AV64,(IF($F64=AW$10,AV64,(IF($F64>AW$10," ",IF(AW$10<$G64+$F64,SLN($E64,$H64,$G64)," "))))))," ")
I65: =IFERROR(IF(F65<$K$10,(($K$10-F65-1)*((E65-H65)/G65)+(((E65-H65)/G65)/2)),0),0) -> 0 | J65: =IF($F65+$G65=J$10,($E65-$H65)/$G65/2,(IF($F65=J$10,($E65-$H65)/$G65/2,0))) -> 0 | K65: =IFERROR(IF($F65+$G65=K$10,J65,(IF($F65=K$10,J65,(IF($F65>K$10," ",IF(K$10<$G65+$F65,SLN($E65,$H65,$G65)," "))))))," ") | L65: =IF($F65+$G65=L$10,($E65-$H65)/$G65/2,(IF($F65=L$10,($E65-$H65)/$G65/2,0))) -> 0 | M65: =IFERROR(IF($F65+$G65=M$10,L65,(IF($F65=M$10,L65,(IF($F65>M$10," ",IF(M$10<$G65+$F65,SLN($E65,$H65,$G65)," "))))))," ") | N65: =IF($F65+$G65=N$10,($E65-$H65)/$G65/2,(IF($F65=N$10,($E65-$H65)/$G65/2,0))) -> 0 | O65: =IFERROR(IF($F65+$G65=O$10,N65,(IF($F65=O$10,N65,(IF($F65>O$10," ",IF(O$10<$G65+$F65,SLN($E65,$H65,$G65)," "))))))," ") | P65: =IF($F65+$G65=P$10,($E65-$H65)/$G65/2,(IF($F65=P$10,($E65-$H65)/$G65/2,0))) -> 0 | Q65: =IFERROR(IF($F65+$G65=Q$10,P65,(IF($F65=Q$10,P65,(IF($F65>Q$10," ",IF(Q$10<$G65+$F65,SLN($E65,$H65,$G65)," "))))))," ") | R65: =IF($F65+$G65=R$10,($E65-$H65)/$G65/2,(IF($F65=R$10,($E65-$H65)/$G65/2,0))) -> 0 | S65: =IFERROR(IF($F65+$G65=S$10,R65,(IF($F65=S$10,R65,(IF($F65>S$10," ",IF(S$10<$G65+$F65,SLN($E65,$H65,$G65)," "))))))," ") | T65: =IF($F65+$G65=T$10,($E65-$H65)/$G65/2,(IF($F65=T$10,($E65-$H65)/$G65/2,0))) -> 0 | U65: =IFERROR(IF($F65+$G65=U$10,T65,(IF($F65=U$10,T65,(IF($F65>U$10," ",IF(U$10<$G65+$F65,SLN($E65,$H65,$G65)," "))))))," ") | V65: =IF($F65+$G65=V$10,($E65-$H65)/$G65/2,(IF($F65=V$10,($E65-$H65)/$G65/2,0))) -> 0 | W65: =IFERROR(IF($F65+$G65=W$10,V65,(IF($F65=W$10,V65,(IF($F65>W$10," ",IF(W$10<$G65+$F65,SLN($E65,$H65,$G65)," "))))))," ") | X65: =IF($F65+$G65=X$10,($E65-$H65)/$G65/2,(IF($F65=X$10,($E65-$H65)/$G65/2,0))) -> 0 | Y65: =IFERROR(IF($F65+$G65=Y$10,X65,(IF($F65=Y$10,X65,(IF($F65>Y$10," ",IF(Y$10<$G65+$F65,SLN($E65,$H65,$G65)," "))))))," ") | Z65: =IF($F65+$G65=Z$10,($E65-$H65)/$G65/2,(IF($F65=Z$10,($E65-$H65)/$G65/2,0))) -> 0 | AA65: =IFERROR(IF($F65+$G65=AA$10,Z65,(IF($F65=AA$10,Z65,(IF($F65>AA$10," ",IF(AA$10<$G65+$F65,SLN($E65,$H65,$G65)," "))))))," ") | AB65: =IF($F65+$G65=AB$10,($E65-$H65)/$G65/2,(IF($F65=AB$10,($E65-$H65)/$G65/2,0))) -> 0 | AC65: =IFERROR(IF($F65+$G65=AC$10,AB65,(IF($F65=AC$10,AB65,(IF($F65>AC$10," ",IF(AC$10<$G65+$F65,SLN($E65,$H65,$G65)," "))))))," ") | AD65: =IF($F65+$G65=AD$10,($E65-$H65)/$G65/2,(IF($F65=AD$10,($E65-$H65)/$G65/2,0))) -> 0 | AE65: =IFERROR(IF($F65+$G65=AE$10,AD65,(IF($F65=AE$10,AD65,(IF($F65>AE$10," ",IF(AE$10<$G65+$F65,SLN($E65,$H65,$G65)," "))))))," ") | AF65: =IF($F65+$G65=AF$10,($E65-$H65)/$G65/2,(IF($F65=AF$10,($E65-$H65)/$G65/2,0))) -> 0 | AG65: =IFERROR(IF($F65+$G65=AG$10,AF65,(IF($F65=AG$10,AF65,(IF($F65>AG$10," ",IF(AG$10<$G65+$F65,SLN($E65,$H65,$G65)," "))))))," ") | AH65: =IF($F65+$G65=AH$10,($E65-$H65)/$G65/2,(IF($F65=AH$10,($E65-$H65)/$G65/2,0))) -> 0 | AI65: =IFERROR(IF($F65+$G65=AI$10,AH65,(IF($F65=AI$10,AH65,(IF($F65>AI$10," ",IF(AI$10<$G65+$F65,SLN($E65,$H65,$G65)," "))))))," ") | AJ65: =IF($F65+$G65=AJ$10,($E65-$H65)/$G65/2,(IF($F65=AJ$10,($E65-$H65)/$G65/2,0))) -> 0 | AK65: =IFERROR(IF($F65+$G65=AK$10,AJ65,(IF($F65=AK$10,AJ65,(IF($F65>AK$10," ",IF(AK$10<$G65+$F65,SLN($E65,$H65,$G65)," "))))))," ") | AL65: =IF($F65+$G65=AL$10,($E65-$H65)/$G65/2,(IF($F65=AL$10,($E65-$H65)/$G65/2,0))) -> 0 | AM65: =IFERROR(IF($F65+$G65=AM$10,AL65,(IF($F65=AM$10,AL65,(IF($F65>AM$10," ",IF(AM$10<$G65+$F65,SLN($E65,$H65,$G65)," "))))))," ") | AN65: =IF($F65+$G65=AN$10,($E65-$H65)/$G65/2,(IF($F65=AN$10,($E65-$H65)/$G65/2,0))) -> 0 | AO65: =IFERROR(IF($F65+$G65=AO$10,AN65,(IF($F65=AO$10,AN65,(IF($F65>AO$10," ",IF(AO$10<$G65+$F65,SLN($E65,$H65,$G65)," "))))))," ") | AP65: =IF($F65+$G65=AP$10,($E65-$H65)/$G65/2,(IF($F65=AP$10,($E65-$H65)/$G65/2,0))) -> 0 | AQ65: =IFERROR(IF($F65+$G65=AQ$10,AP65,(IF($F65=AQ$10,AP65,(IF($F65>AQ$10," ",IF(AQ$10<$G65+$F65,SLN($E65,$H65,$G65)," "))))))," ") | AR65: =IF($F65+$G65=AR$10,($E65-$H65)/$G65/2,(IF($F65=AR$10,($E65-$H65)/$G65/2,0))) -> 0 | AS65: =IFERROR(IF($F65+$G65=AS$10,AR65,(IF($F65=AS$10,AR65,(IF($F65>AS$10," ",IF(AS$10<$G65+$F65,SLN($E65,$H65,$G65)," "))))))," ") | AT65: =IF($F65+$G65=AT$10,($E65-$H65)/$G65/2,(IF($F65=AT$10,($E65-$H65)/$G65/2,0))) -> 0 | AU65: =IFERROR(IF($F65+$G65=AU$10,AT65,(IF($F65=AU$10,AT65,(IF($F65>AU$10," ",IF(AU$10<$G65+$F65,SLN($E65,$H65,$G65)," "))))))," ") | AV65: =IF($F65+$G65=AV$10,($E65-$H65)/$G65/2,(IF($F65=AV$10,($E65-$H65)/$G65/2,0))) -> 0 | AW65: =IFERROR(IF($F65+$G65=AW$10,AV65,(IF($F65=AW$10,AV65,(IF($F65>AW$10," ",IF(AW$10<$G65+$F65,SLN($E65,$H65,$G65)," "))))))," ")
I66: =IFERROR(IF(F66<$K$10,(($K$10-F66-1)*((E66-H66)/G66)+(((E66-H66)/G66)/2)),0),0) -> 0 | J66: =IF($F66+$G66=J$10,($E66-$H66)/$G66/2,(IF($F66=J$10,($E66-$H66)/$G66/2,0))) -> 0 | K66: =IFERROR(IF($F66+$G66=K$10,J66,(IF($F66=K$10,J66,(IF($F66>K$10," ",IF(K$10<$G66+$F66,SLN($E66,$H66,$G66)," "))))))," ") | L66: =IF($F66+$G66=L$10,($E66-$H66)/$G66/2,(IF($F66=L$10,($E66-$H66)/$G66/2,0))) -> 0 | M66: =IFERROR(IF($F66+$G66=M$10,L66,(IF($F66=M$10,L66,(IF($F66>M$10," ",IF(M$10<$G66+$F66,SLN($E66,$H66,$G66)," "))))))," ") | N66: =IF($F66+$G66=N$10,($E66-$H66)/$G66/2,(IF($F66=N$10,($E66-$H66)/$G66/2,0))) -> 0 | O66: =IFERROR(IF($F66+$G66=O$10,N66,(IF($F66=O$10,N66,(IF($F66>O$10," ",IF(O$10<$G66+$F66,SLN($E66,$H66,$G66)," "))))))," ") | P66: =IF($F66+$G66=P$10,($E66-$H66)/$G66/2,(IF($F66=P$10,($E66-$H66)/$G66/2,0))) -> 0 | Q66: =IFERROR(IF($F66+$G66=Q$10,P66,(IF($F66=Q$10,P66,(IF($F66>Q$10," ",IF(Q$10<$G66+$F66,SLN($E66,$H66,$G66)," "))))))," ") | R66: =IF($F66+$G66=R$10,($E66-$H66)/$G66/2,(IF($F66=R$10,($E66-$H66)/$G66/2,0))) -> 0 | S66: =IFERROR(IF($F66+$G66=S$10,R66,(IF($F66=S$10,R66,(IF($F66>S$10," ",IF(S$10<$G66+$F66,SLN($E66,$H66,$G66)," "))))))," ") | T66: =IF($F66+$G66=T$10,($E66-$H66)/$G66/2,(IF($F66=T$10,($E66-$H66)/$G66/2,0))) -> 0 | U66: =IFERROR(IF($F66+$G66=U$10,T66,(IF($F66=U$10,T66,(IF($F66>U$10," ",IF(U$10<$G66+$F66,SLN($E66,$H66,$G66)," "))))))," ") | V66: =IF($F66+$G66=V$10,($E66-$H66)/$G66/2,(IF($F66=V$10,($E66-$H66)/$G66/2,0))) -> 0 | W66: =IFERROR(IF($F66+$G66=W$10,V66,(IF($F66=W$10,V66,(IF($F66>W$10," ",IF(W$10<$G66+$F66,SLN($E66,$H66,$G66)," "))))))," ") | X66: =IF($F66+$G66=X$10,($E66-$H66)/$G66/2,(IF($F66=X$10,($E66-$H66)/$G66/2,0))) -> 0 | Y66: =IFERROR(IF($F66+$G66=Y$10,X66,(IF($F66=Y$10,X66,(IF($F66>Y$10," ",IF(Y$10<$G66+$F66,SLN($E66,$H66,$G66)," "))))))," ") | Z66: =IF($F66+$G66=Z$10,($E66-$H66)/$G66/2,(IF($F66=Z$10,($E66-$H66)/$G66/2,0))) -> 0 | AA66: =IFERROR(IF($F66+$G66=AA$10,Z66,(IF($F66=AA$10,Z66,(IF($F66>AA$10," ",IF(AA$10<$G66+$F66,SLN($E66,$H66,$G66)," "))))))," ") | AB66: =IF($F66+$G66=AB$10,($E66-$H66)/$G66/2,(IF($F66=AB$10,($E66-$H66)/$G66/2,0))) -> 0 | AC66: =IFERROR(IF($F66+$G66=AC$10,AB66,(IF($F66=AC$10,AB66,(IF($F66>AC$10," ",IF(AC$10<$G66+$F66,SLN($E66,$H66,$G66)," "))))))," ") | AD66: =IF($F66+$G66=AD$10,($E66-$H66)/$G66/2,(IF($F66=AD$10,($E66-$H66)/$G66/2,0))) -> 0 | AE66: =IFERROR(IF($F66+$G66=AE$10,AD66,(IF($F66=AE$10,AD66,(IF($F66>AE$10," ",IF(AE$10<$G66+$F66,SLN($E66,$H66,$G66)," "))))))," ") | AF66: =IF($F66+$G66=AF$10,($E66-$H66)/$G66/2,(IF($F66=AF$10,($E66-$H66)/$G66/2,0))) -> 0 | AG66: =IFERROR(IF($F66+$G66=AG$10,AF66,(IF($F66=AG$10,AF66,(IF($F66>AG$10," ",IF(AG$10<$G66+$F66,SLN($E66,$H66,$G66)," "))))))," ") | AH66: =IF($F66+$G66=AH$10,($E66-$H66)/$G66/2,(IF($F66=AH$10,($E66-$H66)/$G66/2,0))) -> 0 | AI66: =IFERROR(IF($F66+$G66=AI$10,AH66,(IF($F66=AI$10,AH66,(IF($F66>AI$10," ",IF(AI$10<$G66+$F66,SLN($E66,$H66,$G66)," "))))))," ") | AJ66: =IF($F66+$G66=AJ$10,($E66-$H66)/$G66/2,(IF($F66=AJ$10,($E66-$H66)/$G66/2,0))) -> 0 | AK66: =IFERROR(IF($F66+$G66=AK$10,AJ66,(IF($F66=AK$10,AJ66,(IF($F66>AK$10," ",IF(AK$10<$G66+$F66,SLN($E66,$H66,$G66)," "))))))," ") | AL66: =IF($F66+$G66=AL$10,($E66-$H66)/$G66/2,(IF($F66=AL$10,($E66-$H66)/$G66/2,0))) -> 0 | AM66: =IFERROR(IF($F66+$G66=AM$10,AL66,(IF($F66=AM$10,AL66,(IF($F66>AM$10," ",IF(AM$10<$G66+$F66,SLN($E66,$H66,$G66)," "))))))," ") | AN66: =IF($F66+$G66=AN$10,($E66-$H66)/$G66/2,(IF($F66=AN$10,($E66-$H66)/$G66/2,0))) -> 0 | AO66: =IFERROR(IF($F66+$G66=AO$10,AN66,(IF($F66=AO$10,AN66,(IF($F66>AO$10," ",IF(AO$10<$G66+$F66,SLN($E66,$H66,$G66)," "))))))," ") | AP66: =IF($F66+$G66=AP$10,($E66-$H66)/$G66/2,(IF($F66=AP$10,($E66-$H66)/$G66/2,0))) -> 0 | AQ66: =IFERROR(IF($F66+$G66=AQ$10,AP66,(IF($F66=AQ$10,AP66,(IF($F66>AQ$10," ",IF(AQ$10<$G66+$F66,SLN($E66,$H66,$G66)," "))))))," ") | AR66: =IF($F66+$G66=AR$10,($E66-$H66)/$G66/2,(IF($F66=AR$10,($E66-$H66)/$G66/2,0))) -> 0 | AS66: =IFERROR(IF($F66+$G66=AS$10,AR66,(IF($F66=AS$10,AR66,(IF($F66>AS$10," ",IF(AS$10<$G66+$F66,SLN($E66,$H66,$G66)," "))))))," ") | AT66: =IF($F66+$G66=AT$10,($E66-$H66)/$G66/2,(IF($F66=AT$10,($E66-$H66)/$G66/2,0))) -> 0 | AU66: =IFERROR(IF($F66+$G66=AU$10,AT66,(IF($F66=AU$10,AT66,(IF($F66>AU$10," ",IF(AU$10<$G66+$F66,SLN($E66,$H66,$G66)," "))))))," ") | AV66: =IF($F66+$G66=AV$10,($E66-$H66)/$G66/2,(IF($F66=AV$10,($E66-$H66)/$G66/2,0))) -> 0 | AW66: =IFERROR(IF($F66+$G66=AW$10,AV66,(IF($F66=AW$10,AV66,(IF($F66>AW$10," ",IF(AW$10<$G66+$F66,SLN($E66,$H66,$G66)," "))))))," ")
I67: =IFERROR(IF(F67<$K$10,(($K$10-F67-1)*((E67-H67)/G67)+(((E67-H67)/G67)/2)),0),0) -> 0 | J67: =IF($F67+$G67=J$10,($E67-$H67)/$G67/2,(IF($F67=J$10,($E67-$H67)/$G67/2,0))) -> 0 | K67: =IFERROR(IF($F67+$G67=K$10,J67,(IF($F67=K$10,J67,(IF($F67>K$10," ",IF(K$10<$G67+$F67,SLN($E67,$H67,$G67)," "))))))," ") | L67: =IF($F67+$G67=L$10,($E67-$H67)/$G67/2,(IF($F67=L$10,($E67-$H67)/$G67/2,0))) -> 0 | M67: =IFERROR(IF($F67+$G67=M$10,L67,(IF($F67=M$10,L67,(IF($F67>M$10," ",IF(M$10<$G67+$F67,SLN($E67,$H67,$G67)," "))))))," ") | N67: =IF($F67+$G67=N$10,($E67-$H67)/$G67/2,(IF($F67=N$10,($E67-$H67)/$G67/2,0))) -> 0 | O67: =IFERROR(IF($F67+$G67=O$10,N67,(IF($F67=O$10,N67,(IF($F67>O$10," ",IF(O$10<$G67+$F67,SLN($E67,$H67,$G67)," "))))))," ") | P67: =IF($F67+$G67=P$10,($E67-$H67)/$G67/2,(IF($F67=P$10,($E67-$H67)/$G67/2,0))) -> 0 | Q67: =IFERROR(IF($F67+$G67=Q$10,P67,(IF($F67=Q$10,P67,(IF($F67>Q$10," ",IF(Q$10<$G67+$F67,SLN($E67,$H67,$G67)," "))))))," ") | R67: =IF($F67+$G67=R$10,($E67-$H67)/$G67/2,(IF($F67=R$10,($E67-$H67)/$G67/2,0))) -> 0 | S67: =IFERROR(IF($F67+$G67=S$10,R67,(IF($F67=S$10,R67,(IF($F67>S$10," ",IF(S$10<$G67+$F67,SLN($E67,$H67,$G67)," "))))))," ") | T67: =IF($F67+$G67=T$10,($E67-$H67)/$G67/2,(IF($F67=T$10,($E67-$H67)/$G67/2,0))) -> 0 | U67: =IFERROR(IF($F67+$G67=U$10,T67,(IF($F67=U$10,T67,(IF($F67>U$10," ",IF(U$10<$G67+$F67,SLN($E67,$H67,$G67)," "))))))," ") | V67: =IF($F67+$G67=V$10,($E67-$H67)/$G67/2,(IF($F67=V$10,($E67-$H67)/$G67/2,0))) -> 0 | W67: =IFERROR(IF($F67+$G67=W$10,V67,(IF($F67=W$10,V67,(IF($F67>W$10," ",IF(W$10<$G67+$F67,SLN($E67,$H67,$G67)," "))))))," ") | X67: =IF($F67+$G67=X$10,($E67-$H67)/$G67/2,(IF($F67=X$10,($E67-$H67)/$G67/2,0))) -> 0 | Y67: =IFERROR(IF($F67+$G67=Y$10,X67,(IF($F67=Y$10,X67,(IF($F67>Y$10," ",IF(Y$10<$G67+$F67,SLN($E67,$H67,$G67)," "))))))," ") | Z67: =IF($F67+$G67=Z$10,($E67-$H67)/$G67/2,(IF($F67=Z$10,($E67-$H67)/$G67/2,0))) -> 0 | AA67: =IFERROR(IF($F67+$G67=AA$10,Z67,(IF($F67=AA$10,Z67,(IF($F67>AA$10," ",IF(AA$10<$G67+$F67,SLN($E67,$H67,$G67)," "))))))," ") | AB67: =IF($F67+$G67=AB$10,($E67-$H67)/$G67/2,(IF($F67=AB$10,($E67-$H67)/$G67/2,0))) -> 0 | AC67: =IFERROR(IF($F67+$G67=AC$10,AB67,(IF($F67=AC$10,AB67,(IF($F67>AC$10," ",IF(AC$10<$G67+$F67,SLN($E67,$H67,$G67)," "))))))," ") | AD67: =IF($F67+$G67=AD$10,($E67-$H67)/$G67/2,(IF($F67=AD$10,($E67-$H67)/$G67/2,0))) -> 0 | AE67: =IFERROR(IF($F67+$G67=AE$10,AD67,(IF($F67=AE$10,AD67,(IF($F67>AE$10," ",IF(AE$10<$G67+$F67,SLN($E67,$H67,$G67)," "))))))," ") | AF67: =IF($F67+$G67=AF$10,($E67-$H67)/$G67/2,(IF($F67=AF$10,($E67-$H67)/$G67/2,0))) -> 0 | AG67: =IFERROR(IF($F67+$G67=AG$10,AF67,(IF($F67=AG$10,AF67,(IF($F67>AG$10," ",IF(AG$10<$G67+$F67,SLN($E67,$H67,$G67)," "))))))," ") | AH67: =IF($F67+$G67=AH$10,($E67-$H67)/$G67/2,(IF($F67=AH$10,($E67-$H67)/$G67/2,0))) -> 0 | AI67: =IFERROR(IF($F67+$G67=AI$10,AH67,(IF($F67=AI$10,AH67,(IF($F67>AI$10," ",IF(AI$10<$G67+$F67,SLN($E67,$H67,$G67)," "))))))," ") | AJ67: =IF($F67+$G67=AJ$10,($E67-$H67)/$G67/2,(IF($F67=AJ$10,($E67-$H67)/$G67/2,0))) -> 0 | AK67: =IFERROR(IF($F67+$G67=AK$10,AJ67,(IF($F67=AK$10,AJ67,(IF($F67>AK$10," ",IF(AK$10<$G67+$F67,SLN($E67,$H67,$G67)," "))))))," ") | AL67: =IF($F67+$G67=AL$10,($E67-$H67)/$G67/2,(IF($F67=AL$10,($E67-$H67)/$G67/2,0))) -> 0 | AM67: =IFERROR(IF($F67+$G67=AM$10,AL67,(IF($F67=AM$10,AL67,(IF($F67>AM$10," ",IF(AM$10<$G67+$F67,SLN($E67,$H67,$G67)," "))))))," ") | AN67: =IF($F67+$G67=AN$10,($E67-$H67)/$G67/2,(IF($F67=AN$10,($E67-$H67)/$G67/2,0))) -> 0 | AO67: =IFERROR(IF($F67+$G67=AO$10,AN67,(IF($F67=AO$10,AN67,(IF($F67>AO$10," ",IF(AO$10<$G67+$F67,SLN($E67,$H67,$G67)," "))))))," ") | AP67: =IF($F67+$G67=AP$10,($E67-$H67)/$G67/2,(IF($F67=AP$10,($E67-$H67)/$G67/2,0))) -> 0 | AQ67: =IFERROR(IF($F67+$G67=AQ$10,AP67,(IF($F67=AQ$10,AP67,(IF($F67>AQ$10," ",IF(AQ$10<$G67+$F67,SLN($E67,$H67,$G67)," "))))))," ") | AR67: =IF($F67+$G67=AR$10,($E67-$H67)/$G67/2,(IF($F67=AR$10,($E67-$H67)/$G67/2,0))) -> 0 | AS67: =IFERROR(IF($F67+$G67=AS$10,AR67,(IF($F67=AS$10,AR67,(IF($F67>AS$10," ",IF(AS$10<$G67+$F67,SLN($E67,$H67,$G67)," "))))))," ") | AT67: =IF($F67+$G67=AT$10,($E67-$H67)/$G67/2,(IF($F67=AT$10,($E67-$H67)/$G67/2,0))) -> 0 | AU67: =IFERROR(IF($F67+$G67=AU$10,AT67,(IF($F67=AU$10,AT67,(IF($F67>AU$10," ",IF(AU$10<$G67+$F67,SLN($E67,$H67,$G67)," "))))))," ") | AV67: =IF($F67+$G67=AV$10,($E67-$H67)/$G67/2,(IF($F67=AV$10,($E67-$H67)/$G67/2,0))) -> 0 | AW67: =IFERROR(IF($F67+$G67=AW$10,AV67,(IF($F67=AW$10,AV67,(IF($F67>AW$10," ",IF(AW$10<$G67+$F67,SLN($E67,$H67,$G67)," "))))))," ")
... I70: =IFERROR(IF(F70<$K$10,(($K$10-F70-1)*((E70-H70)/G70)+(((E70-H70)/G70)/2)),0),0) -> 0 | J70: =IF($F70+$G70=J$10,($E70-$H70)/$G70/2,(IF($F70=J$10,($E70-$H70)/$G70/2,0))) -> 0 | K70: =IFERROR(IF($F70+$G70=K$10,J70,(IF($F70=K$10,J70,(IF($F70>K$10," ",IF(K$10<$G70+$F70,SLN($E70,$H70,$G70)," "))))))," ") | L70: =IF($F70+$G70=L$10,($E70-$H70)/$G70/2,(IF($F70=L$10,($E70-$H70)/$G70/2,0))) -> 0 | M70: =IFERROR(IF($F70+$G70=M$10,L70,(IF($F70=M$10,L70,(IF($F70>M$10," ",IF(M$10<$G70+$F70,SLN($E70,$H70,$G70)," "))))))," ") | N70: =IF($F70+$G70=N$10,($E70-$H70)/$G70/2,(IF($F70=N$10,($E70-$H70)/$G70/2,0))) -> 0 | O70: =IFERROR(IF($F70+$G70=O$10,N70,(IF($F70=O$10,N70,(IF($F70>O$10," ",IF(O$10<$G70+$F70,SLN($E70,$H70,$G70)," "))))))," ") | P70: =IF($F70+$G70=P$10,($E70-$H70)/$G70/2,(IF($F70=P$10,($E70-$H70)/$G70/2,0))) -> 0 | Q70: =IFERROR(IF($F70+$G70=Q$10,P70,(IF($F70=Q$10,P70,(IF($F70>Q$10," ",IF(Q$10<$G70+$F70,SLN($E70,$H70,$G70)," "))))))," ") | R70: =IF($F70+$G70=R$10,($E70-$H70)/$G70/2,(IF($F70=R$10,($E70-$H70)/$G70/2,0))) -> 0 | S70: =IFERROR(IF($F70+$G70=S$10,R70,(IF($F70=S$10,R70,(IF($F70>S$10," ",IF(S$10<$G70+$F70,SLN($E70,$H70,$G70)," "))))))," ") | T70: =IF($F70+$G70=T$10,($E70-$H70)/$G70/2,(IF($F70=T$10,($E70-$H70)/$G70/2,0))) -> 0 | U70: =IFERROR(IF($F70+$G70=U$10,T70,(IF($F70=U$10,T70,(IF($F70>U$10," ",IF(U$10<$G70+$F70,SLN($E70,$H70,$G70)," "))))))," ") | V70: =IF($F70+$G70=V$10,($E70-$H70)/$G70/2,(IF($F70=V$10,($E70-$H70)/$G70/2,0))) -> 0 | W70: =IFERROR(IF($F70+$G70=W$10,V70,(IF($F70=W$10,V70,(IF($F70>W$10," ",IF(W$10<$G70+$F70,SLN($E70,$H70,$G70)," "))))))," ") | X70: =IF($F70+$G70=X$10,($E70-$H70)/$G70/2,(IF($F70=X$10,($E70-$H70)/$G70/2,0))) -> 0 | Y70: =IFERROR(IF($F70+$G70=Y$10,X70,(IF($F70=Y$10,X70,(IF($F70>Y$10," ",IF(Y$10<$G70+$F70,SLN($E70,$H70,$G70)," "))))))," ") | Z70: =IF($F70+$G70=Z$10,($E70-$H70)/$G70/2,(IF($F70=Z$10,($E70-$H70)/$G70/2,0))) -> 0 | AA70: =IFERROR(IF($F70+$G70=AA$10,Z70,(IF($F70=AA$10,Z70,(IF($F70>AA$10," ",IF(AA$10<$G70+$F70,SLN($E70,$H70,$G70)," "))))))," ") | AB70: =IF($F70+$G70=AB$10,($E70-$H70)/$G70/2,(IF($F70=AB$10,($E70-$H70)/$G70/2,0))) -> 0 | AC70: =IFERROR(IF($F70+$G70=AC$10,AB70,(IF($F70=AC$10,AB70,(IF($F70>AC$10," ",IF(AC$10<$G70+$F70,SLN($E70,$H70,$G70)," "))))))," ") | AD70: =IF($F70+$G70=AD$10,($E70-$H70)/$G70/2,(IF($F70=AD$10,($E70-$H70)/$G70/2,0))) -> 0 | AE70: =IFERROR(IF($F70+$G70=AE$10,AD70,(IF($F70=AE$10,AD70,(IF($F70>AE$10," ",IF(AE$10<$G70+$F70,SLN($E70,$H70,$G70)," "))))))," ") | AF70: =IF($F70+$G70=AF$10,($E70-$H70)/$G70/2,(IF($F70=AF$10,($E70-$H70)/$G70/2,0))) -> 0 | AG70: =IFERROR(IF($F70+$G70=AG$10,AF70,(IF($F70=AG$10,AF70,(IF($F70>AG$10," ",IF(AG$10<$G70+$F70,SLN($E70,$H70,$G70)," "))))))," ") | AH70: =IF($F70+$G70=AH$10,($E70-$H70)/$G70/2,(IF($F70=AH$10,($E70-$H70)/$G70/2,0))) -> 0 | AI70: =IFERROR(IF($F70+$G70=AI$10,AH70,(IF($F70=AI$10,AH70,(IF($F70>AI$10," ",IF(AI$10<$G70+$F70,SLN($E70,$H70,$G70)," "))))))," ") | AJ70: =IF($F70+$G70=AJ$10,($E70-$H70)/$G70/2,(IF($F70=AJ$10,($E70-$H70)/$G70/2,0))) -> 0 | AK70: =IFERROR(IF($F70+$G70=AK$10,AJ70,(IF($F70=AK$10,AJ70,(IF($F70>AK$10," ",IF(AK$10<$G70+$F70,SLN($E70,$H70,$G70)," "))))))," ") | AL70: =IF($F70+$G70=AL$10,($E70-$H70)/$G70/2,(IF($F70=AL$10,($E70-$H70)/$G70/2,0))) -> 0 | AM70: =IFERROR(IF($F70+$G70=AM$10,AL70,(IF($F70=AM$10,AL70,(IF($F70>AM$10," ",IF(AM$10<$G70+$F70,SLN($E70,$H70,$G70)," "))))))," ") | AN70: =IF($F70+$G70=AN$10,($E70-$H70)/$G70/2,(IF($F70=AN$10,($E70-$H70)/$G70/2,0))) -> 0 | AO70: =IFERROR(IF($F70+$G70=AO$10,AN70,(IF($F70=AO$10,AN70,(IF($F70>AO$10," ",IF(AO$10<$G70+$F70,SLN($E70,$H70,$G70)," "))))))," ") | AP70: =IF($F70+$G70=AP$10,($E70-$H70)/$G70/2,(IF($F70=AP$10,($E70-$H70)/$G70/2,0))) -> 0 | AQ70: =IFERROR(IF($F70+$G70=AQ$10,AP70,(IF($F70=AQ$10,AP70,(IF($F70>AQ$10," ",IF(AQ$10<$G70+$F70,SLN($E70,$H70,$G70)," "))))))," ") | AR70: =IF($F70+$G70=AR$10,($E70-$H70)/$G70/2,(IF($F70=AR$10,($E70-$H70)/$G70/2,0))) -> 0 | AS70: =IFERROR(IF($F70+$G70=AS$10,AR70,(IF($F70=AS$10,AR70,(IF($F70>AS$10," ",IF(AS$10<$G70+$F70,SLN($E70,$H70,$G70)," "))))))," ") | AT70: =IF($F70+$G70=AT$10,($E70-$H70)/$G70/2,(IF($F70=AT$10,($E70-$H70)/$G70/2,0))) -> 0 | AU70: =IFERROR(IF($F70+$G70=AU$10,AT70,(IF($F70=AU$10,AT70,(IF($F70>AU$10," ",IF(AU$10<$G70+$F70,SLN($E70,$H70,$G70)," "))))))," ") | AV70: =IF($F70+$G70=AV$10,($E70-$H70)/$G70/2,(IF($F70=AV$10,($E70-$H70)/$G70/2,0))) -> 0 | AW70: =IFERROR(IF($F70+$G70=AW$10,AV70,(IF($F70=AW$10,AV70,(IF($F70>AW$10," ",IF(AW$10<$G70+$F70,SLN($E70,$H70,$G70)," "))))))," ")
A71: ANNUAL TOTAL | I71: =SUM(I11:I70) -> 0 | K71: =SUM(K11:K70) -> 0 | M71: =SUM(M11:M70) -> 0 | O71: =SUM(O11:O70) -> 0 | Q71: =SUM(Q11:Q70) -> 0 | S71: =SUM(S11:S70) -> 0 | U71: =SUM(U11:U70) -> 0 | W71: =SUM(W11:W70) -> 0 | Y71: =SUM(Y11:Y70) -> 0 | AA71: =SUM(AA11:AA70) -> 0 | AC71: =SUM(AC11:AC70) -> 0 | AE71: =SUM(AE11:AE70) -> 0 | AG71: =SUM(AG11:AG70) -> 0 | AI71: =SUM(AI11:AI70) -> 0 | AK71: =SUM(AK11:AK70) -> 0 | AM71: =SUM(AM11:AM70) -> 0 | AO71: =SUM(AO11:AO70) -> 0 | AQ71: =SUM(AQ11:AQ70) -> 0 | AR71: =SUM(AR11:AR70) -> #VALUE! | AS71: =SUM(AS11:AS70) -> 0 | AT71: =SUM(AT11:AT70) -> #VALUE! | AU71: =SUM(AU11:AU70) -> 0 | AV71: =SUM(AV11:AV70) -> #VALUE! | AW71: =SUM(AW11:AW70) -> 0

Sheet o_Transaction
A1: PostingDate | B1: TransactionDate | C1: InstrumentId | D1: TransactionName | E1: =IF(AND(D1<>"",'Depreciation Schedule'!BD10=""),0,'Depreciation Schedule'!BD10) -> Amount | F1: AttributeId
A2: ='Depreciation Schedule'!AY11 | B2: ='Depreciation Schedule'!AZ11 | C2: ='Depreciation Schedule'!BA11 | D2: ='Depreciation Schedule'!BC11 | E2: =IF(AND('Depreciation Schedule'!A11<>"",'Depreciation Schedule'!BD11=" "),0,'Depreciation Schedule'!BD11) -> #N/A | F2: ='Depreciation Schedule'!BB11
A3: ='Depreciation Schedule'!AY12 | B3: ='Depreciation Schedule'!AZ12 | C3: ='Depreciation Schedule'!BA12 | D3: ='Depreciation Schedule'!BC12 | E3: =IF(AND('Depreciation Schedule'!A12<>"",'Depreciation Schedule'!BD12=" "),0,'Depreciation Schedule'!BD12) -> #N/A | F3: ='Depreciation Schedule'!BB12
A4: ='Depreciation Schedule'!AY13 | B4: ='Depreciation Schedule'!AZ13 | C4: ='Depreciation Schedule'!BA13 | D4: ='Depreciation Schedule'!BC13 | E4: =IF(AND('Depreciation Schedule'!A13<>"",'Depreciation Schedule'!BD13=" "),0,'Depreciation Schedule'!BD13) -> #N/A | F4: ='Depreciation Schedule'!BB13
A5: ='Depreciation Schedule'!AY14 | B5: ='Depreciation Schedule'!AZ14 | C5: ='Depreciation Schedule'!BA14 | D5: ='Depreciation Schedule'!BC14 | E5: =IF(AND('Depreciation Schedule'!A14<>"",'Depreciation Schedule'!BD14=" "),0,'Depreciation Schedule'!BD14) -> #N/A | F5: ='Depreciation Schedule'!BB14
A6: ='Depreciation Schedule'!AY15 | B6: ='Depreciation Schedule'!AZ15 | C6: ='Depreciation Schedule'!BA15 | D6: ='Depreciation Schedule'!BC15 | E6: =IF(AND('Depreciation Schedule'!A15<>"",'Depreciation Schedule'!BD15=" "),0,'Depreciation Schedule'!BD15) -> #N/A | F6: ='Depreciation Schedule'!BB15
A7: ='Depreciation Schedule'!AY16 | B7: ='Depreciation Schedule'!AZ16 | C7: ='Depreciation Schedule'!BA16 | D7: ='Depreciation Schedule'!BC16 | E7: =IF(AND('Depreciation Schedule'!A16<>"",'Depreciation Schedule'!BD16=" "),0,'Depreciation Schedule'!BD16) -> #N/A | F7: ='Depreciation Schedule'!BB16
A8: ='Depreciation Schedule'!AY17 | B8: ='Depreciation Schedule'!AZ17 | C8: ='Depreciation Schedule'!BA17 | D8: ='Depreciation Schedule'!BC17 | E8: =IF(AND('Depreciation Schedule'!A17<>"",'Depreciation Schedule'!BD17=" "),0,'Depreciation Schedule'!BD17) -> #N/A | F8: ='Depreciation Schedule'!BB17
A9: ='Depreciation Schedule'!AY18 | B9: ='Depreciation Schedule'!AZ18 | C9: ='Depreciation Schedule'!BA18 | D9: ='Depreciation Schedule'!BC18 | E9: =IF(AND('Depreciation Schedule'!A18<>"",'Depreciation Schedule'!BD18=" "),0,'Depreciation Schedule'!BD18) -> #N/A | F9: ='Depreciation Schedule'!BB18
A10: ='Depreciation Schedule'!AY19 | B10: ='Depreciation Schedule'!AZ19 | C10: ='Depreciation Schedule'!BA19 | D10: ='Depreciation Schedule'!BC19 | E10: =IF(AND('Depreciation Schedule'!A19<>"",'Depreciation Schedule'!BD19=" "),0,'Depreciation Schedule'!BD19) -> #N/A | F10: ='Depreciation Schedule'!BB19
A11: ='Depreciation Schedule'!AY20 | B11: ='Depreciation Schedule'!AZ20 | C11: ='Depreciation Schedule'!BA20 | D11: ='Depreciation Schedule'!BC20 | E11: =IF(AND('Depreciation Schedule'!A20<>"",'Depreciation Schedule'!BD20=" "),0,'Depreciation Schedule'!BD20) -> #N/A | F11: ='Depreciation Schedule'!BB20
A12: ='Depreciation Schedule'!AY21 | B12: ='Depreciation Schedule'!AZ21 | C12: ='Depreciation Schedule'!BA21 | D12: ='Depreciation Schedule'!BC21 | E12: =IF(AND('Depreciation Schedule'!A21<>"",'Depreciation Schedule'!BD21=" "),0,'Depreciation Schedule'!BD21) -> #N/A | F12: ='Depreciation Schedule'!BB21
A13: ='Depreciation Schedule'!AY22 | B13: ='Depreciation Schedule'!AZ22 | C13: ='Depreciation Schedule'!BA22 | D13: ='Depreciation Schedule'!BC22 | E13: =IF(AND('Depreciation Schedule'!A22<>"",'Depreciation Schedule'!BD22=" "),0,'Depreciation Schedule'!BD22) -> #N/A | F13: ='Depreciation Schedule'!BB22
... A46: ='Depreciation Schedule'!AY55 | B46: ='Depreciation Schedule'!AZ55 | C46: ='Depreciation Schedule'!BA55 | D46: ='Depreciation Schedule'!BC55 | E46: =IF(AND('Depreciation Schedule'!A55<>"",'Depreciation Schedule'!BD55=" "),0,'Depreciation Schedule'!BD55) -> #N/A | F46: ='Depreciation Schedule'!BB55
