Workbook
Name Fund1: #REF!
Name Payment: #REF!

Sheet PO
A1: PostingDate | B1: EffectiveDate | C1: InstrumentId | D1: AttributeId | E1: TRANSACTIONS_AMOUNT_PAYOFF_UPB | F1: TRANSACTIONS_AMOUNT_PAYOFF_INTEREST

Sheet PMT
A1: PostingDate | B1: EffectiveDate | C1: InstrumentId | D1: AttributeId | E1: TRANSACTIONS_AMOUNT_PAYMENT_PRINCIPAL

Sheet EOD
A1: PostingDate | B1: EffectiveDate | C1: InstrumentId | D1: AttributeId | E1: BALANCES_ENDINGBALANCE_UPB | F1: BALANCES_ENDINGBALANCE_AIR | G1: ATTRIBUTE_ORIGINATION_DATE_CURRENT | H1: ATTRIBUTE_ACCRUAL_METHOD_CURRENT | I1: ATTRIBUTE_INTEREST_RATE_CURRENT

Sheet Calculation
A1: Balance | B1: Amount | D1: PostingDate | E1: EffectiveDate | F1: TransactionName | G1: Amount
A2: UPB Balance | B2: =EOD!E2 -> 0 | D2: =$B$12 -> 45688 | E2: =IF(PO!E2="","",PO!B2) | F2: PayOff-UPB | G2: =-PO!E2 -> 0
A3: AIR Balance | B3: =EOD!F2 -> 0 | D3: =$B$12 -> 45688 | E3: =IF(PO!E2="","",PO!B2) | F3: PayOff-Interest | G3: =-PO!F2 -> 0
A4: Origination Date | B4: =EOD!G2 -> 0 | D4: =$B$12 -> 45688 | E4: =IF(PMT!E2="","",PMT!B2) | F4: Payment-Principal | G4: =-PMT!E2 -> 0
A5: Accrual Method | B5: =EOD!H2 -> 0
A6: InterestRate | B6: =EOD!I2 -> 0
A7: LoanId | B7: =IF(EOD!C2="","",EOD!C2)
A8: Attributeid | B8: =EOD!D2 -> 0
A11: PriorExecutionDate | B11: =DATE(YEAR(B12), MONTH(B12), 0) -> 45657
A12: ExecutionDate | B12: 45688
A13: Method | B13: =IF(B5="PIK",B5,"")
A14: =COLUMN(A15) -> 1 | B14: =COLUMN(B15) -> 2 | C14: =COLUMN(C15) -> 3 | D14: =COLUMN(D15) -> 4 | E14: =COLUMN(E15) -> 5 | F14: =COLUMN(F15) -> 6 | G14: =COLUMN(G15) -> 7 | H14: =COLUMN(H15) -> 8 | ... AC14: =COLUMN(AC15) -> 29
A15: Loan | B15: Settlement Date | C15: Interest Rate | D15: Prin Bal 12/31 | E15: Int Accru Bal 12/31 | F15: Payoff Date | G15: Paydown Date | H15: Capitalization Date | I15: PayOff Day | J15: Days Before Paydpwn | K15: Days After Paydown | L15: Days before Capitalization | M15: Days After Capitalization/Payoff | N15: Days After Capitalization & Before Paydown | O15: Per Day Interest Rate | P15: Additional Jan Interest Accrued (Before PIK) | Q15: Jan Interest Capitalized | R15: Principal Balance After Capitalization | S15: Principal Paydown | T15: Additional Jan Interest Accrued (After PIK) | U15: Total Additional Jan Interest Accrued | V15: Total Payoff | W15: Interest paid allocated from prin pymt | X15: Interest paid in Jan | Y15: Total Interest Received | Z15: Interest Adjustment | AA15: Prin Bal 1/31 | AB15: Int Bal 1/31
A16: =IF(B13<>"PIK","",B7) | B16: =IF(B13<>"PIK","",B4) | C16: =IF(B13<>"PIK","",B6) | D16: =IF(B13<>"PIK","",B2) | E16: =IF(B13<>"PIK","",B3) | F16: =IF(B13<>"PIK","",IF(E2=0,"",E2)) | G16: =IF(B13<>"PIK","",IF(E4=0,"",E4)) | H16: =IF(B13<>"PIK","",DATE( YEAR(B16), MONTH(B16)+ IF( ((YEAR($B$12)-YEAR(B16))*12+(MONTH($B$12)-MONTH(B16))---(DAY($B$12)<DAY(B16)))=0, 1, (YEAR($B$12)-YEAR(B16))*12+(MONTH($B$12)-MONTH(B16))---(DAY($B$12)<DAY(B16)) ), DAY(B16) )) | I16: =IF(B13<>"PIK","",IF(F16="","",DAY(F16-1))) | J16: =IF(B13<>"PIK","",IFERROR(DAY(G16-1),"")) | K16: =IF(B13<>"PIK","",IFERROR(DAY($B$12)-J16,"")) | L16: =IF(B13<>"PIK","",IF((H16-$B$11)-1>31,($B$12-B16)+1,(H16-$B$11)-1)) | M16: =IF(B13<>"PIK","",IF((H16-$B$11)-1>31,"",IF(F16<>"",IF(I16>L16,ABS(L16-I16)-1,0),$B$12-H16)+1)) | N16: =IF(B13<>"PIK","",IFERROR(J16-L16,"")) | O16: =IF(B13<>"PIK","",C16/36500) | P16: =IF(B13<>"PIK","",(O16*D16)*MIN(L16,I16)) | Q16: =IF(B13<>"PIK","",IF(OR(L16>I16,(H16-$B$11)-1>31),0,(E16+P16))) | R16: =IF(B13<>"PIK","",IF(L16>I16,0,(D16+Q16))) | S16: =IF(B13<>"PIK","",G4) | T16: =IF(B13<>"PIK","",IFERROR(IF(G16="",(R16*O16)*M16,((R16*O16)*N16)+(((R16-S16)*O16)*K16)),)) | U16: =IF(B13<>"PIK","",P16+T16) | V16: =IF(B13<>"PIK","",G2+G3) | W16: =IF(B13<>"PIK","",G3) | X16: =IF(B13<>"PIK","",0) | Y16: =IF(B13<>"PIK","",W16+X16) | Z16: =IF(B13<>"PIK","",IF(W16=0,0,-(E16+U16-Q16-W16))) | AA16: =IF(B13<>"PIK","",D16-S16+Q16-(V16-W16)) | AB16: =IF(B13<>"PIK","",E16+U16-Q16-W16+Z16)
C18: Loanid | D18: =A16 | K18: Loanid | L18: =A35
C19: Conversion_Principal | D19: =VLOOKUP($D$18,$A$16:$AB$16,D14,FALSE) | K19: Conversion_Principal | L19: =VLOOKUP($L$18,$A$35:$AC$35,D33,FALSE)
C20: Conversion_Interest | D20: =VLOOKUP($D$18,$A$16:$AB$16,E14,FALSE) | K20: Conversion_Interest | L20: =VLOOKUP($L$18,$A$35:$AC$35,E33,FALSE)
C21: Interest_Accrual | D21: =VLOOKUP($D$18,$A$16:$AB$16,U14,FALSE) | G21: Balance Checker | K21: Interest_Accrual | L21: =VLOOKUP($L$18,$A$35:$AC$35,Q33,FALSE) | O21: Balance Checker
C22: PayOff_UPB | D22: =IFERROR(-(VLOOKUP($D$18,$A$16:$AB$16,V14,FALSE)-VLOOKUP($D$18,$A$16:$AB$16,W14,FALSE)),"") | G22: UPB | H22: Interest | K22: PayOff_UPB | L22: =IFERROR(-(VLOOKUP($L$18,$A$35:$AC$35,T14,FALSE)-VLOOKUP($L$18,$A$35:$AC$35,U14,FALSE)),"") | O22: UPB | P22: Interest
C23: PayOff_Interest | D23: =IFERROR(-(VLOOKUP($D$18,$A$16:$AB$16,W14,FALSE)),"") | G23: =IFERROR(D19+D22+D26+D27,"") | H23: =IFERROR(D20+D21+D23+D24+D25,"") | K23: PayOff_Interest | L23: =IFERROR(-VLOOKUP($L$18,$A$35:$AC$35,U33,FALSE),"") | O23: =IFERROR(L19+L22+L25,"") | P23: =IFERROR(L20+L21+L23+L24,"")
C24: PayOff_InterestAdj | D24: =VLOOKUP($D$18,$A$16:$AB$16,Z14,FALSE) | G24: =VLOOKUP($D$18,$A$16:$AB$16,AA14,FALSE) | H24: =VLOOKUP($D$18,$A$16:$AB$16,AB14,FALSE) | K24: PayOff_InterestAdj | L24: =VLOOKUP($L$18,$A$35:$AC$35,X33,FALSE) | O24: =VLOOKUP($L$18,$A$35:$AC$35,Z33,FALSE) | P24: =VLOOKUP($L$18,$A$35:$AC$35,AA33,FALSE)
C25: Capitalized_Interest | D25: =IFERROR(-(VLOOKUP($D$18,$A$16:$AB$16,Q14,FALSE)),"") | G25: =IFERROR(G24-G23,"") | H25: =IFERROR(H24-H23,"") | K25: Payment_Principal | L25: =IFERROR(-VLOOKUP($L$18,$A$35:$AC$35,S33,FALSE),"") | O25: =IFERROR(O24-O23,"") | P25: =IFERROR(P24-P23,"")
C26: Capitalized_Principal | D26: =VLOOKUP($D$18,$A$16:$AB$16,Q14,FALSE)
C27: Payment_Principal | D27: =IFERROR(-VLOOKUP($D$18,$A$16:$AB$16,S14,FALSE),"")
A30: PriorExecutionDate | B30: =B11 -> 45657
A31: ExecutionDate | B31: =B12 -> 45688
A32: Method | B32: =IF(B5="ACCRUAL",B5,"")
A33: =COLUMN(A34) -> 1 | B33: =COLUMN(B34) -> 2 | C33: =COLUMN(C34) -> 3 | D33: =COLUMN(D34) -> 4 | E33: =COLUMN(E34) -> 5 | F33: =COLUMN(F34) -> 6 | G33: =COLUMN(G34) -> 7 | H33: =COLUMN(H34) -> 8 | ... AA33: =COLUMN(AA34) -> 27
A34: Loan | B34: Settlement Date | C34: Interest Rate | D34: Prin Bal 12/31 | E34: Int Accru Bal 12/31 | F34: Month End days | G34: Days Before Payoff | H34: Days Before Paydown | I34: Days On Boarding | J34: Per day Interest rate | K34: Paydown Date | L34: Payoff Date | M34: Total Jan Interest Accrued Plain | N34: Total Jan Interest Accrued Payoff | O34: Total Jan Interest Accrued Paydown | P34: Total Jan Interest Accrued Boarding | Q34: Total Accrued Interest | R34: Principal Disbursement | S34: Principal Paydown | T34: Total Payoff | U34: Interest paid allocated from prin pymt | V34: Interest paid in Jan | W34: Total Interest Received | X34: Interest Adjustment | Y34: Total Interest Earned | Z34: Prin Bal 1/31 | AA34: Int Accru Bal 1/31
A35: =IF(B32<>"ACCRUAL","",B7) | B35: =IF(B32<>"ACCRUAL","",B4) | C35: =IF(B32<>"ACCRUAL","",B6) | D35: =IF(B32<>"ACCRUAL","",B2) | E35: =IF(B32<>"ACCRUAL","",B3) | F35: =IF(B32<>"ACCRUAL","",DAY($B$31)) | G35: =IF(B32<>"ACCRUAL","",IF(L35="",0,(L35-$B$30)-1)) | H35: =IF(B32<>"ACCRUAL","",IF(K35="",0,(K35-$B$30)-1)) | I35: =IF(B32<>"ACCRUAL","",IF( ((YEAR($B$31)-YEAR(B35))*12+(MONTH($B$31)-MONTH(B35))---(DAY($B$31)<DAY(B35)))=0, $B$31-B35+1, 0 )) | J35: =IF(B32<>"ACCRUAL","",C35/36500) | K35: =IF(B32<>"ACCRUAL","",IF(E4=0,"",E4)) | L35: =IF(B32<>"ACCRUAL","",IF(E2=0,"",E2)) | M35: =IF(B32<>"ACCRUAL","",IF( AND( L35="", K35="", ((YEAR($B$31)-YEAR(B35))*12+(MONTH($B$31)-MONTH(B35))---(DAY($B$31)<DAY(B35)))<>0 ), ((J35-S35)*D35)*F35, 0 )) | N35: =IF(B32<>"ACCRUAL","",((J35*D35)*G35)) | O35: =IF(B32<>"ACCRUAL","",IF(K35="",0,((D35*J35)*H35)+(((D35-S35)*J35)*(F35-H35)))) | P35: =IF(B32<>"ACCRUAL","",IF( ((YEAR($B$31)-YEAR(B35))*12+(MONTH($B$31)-MONTH(B35))---(DAY($B$31)<DAY(B35)))=0, (D35*J35)*I35, 0 )) | Q35: =IF(B32<>"ACCRUAL","",M35+N35+O35+P35) | R35: 0 | S35: =IF(B32<>"ACCRUAL","",G4) | T35: =IF(B32<>"ACCRUAL","",G2+G3) | U35: =IF(B32<>"ACCRUAL","",G3) | V35: =IF(B32<>"ACCRUAL","",0) | W35: =IF(B32<>"ACCRUAL","",U35+V35) | X35: =IF(B32<>"ACCRUAL","",IF(W35=0,0,-(E35+Q35-W35))) | Y35: =IF(B32<>"ACCRUAL","",X35+Q35) | Z35: =IF(B32<>"ACCRUAL","",D35-S35-(T35-U35)) | AA35: =IF(B32<>"ACCRUAL","",E35+Q35-W35+X35)
A37: TRANSACTIONS
A38: PostingDate | B38: TransactionDate | C38: InstrumentId | D38: Transactiontype | E38: Amount | F38: AttributeId
A39: =IF($B$7="","",$B$12) | B39: =IF($B$7="","",$A$39) | C39: =IF($B$7="","",$B$7) | D39: =IF($B$7="","","INTEREST_ACCRUAL") | E39: =IF($B$7="","",IF(B5="PIK",ROUND(D21,4),ROUND(L21,4))) | F39: =IF($B$7="","",$B$8)
A40: =IF($B$7="","",$B$12) | B40: =IF($B$7="","",$A$39) | C40: =IF($B$7="","",$B$7) | D40: =IF($B$7="","","PAYOFF_INTERESTADJ") | E40: =IF($B$7="","",IF(B5="PIK",ROUND(D24,4),ROUND(L24,4))) | F40: =IF($B$7="","",$B$8)
A41: =IF($B$7="","",$B$12) | B41: =IF($B$7="","",$A$39) | C41: =IF($B$7="","",$B$7) | D41: =IF($B$7="","","CAPITALIZED_INTEREST") | E41: =IF($B$7="","",IF(B5="PIK",ROUND(D25,4),0)) | F41: =IF($B$7="","",$B$8)
A42: =IF($B$7="","",$B$12) | B42: =IF($B$7="","",$A$39) | C42: =IF($B$7="","",$B$7) | D42: =IF($B$7="","","CAPITALIZED_PRINCIPAL") | E42: =IF($B$7="","",IF(B5="PIK",ROUND(D26,4),0)) | F42: =IF($B$7="","",$B$8)

Sheet o_Transaction
A1: PostingDate | B1: TransactionDate | C1: InstrumentId | D1: TransactionName | E1: Amount | F1: AttributeId
A2: =Calculation!A39 | B2: =Calculation!B39 | C2: =Calculation!C39 | D2: =Calculation!D39 | E2: =Calculation!E39 | F2: =Calculation!F39
A3: =Calculation!A40 | B3: =Calculation!B40 | C3: =Calculation!C40 | D3: =Calculation!D40 | E3: =Calculation!E40 | F3: =Calculation!F40
A4: =Calculation!A41 | B4: =Calculation!B41 | C4: =Calculation!C41 | D4: =Calculation!D41 | E4: =Calculation!E41 | F4: =Calculation!F41
A5: =Calculation!A42 | B5: =Calculation!B42 | C5: =Calculation!C42 | D5: =Calculation!D42 | E5: =Calculation!E42 | F5: =Calculation!F42
